Workbook
Name ____: #REF!
Name ______________________________qw1101: #REF!
Name ______________________________qw1102: #REF!
Name ______________________________qw1103: #REF!
Name ______________________________qw1104: #REF!
Name ______________________________qw1201: #REF!
Name ______________________________qw1202: #REF!
Name ______________________________qw1203: #REF!
Name ______________________________qw1204: #REF!
Name ______________________________qw1301: #REF!
Name ______________________________qw1302: #REF!
Name ______________________________qw1303: #REF!
Name ______________________________qw1304: #REF!
Name ______________________________qw1305: #REF!
Name ______________________________qw1306: #REF!
Name ______________________________qw1307: #REF!
Name ______________________________qw1308: #REF!
Name ______________________________qw1411: #REF!
Name ______________________________qw1412: #REF!
Name ______________________________qw1421: #REF!
Name ______________________________qw1422: #REF!
Name ______________________________qw1423: #REF!
Name ______________________________qw1501: #REF!
Name ______________________________qw1502: #REF!
Name ______________________________qw2111: #REF!
Name ______________________________qw2112: #REF!
Name ______________________________qw2113: #REF!
Name ______________________________qw2114: #REF!
Name ______________________________qw2115: #REF!
Name ______________________________qw2116: #REF!
Name ______________________________qw2121: #REF!
Name ______________________________qw2211: #REF!
Name ______________________________qw2221: #REF!
Name ______________________________qw2222: #REF!
Name ______________________________qw2301: #REF!
Name ______________________________qw2302: #REF!
Name ______________________________qw2401: #REF!
Name ______________________________qw2901: #REF!
Name ______________________________qw3101: #REF!
Name ______________________________qw3102: #REF!
Name ______________________________qw3201: #REF!
Name ______________________________qw3301: #REF!
Name ______________________________qw3401: #REF!
Name ______________________________qw3402: #REF!
Name ______________________________qw3403: #REF!
Name ______________________________qw3501: #REF!
Name ______________________________qw3502: #REF!
Name ______________________________qw3801: #REF!
Name ______________________________qw3911: #REF!
Name ______________________________qw3921: #REF!
Name ______________________________qw4111: #REF!
Name ______________________________qw4112: #REF!
Name ______________________________qw4113: #REF!
Name ______________________________qw4114: #REF!
Name ______________________________qw4115: #REF!
Name ______________________________qw4121: #REF!
Name ______________________________qw4122: #REF!
Name ______________________________qw4131: #REF!
Name ______________________________qw4141: #REF!
Name ______________________________qw4211: #REF!

Sheet 125мм 0,68 0,78
H1: Ед.изм | I1: ANFO | J1: EMULS
A2: Сетка | B2: 3.7 | C2: 3.7 | D2: Сетка | E2: 4 | F2: 4 | G2: Объем блока | H2: м3 | I2: =P4 -> 25000 | J2: =Q4 -> 25000 | L2: Смета затрат на производство взрывных работ на объекте
A3: Глубина | B3: 11 | D3: Глубина | E3: 11 | G3: Кол-во скважин | H3: шт. | I3: =I2/B5+5 -> 187.61505 | J3: =J2/E5+5 -> 161.25 | L3: "карьер м-ия С-Саркаевское гор. +150 " ООО "Ергач"
A4: Удельный | B4: =B6/B5 -> 0.68148875 | D4: Удельный | E4: =E6/E5 -> 0.7888984 | G4: Кол-во п.м. | H4: п.м. | I4: =I3*A8 -> 2063.7655 | J4: =J3*D8 -> 1773.75 | L4: Средний объем взрываемого блока, м3 | P4: 25000 | Q4: 25000
A5: Выход | B5: =B2*C2*(B3-$I$13) -> 136.9 | D5: Выход | E5: =E2*F2*(E3-$I$13) -> 160 | G5: Масса ВВ | H5: кг. | I5: =I3*B19 -> 17503.698 | J5: =J3*E19 -> 20353.579
A6: Заряд | B6: =B19+B13 -> 93.29581 | D6: Заряд | E6: =E19+E13 -> 126.22374 | G6: Шашка ДПУ-ПТ600 | H6: шт. | I6: =I3+4 -> 191.61505 | J6: =J3+4 -> 165.25 | L6: Выход В.Г.М. с 1 сважины,м3 | P6: =B5 -> 136.9 | Q6: =E5 -> 160
H7: кг. | I7: =I6*0.65 -> 124.54978 | J7: =J6*0.65 -> 107.4125 | L7: Кол-во скважин, шт | P7: =I3 -> 187.61505 | Q7: =J3 -> 161.25
A8: =B3 -> 11 | C8: =A32*22 -> 2.8875 | D8: =E3 -> 11 | F8: =A32*22 -> 2.8875 | G8: С-500-15 | H8: шт. | I8: =I6 -> 191.61505 | J8: =J6 -> 165.25 | L8: Выход В.Г.М. с 1 п.м. скважины | P8: =B5/B3 -> 12.445455 | Q8: =E5/E3 -> 14.545455
G9: П-17-5 | H9: шт. | I9: =I3/10+2 -> 20.761505 | J9: =J3/10+2 -> 18.125 | L9: Объем буровых работ, м | P9: =I4 -> 2063.7655 | Q9: =J4 -> 1773.75
G10: П-25-5 | H10: шт. | I10: =I3+2 -> 189.61505 | J10: =J3+2 -> 163.25 | L10: Удельный расход с учетом парносближенных | P10: =I5/I2 -> 0.70014792 | Q10: =J5/J2 -> 0.81414314
G11: ЭД-8М1 | H11: шт. | I11: 2 | J11: 2 | L11: Количество смен бурения | P11: =P9/I16+I24 -> 21.637655 | Q11: =Q9/J16+J24 -> 18.7375
P12: БВР сухие | Q12: БВР обв | R12: ВР сухие | S12: ВР обв | T12: Бурение
G13: Перебур | H13: м | I13: 1 | J13: 1 | L13: Материалы: | M13: Ед. изм. | N13: Кол-во | O13: Цена | P13: Сумма | Q13: Сумма | T13: Сумма
G14: Продолж-ть смены | H14: ч | I14: 10 | J14: 10 | L14: Аммиачная селитра пористая | O14: =[316]Лист1!$D$2 -> #REF! | P14: =N14*O14 -> #REF!
G15: Скорость проходки | H15: п.м./ч | I15: 10 | J15: 10 | L15: Дизельное топливо | O15: =[317]Лист1!$D$4 -> #REF! | P15: =N15*O15 -> #REF!
G16: Произв-ть смены | H16: п.м./см | I16: =I14*I15 -> 100 | J16: =J14*J15 -> 100 | L16: ПВВ "Гранулит АСП" | M16: т | N16: =P4*P10/1000 -> 17.503698 | O16: ='[318]Гранулит АСП-1'!$I$21 -> #REF! | P16: =N16*O16 -> #REF! | R16: =P16 -> #REF!
G17: Коэф-т исп-я обсадных | H17: % | I17: 0.1 | J17: 0.1 | L17: ЭВВ "Березит" | M17: т | N17: =Q4*Q10/1000 -> 20.353579 | O17: ='[319]Березит Э-100'!$P$50 -> #REF! | Q17: =N17*O17 -> #REF! | S17: =Q17 -> #REF!
G18: Норм. прох-ки коронки | H18: п.м. | I18: 700 | J18: 700 | L18: =[320]Лист1!$B$4 -> #REF! | M18: т | N18: =I7/1000 -> 0.12454978 | O18: =[320]Лист1!$E$4 -> #REF! | Q18: =J7/1000*O18 -> #REF! | S18: =Q18 -> #REF!
B19: =C19*D32 -> 93.29581 | C19: =A8-C8-C13-C16 -> 8.1125 | E19: =F19*D34 -> 126.22374 | F19: =D8-F8-F13-F16 -> 8.1125 | G19: Норм. прох-ки ППУ | H19: п.м. | I19: 10000 | J19: 10000 | L19: =[320]Лист1!$B$5 -> #REF! | M19: т | N19: =(I6+5)*0.0004 -> 0.078646019 | O19: =[320]Лист1!$E$5 -> #REF! | P19: =N19*O19 -> #REF! | R19: =P19 -> #REF!
G20: Норм. проходки РК | H20: п.м. | I20: 15000 | J20: 15000 | L20: =[320]Лист1!$B$7 -> #REF! | M20: шт | N20: =I8 -> 191.61505 | O20: =[320]Лист1!$F$7 -> #REF! | P20: =I8*O20 -> #REF! | Q20: =J8*O20 -> #REF! | R20: =P20 -> #REF! | S20: =Q20 -> #REF!
B21: АСП | G21: Норм. проходки штанга | H21: п.м. | I21: 10000 | J21: 10000 | L21: =[320]Лист1!$B$11 -> #REF! | M21: шт | N21: =I9 -> 20.761505 | O21: =[320]Лист1!$F$11 -> #REF! | P21: =I9*O21 -> #REF! | Q21: =J9*O21 -> #REF! | R21: =P21 -> #REF! | S21: =Q21 -> #REF!
E22: ЭВВ | L22: =[320]Лист1!$B$11 -> #REF! | M22: шт | N22: =I10 -> 189.61505 | O22: =[320]Лист1!$F$11 -> #REF! | P22: =I10*O22 -> #REF! | Q22: =J10*O22 -> #REF! | R22: =P22 -> #REF! | S22: =Q22 -> #REF!
L23: =[320]Лист1!$B$17 -> #REF! | M23: шт | N23: 2 | O23: =[320]Лист1!$D$17 -> #REF! | P23: =I11*O23 -> #REF! | Q23: =J11*O23 -> #REF! | R23: =P23 -> #REF! | S23: =Q23 -> #REF!
G24: Непроизв. работа экипажа БУ | H24: см | I24: 1 | J24: 1 | L24: =[321]Лист1!$B$18 -> #REF! | M24: шт | O24: =[321]Лист1!$D$18 -> #REF!
G25: Стоимость проживания | H25: руб | I25: 1000 | J25: 1000 | L25: ИТОГО ВМ: | P25: =SUM(P16:P23) -> #REF! | Q25: =SUM(Q16:Q23) -> #REF! | R25: =SUM(R16:R23) -> #REF! | S25: =SUM(S16:S23) -> #REF! | T25: =SUM(T16:T23) -> 0
L26: Хранение, производство и доставка ВМ и СИ
L27: Стоимость хранения | M27: руб. | P27: =P4*1.5 -> 37500 | Q27: =Q4*1.5 -> 37500 | R27: =P27 -> 37500 | S27: =Q27 -> 37500
L28: Доставка , разгрузка ВМ | M28: руб. | P28: 5000 | Q28: 5000 | R28: =P28 -> 5000 | S28: =Q28 -> 5000
L29: Энергозатраты на производство ЭВВ Березит | M29: руб. | N29: =N17 -> 20.353579 | O29: ='[322]Березит Э-100'!$E$73 -> #REF! | Q29: =N29*O29 -> #REF! | S29: =Q29 -> #REF!
A30: Диаметр заряда, м | D30: Вместимость, кг | L30: Разгрузка, перевалка компонентов | M30: руб. | N30: =N16 -> 17.503698 | O30: 700 | P30: =N30*O30 -> 12252.589 | Q30: =N17*O30 -> 14247.505 | R30: =P30 -> 12252.589 | S30: =Q30 -> 14247.505
D31: ANFO | L31: Роялти
A32: 0.13125 | D32: =PI()*POWER(A32,2)/4*850 -> 11.500254 | L32: Итого расходы на хранение и доставку | P32: =SUM(P27:P30) -> 54752.589 | Q32: =SUM(Q27:Q30) -> #REF! | R32: =SUM(R27:R30) -> 54752.589 | S32: =SUM(S27:S30) -> #REF! | T32: =SUM(T27:T30) -> 0
D33: EMULS | L33: Буровой инструмент: | P33: =N34*O34+N35*O35+N36*O36+N37*O37+N38*O38+N39*O39+N40*O40+N41*O41 -> #REF!
D34: =PI()*POWER(A32,2)/4*1150 -> 15.559167 | L34: =[323]Лист1!$B$17 -> #REF! | M34: шт | N34: =P9/I18 -> 2.9482365 | O34: =[323]Лист1!$D$17*1.2 -> #REF! | P34: =P4/P8/I18*O34 -> #REF! | Q34: =Q4/Q8/J18*O34 -> #REF! | T34: =O34/I18 -> #REF!
L35: =[323]Лист1!$B$5 -> #REF! | M35: шт | N35: =P9/I19 -> 0.20637655 | O35: =[323]Лист1!$D$5 -> #REF! | P35: =P4/P8/I19*O35 -> #REF! | Q35: =Q4/Q8/J19*O35 -> #REF! | T35: =O35/I19 -> #REF!
L36: =[323]Лист1!$B$24 -> #REF! | M36: шт | N36: =P9/I20 -> 0.13758437 | O36: =[323]Лист1!$D$24 -> #REF! | P36: =P4/P8/I20*O36 -> #REF! | Q36: =Q4/Q8/J20*P36 -> #REF! | T36: =O36/I20 -> #REF!
L37: =[323]Лист1!$B$27 -> #REF! | M37: шт | N37: =P9/6000 -> 0.34396092 | O37: =[323]Лист1!$D$27 -> #REF! | P37: =N37*O37 -> #REF! | T37: =O37/10000 -> #REF!
L38: =[323]Лист1!$B$42 -> #REF! | M38: шт | N38: =P9/I21 -> 0.20637655 | O38: =[323]Лист1!$D$42 -> #REF! | P38: =P4/P8/I21*O38 -> #REF! | Q38: =Q4/Q8/J21*O38 -> #REF! | T38: =O38/J21 -> #REF!
L39: =[324]Лист1!$B$51 -> #REF! | M39: шт | N39: 0.5 | O39: =[324]Лист1!$D$51*1.21 -> #REF! | P39: =N39*O39 -> #REF!
L40: =[323]Лист1!$B$60 -> #REF! | M40: п.м. | N40: =P9*I17 -> 206.37655 | O40: =[323]Лист1!$D$60 -> #REF! | P40: =N40*O40 -> #REF! | Q40: =Q9*J17*O40 -> #REF! | T40: =O40*0.1 -> #REF!
L41: Доставка инструмента | N41: 0.5 | O41: 3000 | P41: =N41*O41 -> 1500 | Q41: =N41*O41 -> 1500 | T41: =Q41/Q9 -> 0.84566596 | U41: Стоимость БИ на 1 пог. метр
L42: Итого буровой инструмент | P42: =SUM(P34:P41) -> #REF! | Q42: =SUM(Q34:Q41) -> #REF! | T42: =SUM(T34:T41) -> #REF!
L43: Состав участка, ФОТ | N43: кол-во | P43: Сумма
L44: Взрывники+РВР | N44: 3 | P44: =(P4*0.2+2500)/0.87*N44 -> 25862.069 | Q44: =(Q4*0.2+2500)/0.87*N44 -> 25862.069 | R44: =P44 -> 25862.069 | S44: =Q44 -> 25862.069
L45: Водитель СЗМ | N45: 1 | P45: =(N16*300+3500)/0.87 -> 10058.746 | Q45: =(N17*300+3500)/0.87 -> 11041.464 | R45: =P45 -> 10058.746 | S45: =Q45 -> 11041.464
L46: Зав. складом ВМ | N46: 1 | P46: =30000/0.87/15 -> 2298.8506 | Q46: =30000/0.87/10 -> 3448.2759 | R46: =P46 -> 2298.8506 | S46: =Q46 -> 3448.2759
L47: Экипаж буровой установки | N47: 2 | P47: =P11*N47*3000/0.87 -> 149225.21 | Q47: =N47*Q11*3000/0.87 -> 129224.14 | T47: =Q47/Q9 -> 72.853637
L48: Начальник бурового участка | N48: 15 | P48: =N48*1000/0.87 -> 17241.379 | Q48: =P48 -> 17241.379 | T48: =Q48/Q9 -> 9.7202984
L49: Мастер УМПП НК ЭВВ 5 | N49: =N29/11 -> 1.8503253 | Q49: =N49*2500 -> 4625.8133 | S49: =Q49 -> 4625.8133
L51: Итого ФОТ | N51: =SUM(N44:N48) -> 22 | P51: =SUM(P44:P48) -> 204686.25 | Q51: =SUM(Q44:Q49) -> 191443.14 | R51: =SUM(R44:R48) -> 38219.666 | S51: =SUM(S44:S48) -> 40351.809 | T51: =SUM(T44:T48) -> 82.573935 | U51: ФОТ БИ на 1 пог. метр
J52: 0.007 | L52: Отчисления от несчастного случая 2,1% | P52: =P51*2.1% -> 4298.4113 | Q52: =Q51*2.1% -> 4020.3059 | R52: =R51*2.1% -> 802.61298 | S52: =S51*2.1% -> 847.38798 | T52: =T51*2.1% -> 1.7340526
L53: Отчисления в фонды социального страхования,30% | P53: =P51*30% -> 61405.876 | Q53: =Q51*30% -> 57432.942 | R53: =R51*30% -> 11465.9 | S53: =S51*30% -> 12105.543 | T53: =T51*30% -> 24.772181
L54: ИТОГО ФОТ, с учетом ЕСН | P54: =SUM(P51:P53) -> 270390.54 | Q54: =SUM(Q51:Q53) -> 252896.39 | R54: =SUM(R51:R53) -> 50488.179 | S54: =SUM(S51:S53) -> 53304.739 | T54: =SUM(T51:T53) -> 109.08017
L55: Суточные (4чел.*700 руб*0 дней) | N55: 4 | O55: 700 | P55: =N55*O55*2 -> 5600 | Q55: =N55*O55*2 -> 5600 | R55: =P55 -> 5600 | S55: =Q55 -> 5600
L56: Вахтовые (4чел.*1500 руб*х дней) | N56: 4 | O56: 1500 | P56: =P11/2*O56 -> 16228.241 | Q56: =Q11/2*O56 -> 14053.125 | T56: =Q56/Q9 -> 7.922833
L57: Проживание | N57: 4 | O57: =I25 -> 1000 | P57: =P11*O57 -> 21637.655 | Q57: =Q11*O57 -> 18737.5 | T57: =Q57/Q9 -> 10.563777
L58: Суточные, вахтовые, проживание | P58: =SUM(P55:P57) -> 43465.897 | Q58: =SUM(Q55:Q57) -> 38390.625 | R58: =SUM(R55:R57) -> 5600 | S58: =SUM(S55:S57) -> 5600 | T58: =SUM(T55:T57) -> 18.48661
L59: ГСМ на бурение | N59: =(P11-I24)*I14 -> 206.37655 | O59: 40 | P59: =N59*O59*([317]Лист1!$D$5/1000*0.85) -> #REF! | Q59: =(Q11-J24)*J14*O59*(O15/1000*0.85) -> #REF! | T59: =O59*(O15/1000*0.85)/J15 -> #REF!
L60: Мобилизация буровой установки | N60: 300 | O60: 0.4 | P60: =N60*O60*(O15/1000*0.85) -> #REF! | Q60: =P60 -> #REF! | T60: =Q60/Q9 -> #REF!
L61: ДТ СЗМ пробег до карьера + моточасы | N61: 400 | O61: 0.45 | P61: =N61*O61*(O15*0.85/1000) -> #REF! | Q61: =P61 -> #REF! | R61: =P61 -> #REF! | S61: =Q61 -> #REF!
L62: ДТ Луидор пробег + моточасы | N62: 600 | O62: 0.15 | P62: =N62*O62*(O15*0.85/1000) -> #REF! | Q62: =P62 -> #REF! | R62: =P62 -> #REF! | S62: =Q62 -> #REF!
L63: ДТ для проезда на карьер на легковом а/м | N63: 600 | O63: 0.1 | P63: =N63*O63*(O16*0.85/1000) -> #REF! | Q63: =P63 -> #REF! | R63: =P63 -> #REF! | S63: =Q63 -> #REF! | T63: =Q63/Q9 -> #REF!
L64: Итого ДТ на производство работ | P64: =SUM(P59:P62) -> #REF! | Q64: =SUM(Q59:Q62) -> #REF! | R64: =SUM(R59:R62) -> #REF! | S64: =SUM(S59:S62) -> #REF! | T64: =SUM(T59:T62) -> #REF!
L65: Буровая установка УРБ | M65: смен | N65: =P11 -> 21.637655 | O65: =[325]Лист1!$J$35 -> #REF! | P65: =O65*P11 -> #REF! | Q65: =O65*Q11 -> #REF! | T65: =Q65/Q9 -> #REF!
L66: Компрессор XAXS277 CD | M66: смен | N66: =P11 -> 21.637655 | O66: =[325]Лист1!$J$39 -> #REF! | P66: =N66*O66 -> #REF! | Q66: =O66*(Q11-J24) -> #REF! | T66: =Q66/Q9 -> #REF!
L67: СЗМ.TDR.PR-12 на базе шасси КАМАЗ | M67: смен | N67: 1 | O67: =[325]Лист1!$J$43 -> #REF! | P67: =N67*O67 -> #REF! | Q67: =P67 -> #REF! | R67: =P67 -> #REF! | S67: =Q67 -> #REF!
L68: А/м для перевозки взрывчатых веществ ГАЗ A32 | M68: смен | N68: 2 | O68: =[325]Лист1!$J$46 -> #REF! | P68: =N68*O68 -> #REF! | Q68: =P68 -> #REF! | R68: =P68 -> #REF! | S68: =Q68 -> #REF!
L69: УМПП НК ЭВВ 5 | M69: смен | N69: =N17/11 -> 1.8503253 | O69: ='[322]Березит Э-100'!$E$81 -> #REF! | Q69: =N69*O69 -> #REF! | S69: =N69*O69 -> #REF!
L70: База и вспомогательное | M70: смен | N70: 1 | O70: =[325]Лист1!$J$14+[325]Лист1!$J$6 -> #REF! | P70: =N70*O70 -> #REF! | Q70: =P70 -> #REF! | R70: =P70 -> #REF! | S70: =Q70*1.2 -> #REF! | T70: =Q70/Q9 -> #REF!
L71: Итого амортизация | P71: =SUM(P65:P70) -> #REF! | Q71: =SUM(Q65:Q70) -> #REF! | R71: =SUM(R65:R70) -> #REF! | S71: =SUM(S65:S70) -> #REF! | T71: =SUM(T65:T70) -> #REF!
L72: ТО Спецтехники и оборудования | P72: 15000 | Q72: =P72 -> 15000 | R72: =P72/3 -> 5000 | S72: =Q72/3 -> 5000 | T72: =18000/Q9 -> 10.147992
L73: ОСАГО (УРБ, СВМ, СЗМ) | P73: 500 | Q73: =P73 -> 500 | R73: =P73 -> 500 | S73: =Q73 -> 500 | T73: =Q73*0.66/Q9 -> 0.18604651
L74: Содержание базы | P74: 6000 | Q74: =P74 -> 6000 | R74: =P74/2 -> 3000 | S74: =Q74/2 -> 3000 | T74: =Q74/2/Q9 -> 1.6913319
L75: Запасные части и расходные материалы | O75: 1010 | P75: 30000 | Q75: =P75 -> 30000 | R75: =P75/2 -> 15000 | S75: =Q75/2 -> 15000 | T75: =14400/Q9 -> 8.1183932
L76: Спецодежа и СИЗ | P76: 5000 | Q76: =P76 -> 5000 | R76: =P76/2 -> 2500 | S76: =Q76/2 -> 2500 | T76: =Q76/2/Q9 -> 1.4094433
L77: Проверка технического состояния СЗМ и медосмотр водителей | O77: 1 | P77: 200 | Q77: =P77 -> 200 | R77: =P77 -> 200 | S77: =Q77 -> 200 | T77: =Q77/2/Q9 -> 0.056377731
L78: Итого общепроизводственные затраты | P78: =SUM(P72:P77) -> 56700 | Q78: =SUM(Q72:Q77) -> 56700 | R78: =SUM(R72:R77) -> 26200 | S78: =SUM(S72:S77) -> 26200 | T78: =SUM(T72:T77) -> 21.609584
P79: =P25+P32+P42+P54+P58+P64+P71+P78 -> #REF! | Q79: =Q25+Q32+Q42+Q54+Q58+Q64+Q71+Q78 -> #REF! | R79: =R25+R32+R42+R54+R58+R64+R71+R78 -> #REF! | S79: =S25+S32+S42+S54+S58+S64+S71+S78 -> #REF! | T79: =T25+T32+T42+T54+T58+T64+T71+T78 -> #REF!
O80: руб/м3 | P80: =P79/P4 -> #REF! | Q80: =Q79/Q4 -> #REF! | R80: =R79/P4 -> #REF! | S80: =S79/Q4 -> #REF! | T80: =T79 -> #REF!
L81: Административно-хозяйственные расходы | O81: 0.05 | P81: =P80*O81 -> #REF! | Q81: =Q80*O81 -> #REF! | R81: =R80*O81 -> #REF! | S81: =S80*O81 -> #REF! | T81: =T80*5% -> #REF!
L82: Рентабельность | O82: 0.05 | P82: =P80*O82 -> #REF! | Q82: =Q80*O82 -> #REF! | R82: =R80*O82 -> #REF! | S82: =S80*O82 -> #REF! | T82: =T80*5% -> #REF!
L83: Цена без учета НДС | P83: =P80+P81+P82 -> #REF! | Q83: =Q80+Q81+Q82 -> #REF! | R83: =R80+R81+R82 -> #REF! | S83: =S80+S81+S82 -> #REF! | T83: =T80+T81+T82 -> #REF!
L84: Цена с учетом НДС 20% | P84: =P83*1.2 -> #REF! | Q84: =Q83*1.2 -> #REF! | R84: =R83*1.2 -> #REF! | S84: =S83*1.2 -> #REF! | T84: =T83*1.2 -> #REF!
L87: Общий объем работ, м3 | N87: 600000
L88: Общая выручка без учета НДС, руб. | N88: =N87*R83 -> #REF!
L89: Рентабельность | N89: =N87*R82 -> #REF!

Sheet Лист3
A1: Гранулит АСП-1
A2: Березит Э-100 Рецептура № 1

Sheet смета расч. 0,88 1,16 D165
A1: Исходные данные, технические параметры для расчета | Q1: Смета затрат | W1: =#REF! -> #REF! | AA1: проверка расчетов | AC1: =(S7+T7+U7+V7+W7)-S8-T8-U8-V8-W8-W17-V17-U17-T17-S17+S26+T26+U26+V26+W26-S27-S33-S37-S48-S54-S60-T27-T33-T37-T48-T54-T60-U60-U54-U48-U37-U33-U27-V27-V33-V37-V48-V54-V60-W60-W54-W48-W37-W33-W27 -> #VALUE! | AE1: если не 0- ищем ошибку
Q2: на производство взрывных работ на объекте | T2: поставка вм | AC2: =S7+S26-S67+T7+T26-T67+U7+U26-U67+V7+V26-V67+W7+W26-W67 -> #VALUE!
H3: Показатель | I3: Ед.изм | J3: ANFO | K3: EMULS | Q3: "карьер м-ия Ломовское" АО "ТК" | W3: пм
A4: Сетка | B4: 4 | C4: 4 | D4: Сетка | E4: 4 | F4: 4.2 | H4: Объем блока | I4: м3 | J4: =S5 -> 20000 | K4: =T5 -> 20000 | R4: базовый тариф
A5: Глубина | B5: 11.5 | D5: Глубина | E5: 11.5 | H5: Кол-во скважин | I5: шт. | J5: =J4/B7 -> 119.04762 | K5: =K4/E7 -> 113.37868 | N5: К потерь | O5: 1 | R5: Объем справочно, м3 | S5: 20000 | T5: =S5 -> 20000 | U5: =S5 -> 20000 | V5: =T5 -> 20000 | W5: 10000
A6: Удельный | B6: =B8/B7 -> 0.82964053 | D6: Удельный | E6: =E8/E7 -> 1.0817308 | H6: Добавочные скважины | J6: 7 | K6: 7 | M6: № п/п | N6: Наименование | O6: Ед. изм. | P6: Норма const ANFO (кг./л.//1000 м3) | Q6: Норма const EMULS (кг./л.//1000 м3) | R6: Цена (руб./шт, тн) | S6: БВР сухие | T6: БВР обв | U6: ВР сухие | V6: ВР обв | W6: Бурение
A7: Выход | B7: =B4*C4*(B5-$J$18) -> 168 | D7: Выход | E7: =E4*F4*(E5-$J$18) -> 176.4 | H7: Кол-во п.м. | I7: п.м. | J7: =(J5+J6)*A10 -> 1449.5476 | K7: =(K5+K6)*D10 -> 1384.3549 | M7: 1 | N7: Переменные расходы | S7: =SUBTOTAL(9,S9:S25) -> #VALUE! | T7: =SUBTOTAL(9,T9:T25) -> #VALUE! | U7: =SUBTOTAL(9,U9:U25) -> #VALUE! | V7: =SUBTOTAL(9,V9:V25) -> #VALUE! | W7: =SUBTOTAL(9,W8:W17) -> 0
A8: Заряд | B8: =B21+B15 -> 139.37961 | D8: Заряд | E8: =E21+E15 -> 190.81732 | H8: Масса ВВ | I8: кг. | J8: =(J5+J6)*B21 -> 17568.468 | K8: =(K5+K6)*E21 -> 22970.338 | M8: 1.1. | N8: Расходы на ВМ | S8: =SUBTOTAL(9,S9:S16) -> #VALUE! | T8: =SUBTOTAL(9,T9:T16) -> #VALUE! | U8: =SUBTOTAL(9,U9:U16) -> #VALUE! | V8: =SUBTOTAL(9,V9:V16) -> #VALUE! | W8: =SUBTOTAL(9,W9:W16) -> 0
H9: Шашка ДПУ-ПТ600 | I9: шт. | J9: =J5+J6+4 -> 130.04762 | K9: =K5+K6+4 -> 124.37868 | N9: Гранулит АСП-1 | O9: тн | P9: =J32 -> 0.87842339 | Q9: 0 | R9: =VLOOKUP(N9,#REF!,16,0) -> #REF! | S9: =IF(ISERR($P$9*$R$9)," ",($P$9*$R$9))/1000*$S$5 -> #VALUE! | T9: =IF(ISERR($Q$9*$R$9)," ",($Q$9*$R$9))/1000*$T$5 -> #VALUE! | U9: =IF(ISERR($P$9*$R$9)," ",($P$9*$R$9))/1000*$U$5 -> #VALUE! | V9: =IF(ISERR($Q$9*$R$9)," ",($Q$9*$R$9))/1000*$V$5 -> #VALUE!
A10: =B5 -> 11.5 | C10: =A34*25 -> 4.275 | D10: =E5 -> 11.5 | F10: =A34*25 -> 4.275 | H10: Шашка ДПУ-ПТ600 | I10: кг. | J10: =J9*0.65 -> 84.530952 | K10: =K9*0.65 -> 80.846145 | N10: Березит Э-100 Рецептура № 1 | O10: тн | P10: 0 | Q10: =K32 -> 1.1485169 | R10: =VLOOKUP(N10,#REF!,16,0) -> #REF! | S10: =IF(ISERR($P$10*$R$10)," ",($P$10*$R$10))/1000*$S$5 -> #VALUE! | T10: =IF(ISERR($Q$10*$R$10)," ",($Q$10*$R$10))/1000*$T$5 -> #VALUE! | U10: =IF(ISERR($P$10*$R$10)," ",($P$10*$R$10))/1000*$U$5 -> #VALUE! | V10: =IF(ISERR($Q$10*$R$10)," ",($Q$10*$R$10))/1000*$V$5 -> #VALUE!
H11: Аммонит № 6ЖВ-200 | I11: шт. | J11: =J9 -> 130.04762 | K11: =K9 -> 124.37868 | N11: Детонатор промежуточный ДПУ-ПТ600 | O11: =VLOOKUP(N11,#REF!,2,FALSE) -> #REF! | P11: 0 | Q11: =K10/1000 -> 0.080846145 | R11: =VLOOKUP(N11,#REF!,15,0) -> #REF! | S11: =IF(ISERR($P$11*$R$11)," ",($P$11*$R$11)) | T11: =IF(ISERR($Q$11*$R$11)," ",($Q$11*$R$11)) | U11: =IF(ISERR($P$11*$R$11)," ",($P$11*$R$11)) | V11: =IF(ISERR($Q$11*$R$11)," ",($Q$11*$R$11))
H12: Аммонит № 6ЖВ-200 | I12: кг. | J12: =J11*0.4 -> 52.019048 | K12: =K11*0.4 -> 49.751474 | N12: Аммонит № 6ЖВ-200 ГОСТ 21984-76 | O12: =VLOOKUP(N12,#REF!,2,FALSE) -> #REF! | P12: =J12/1000 -> 0.052019048 | Q12: 0 | R12: =VLOOKUP(N12,#REF!,15,0) -> #REF! | S12: =IF(ISERR($P$12*$R$12)," ",($P$12*$R$12)) | T12: =IF(ISERR($Q$12*$R$12)," ",($Q$12*$R$12)) | U12: =IF(ISERR($P$12*$R$12)," ",($P$12*$R$12)) | V12: =IF(ISERR($Q$12*$R$12)," ",($Q$12*$R$12))
H13: С-500-15 | I13: шт. | J13: =J9 -> 130.04762 | K13: =K9 -> 124.37868 | N13: НСИ "Rionel" серии MS-20-15 м. (в упаковке 1.4 S) | O13: =VLOOKUP(N13,#REF!,2,FALSE) -> #REF! | P13: =J13 -> 130.04762 | Q13: =K13 -> 124.37868 | R13: =VLOOKUP(N13,#REF!,15,0) -> #REF! | S13: =IF(ISERR($P$13*$R$13)," ",($P$13*$R$13)) | T13: =IF(ISERR($Q$13*$R$13)," ",($Q$13*$R$13)) | U13: =IF(ISERR($P$13*$R$13)," ",($P$13*$R$13)) | V13: =IF(ISERR($Q$13*$R$13)," ",($Q$13*$R$13))
H14: П-17-5 | I14: шт. | J14: =(J5+J6)/10+2 -> 14.604762 | K14: =(K5+K6)/10+2 -> 14.037868 | N14: НСИ "Rionel" серии Х-*-4,2 м. (в упаковке 1.4 S) | O14: =VLOOKUP(N14,#REF!,2,FALSE) -> #REF! | P14: =J14 -> 14.604762 | Q14: =K14 -> 14.037868 | R14: =VLOOKUP(N14,#REF!,15,0) -> #REF! | S14: =IF(ISERR($P$14*$R$14)," ",($P$14*$R$14)) | T14: =IF(ISERR($Q$14*$R$14)," ",($Q$14*$R$14)) | U14: =IF(ISERR($P$14*$R$14)," ",($P$14*$R$14)) | V14: =IF(ISERR($Q$14*$R$14)," ",($Q$14*$R$14))
H15: П-25-5 | I15: шт. | J15: =J5+J6+2 -> 128.04762 | K15: =K5+K6+2 -> 122.37868 | N15: НСИ "Rionel" серии Х-*-4,2 м. (в упаковке 1.4 S) | O15: =VLOOKUP(N15,#REF!,2,FALSE) -> #REF! | P15: =J15 -> 128.04762 | Q15: =K15 -> 122.37868 | R15: =VLOOKUP(N15,#REF!,15,0) -> #REF! | S15: =IF(ISERR($P$15*$R$15)," ",($P$15*$R$15)) | T15: =IF(ISERR($Q$15*$R$15)," ",($Q$15*$R$15)) | U15: =IF(ISERR($P$15*$R$15)," ",($P$15*$R$15)) | V15: =IF(ISERR($Q$15*$R$15)," ",($Q$15*$R$15))
H16: ЭД-8М1 | I16: шт. | J16: 2 | K16: 2 | N16: Электродетонатор ЭД-8М1 | O16: =VLOOKUP(N16,#REF!,2,FALSE) -> #REF! | P16: =J16 -> 2 | Q16: =K16 -> 2 | R16: =VLOOKUP(N16,#REF!,15,0) -> #REF! | S16: =IF(ISERR($P$16*$R$16)," ",($P$16*$R$16)) | T16: =IF(ISERR($Q$16*$R$16)," ",($Q$16*$R$16)) | U16: =IF(ISERR($P$16*$R$16)," ",($P$16*$R$16)) | V16: =IF(ISERR($Q$16*$R$16)," ",($Q$16*$R$16))
M17: 1.2. | N17: Расходы на буровой инструмент | S17: =SUBTOTAL(9,S18:S25) -> 1100 | T17: =SUBTOTAL(9,T18:T25) -> 1100 | U17: =SUBTOTAL(9,U18:U25) -> 0 | V17: =SUBTOTAL(9,V18:V25) -> 0 | W17: =SUBTOTAL(9,W18:W25) -> 0
H18: Перебур | I18: м | J18: 1 | K18: 1 | N18: Пневмоударник DT-H4 DHD340 2-3/8 API Reg | O18: =VLOOKUP(N18,#REF!,2,FALSE) -> #REF! | P18: =J7/J24 -> 0.14495476 | Q18: =K7/K24 -> 0.13843549 | R18: =VLOOKUP(N18,#REF!,15,0) -> #REF! | S18: =IF(ISERR($P$18*$R$18)," ",($P$18*$R$18)) | T18: =IF(ISERR($Q$18*$R$18)," ",($Q$18*$R$18))
H19: Продолж-ть смены | I19: ч | J19: 10 | K19: 10 | N19: Ремкомплект DT-H4 DHD340 (внешний) | O19: =VLOOKUP(N19,#REF!,2,FALSE) -> #REF! | P19: =J7/J25 -> 0.20707823 | Q19: =K7/K25 -> 0.19776498 | R19: =VLOOKUP(N19,#REF!,15,0) -> #REF! | S19: =IF(ISERR($P$19*$R$19)," ",($P$19*$R$19)) | T19: =IF(ISERR($Q$19*$R$19)," ",($Q$19*$R$19))
H20: Скорость проходки | I20: п.м./ч | J20: 14 | K20: 14 | N20: Труба буровая ТБСУ 63,5х6,0х4700 мм | O20: =VLOOKUP(N20,#REF!,2,FALSE) -> #REF! | P20: =J7/J27 -> 0.28990952 | Q20: =K7/K27 -> 0.27687098 | R20: =VLOOKUP(N20,#REF!,15,0) -> #REF! | S20: =IF(ISERR($P$20*$R$20)," ",($P$20*$R$20)) | T20: =IF(ISERR($Q$20*$R$20)," ",($Q$20*$R$20))
B21: =C21*D34 -> 139.37961 | C21: =A10-C10-C15-C18 -> 7.225 | E21: =F21*D36 -> 190.81732 | F21: =D10-F10-F15-F18 -> 7.225 | H21: Произв-ть смены | I21: п.м./см | J21: =J19*J20 -> 140 | K21: =K19*K20 -> 140 | N21: Переводник З-50/З-66м(2паза) | O21: =VLOOKUP(N21,#REF!,2,FALSE) -> #REF! | P21: =J7/10000 -> 0.14495476 | Q21: =K7/10000 -> 0.13843549 | R21: =VLOOKUP(N21,#REF!,15,0) -> #REF! | S21: =IF(ISERR($P$21*$R$21)," ",($P$21*$R$21)) | T21: =IF(ISERR($Q$21*$R$21)," ",($Q$21*$R$21))
H22: Коэф-т исп-я обсадных | I22: % | J22: 0.1 | K22: 0.1 | N22: Труба техническая D125 SDR 26 ТУ 2248-001-49127551-2014 | O22: п.м. | P22: =J7*J22 -> 144.95476 | Q22: =K7*K22 -> 138.43549 | R22: =VLOOKUP(N22,#REF!,15,0) -> #REF! | S22: =IF(ISERR($P$22*$R$22)," ",($P$22*$R$22)) | T22: =IF(ISERR($Q$22*$R$22)," ",($Q$22*$R$22))
B23: АСП | H23: Норм. прох-ки коронки | I23: п.м. | J23: 700 | K23: 700 | N23: Коронка буровая DT-DHD340 125 мм CVD/SBL | O23: =VLOOKUP(N23,#REF!,2,FALSE) -> #REF! | P23: =J7/J23 -> 2.0707823 | Q23: =K7/K23 -> 1.9776498 | R23: =VLOOKUP(N23,#REF!,15,0) -> #REF! | S23: =IF(ISERR($P$23*$R$23)," ",($P$23*$R$23)) | T23: =IF(ISERR($Q$23*$R$23)," ",($Q$23*$R$23))
E24: ЭВВ | H24: Норм. прох-ки ППУ | I24: п.м. | J24: 10000 | K24: 10000
H25: Норм. проходки РК | I25: п.м. | J25: 7000 | K25: 7000 | N25: Доставка инструмента | O25: шт | P25: 0.5 | Q25: 0.5 | R25: 2200 | S25: =IF(ISERR($P$25*$R$25)," ",($P$25*$R$25)) -> 1100 | T25: =IF(ISERR($Q$25*$R$25)," ",($Q$25*$R$25)) -> 1100
M26: 2 | N26: Постоянные расходы | S26: =SUBTOTAL(9,S28:S66) -> #REF! | T26: =SUBTOTAL(9,T28:T66) -> #REF! | U26: =SUBTOTAL(9,U28:U66) -> #REF! | V26: =SUBTOTAL(9,V28:V66) -> #REF! | W26: =SUBTOTAL(9,W28:W60) -> 0
H27: Норм. проходки штанга | I27: п.м. | J27: 5000 | K27: 5000 | M27: 2.1. | N27: Хранение, производство и доставка ВМ и СИ | S27: =SUBTOTAL(9,S28:S32) -> 47297.927 | T27: =SUBTOTAL(9,T28:T32) -> 92922.005 | U27: =SUBTOTAL(9,U28:U32) -> 47297.927 | V27: =SUBTOTAL(9,V28:V32) -> 92922.005 | W27: =SUBTOTAL(9,W28:W32) -> 0
H28: Непроизв. работа экипажа БУ | I28: см | J28: 1 | K28: 1 | N28: Стоимость хранения | S28: =S5*1.5 -> 30000 | T28: =T5*1.5 -> 30000 | U28: =U5*1.5 -> 30000 | V28: =V5*1.5 -> 30000
H29: Стоимость проживания | I29: руб | J29: 500 | K29: 500 | N29: Доставка , разгрузка ВМ | S29: 5000 | T29: 5000 | U29: 5000 | V29: 5000
H30: Выход ВГМ с 1 п.м. скважины | I30: м3 | J30: =B7/B5 -> 14.608696 | K30: =E7/E5 -> 15.33913 | N30: Энергозатраты на производство ЭВВ Березит | Q30: =Q10 -> 1.1485169 | R30: =$K$40 -> 1821.6 | T30: =K8/1000*R30 -> 41842.768 | V30: =K8/1000*R30 -> 41842.768
H31: Выход ВГМ с 1 п.м. с учетом доп. скв | I31: м3 | J31: =J4/J7 -> 13.797408 | K31: =K4/K7 -> 14.447163 | N31: Разгрузка, перевалка компонентов | P31: =P9 -> 0.87842339 | Q31: =Q10 -> 1.1485169 | R31: 700 | S31: =J8/1000*R31 -> 12297.927 | T31: =K8/1000*R31 -> 16079.237 | U31: =J8/1000*R31 -> 12297.927 | V31: =K8/1000*R31 -> 16079.237
A32: Диаметр заряда, м | D32: Вместимость, кг | H32: Удельный расход с учетом парносближенных | J32: =J8/J4 -> 0.87842339 | K32: =K8/K4 -> 1.1485169 | N32: Роялти
D33: ANFO | H33: Количество смен бурения | I33: см | J33: =J7/J21+J28 -> 11.353912 | K33: =K7/K21+K28 -> 10.888249 | M33: 2.2. | N33: Суточные, вахтовые, проживание | O33: чел | P33: кол-во см.бур. | S33: =SUBTOTAL(9,S34:S36) -> 30578.605 | T33: =SUBTOTAL(9,T34:T36) -> 35154.148 | U33: =SUBTOTAL(9,U34:U36) -> 5600 | V33: =SUBTOTAL(9,V34:V36) -> 11200 | W33: =SUBTOTAL(9,W34:W36) -> 0
A34: 0.171 | D34: =PI()*POWER(A34,2)/4*840 -> 19.291295 | H34: Количество смен заряжания | I34: см | J34: 1 | K34: 2 | N34: Суточные (хчел.*700 руб*х дней) | O34: 4 | R34: 700 | S34: =O34*J34*R34 -> 2800 | T34: =O34*K34*R34 -> 5600 | U34: =S34 -> 2800 | V34: =T34 -> 5600
D35: EMULS | N35: Вахтовые (хчел.*1500 руб*х дней) | O35: 4 | R35: 1500 | S35: =J33*$R$35 -> 17030.867 | T35: =K33*$R$35 -> 16332.374
D36: =PI()*POWER(A34,2)/4*1150 -> 26.410702 | N36: Проживание (хчел.*1000 руб*х дней) | O36: 4 | R36: 700 | S36: =$R$36*(J33+O36) -> 10747.738 | T36: =$R$36*(K33+(K34*O36)) -> 13221.774 | U36: =O36*R36*J34 -> 2800 | V36: =O36*R36*K34 -> 5600
H37: Энергозатраты на тонну ЭМ | M37: 2.3. | N37: Фонд оплаты труда | P37: кол-во чел. | S37: =SUBTOTAL(9,S38:S46) -> 154043.62 | T37: =SUBTOTAL(9,T38:T46) -> 162987.94 | U37: =SUBTOTAL(9,U38:U46) -> 48922.896 | V37: =SUBTOTAL(9,V38:V46) -> 60556.533 | W37: =SUBTOTAL(9,W38:W46) -> 0
H38: Электроэнергия, кВА | I38: 40 | J38: 7.14 | K38: =I38*J38 -> 285.6 | N38: Взрывники | P38: 3 | S38: =(S5*0.2+4500)/0.87*P38 -> 29310.345 | T38: =(T5*0.2+4500)/0.87*P38 -> 29310.345 | U38: =(U5*0.2+4500)/0.87*P38 -> 29310.345 | V38: =(V5*0.2+4500)/0.87*P38 -> 29310.345
H39: Дизельное топливо, л | I39: 32 | J39: 48 | K39: =I39*J39 -> 1536 | N39: Водитель СЗМ | P39: 1 | S39: =(P9*10*300+1500)/0.87 -> 4753.1841 | T39: =(Q10*10*300+3000)/0.87 -> 7408.679 | U39: =(P9*10*300+2500)/0.87 -> 5902.6094 | V39: =(Q10*10*300+3000)/0.87 -> 7408.679
K40: =K38+K39 -> 1821.6 | N40: Зав. складом ВМ | P40: 1 | S40: =30000/0.87/15 -> 2298.8506 | T40: =30000/0.87/10 -> 3448.2759 | U40: =30000/0.87/15 -> 2298.8506 | V40: =30000/0.87/10 -> 3448.2759
N41: Экипаж буровой установки | P41: 2 | S41: =J33*P41*3000/0.87 -> 78302.838 | T41: =K33*P41*3000/0.87 -> 75091.373
N42: Начальник бурового участка | P42: 1 | S42: =1*3000/0.87 -> 3448.2759 | T42: =1*3000/0.87 -> 3448.2759
N43: Оператор УМПП | P43: 1 | T43: =K8/11000*3000 -> 6264.6377 | V43: =T43 -> 6264.6377
N44: Итого заработная плата | P44: =SUM(P38:P43) -> 9 | S44: =SUBTOTAL(9,S38:S43) -> 118113.49 | T44: =SUBTOTAL(9,T38:T43) -> 124971.59 | U44: =SUBTOTAL(9,U38:U43) -> 37511.805 | V44: =SUBTOTAL(9,V38:V43) -> 46431.937 | W44: =SUBTOTAL(9,W38:W43) -> 0
N45: Отчисления от несчастного случая | P45: 0.0042 | S45: =S44*$P$45 -> 496.07667 | T45: =T44*$P$45 -> 524.88066 | U45: =U44*$P$45 -> 157.54958 | V45: =V44*$P$45 -> 195.01414
N46: Отчисления в фонды социального страхования | P46: 0.3 | S46: =S44*$P$46 -> 35434.048 | T46: =T44*$P$46 -> 37491.476 | U46: =U44*$P$46 -> 11253.541 | V46: =V44*$P$46 -> 13929.581
N47: Итого отчисления с заработной платы | S47: =SUBTOTAL(9,S45:S46) -> 35930.125 | T47: =SUBTOTAL(9,T45:T46) -> 38016.357 | U47: =SUBTOTAL(9,U45:U46) -> 11411.091 | V47: =SUBTOTAL(9,V45:V46) -> 14124.595 | W47: =SUBTOTAL(9,W45:W46) -> 0
M48: 2.4. | N48: ГСМ на бурение | S48: =SUBTOTAL(9,S49:S53) -> #REF! | T48: =SUBTOTAL(9,T49:T53) -> #REF! | U48: =SUBTOTAL(9,U49:U53) -> #REF! | V48: =SUBTOTAL(9,V49:V53) -> #REF! | W48: =SUBTOTAL(9,W49:W52) -> 0
N49: ГСМ на бурение | O49: л/час | P49: 40 | Q49: 40 | R49: =VLOOKUP($Q$3,'Объекты работ'!$A:$E,6,FALSE)/1000 -> #REF! | S49: =(J33-J28)*J19*P49*R49*0.85 -> #REF! | T49: =($K$33-$K$28)*K19*R49*Q49*0.85 -> #REF!
N50: Мобилизация буровой установки | O50: км | P50: =VLOOKUP(Q3,'Объекты работ'!$A:$C,2,FALSE) -> 220 | Q50: 0.4 | R50: =VLOOKUP($Q$3,'Объекты работ'!$A:$E,6,FALSE)/1000 -> #REF! | S50: =P50*Q50*R50*0.85 -> #REF! | T50: =P50*Q50*R50*0.85 -> #REF!
N51: ДТ СЗМ пробег до карьера + моточасы | O51: км | P51: =VLOOKUP(Q3,'Объекты работ'!$A:$C,2,FALSE) -> 220 | Q51: 0.45 | R51: =VLOOKUP(#REF!,#REF!,16,FALSE)/1000 -> #REF! | S51: =P51*Q51*R51*0.85 -> #REF! | T51: =P51*Q51*R51*0.85 -> #REF! | U51: =P51*Q51*R51*0.85 -> #REF! | V51: =P51*Q51*R51*0.85 -> #REF!
N52: ДТ Луидор пробег + моточасы | O52: км | P52: =VLOOKUP(Q3,'Объекты работ'!$A:$C,3,FALSE) -> 270 | Q52: 0.15 | R52: =VLOOKUP(#REF!,#REF!,16,FALSE)/1000 -> #REF! | S52: =P52*Q52*R52*0.85 -> #REF! | T52: =P52*Q52*R52*0.85 -> #REF! | U52: =P52*Q52*R52*0.85 -> #REF! | V52: =P52*Q52*R52*0.85 -> #REF!
K53: ссылка на справ | N53: ДТ для проезда на карьер на легковом а/м | O53: км | P53: =VLOOKUP(Q3,'Объекты работ'!$A:$C,3,FALSE) -> 270 | Q53: 0.15 | R53: =VLOOKUP(#REF!,#REF!,16,FALSE)/1000 -> #REF! | S53: =P53*Q53*R53*0.85 -> #REF! | T53: =P53*Q53*R53*0.85 -> #REF! | U53: =P53*Q53*R53*0.85 -> #REF! | V53: =P53*Q53*R53*0.85 -> #REF!
M54: 2.5. | N54: Амортизация | S54: =SUBTOTAL(9,S55:S59) -> #REF! | T54: =SUBTOTAL(9,T55:T59) -> #REF! | U54: =SUBTOTAL(9,U55:U59) -> #REF! | V54: =SUBTOTAL(9,V55:V59) -> #REF! | W54: =SUBTOTAL(9,W55:W59) -> 0
N55: Буровая установка УРБ-2Д2 с элементами 2Д3 на шасси КАМАЗ-43118 на модернизированной гидравлической | Q55: =VLOOKUP(N55,#REF!,7,FALSE) -> #REF! | S55: =Q55*$J$33 -> #REF! | T55: =Q55*K33 -> #REF!
N56: СЗМ.TDR.PR-12 на базе шасси КАМАЗ (зав.номер 0340621) | O56: смен | P56: =K34 -> 2 | Q56: =VLOOKUP(N56,#REF!,7,FALSE) -> #REF! | S56: =$P$56*$Q$56 -> #REF! | T56: =$P$56*$Q$56 -> #REF! | U56: =$P$56*$Q$56 -> #REF! | V56: =$P$56*$Q$56 -> #REF!
N57: А/м для перевозки взрывчатых веществ категории EX/II класс опасности 1 на базе шасси ГАЗ-А32R32 | O57: смен | P57: =K34 -> 2 | Q57: =VLOOKUP(N57,#REF!,7,FALSE) -> #REF! | S57: =$P$57*$Q$57 -> #REF! | T57: =$P$57*$Q$57 -> #REF! | U57: =$P$57*$Q$57 -> #REF! | V57: =$P$57*$Q$57 -> #REF!
N58: База и вспомогательное | O58: смен | P58: 1 | Q58: =VLOOKUP(N58,#REF!,7,FALSE) -> #REF! | S58: =$P$58*$Q$58 -> #REF! | T58: =$P$58*$Q$58 -> #REF! | U58: =$P$58*$Q$58 -> #REF! | V58: =$P$58*$Q$58 -> #REF!
K59: ссылка на справ | N59: МПП 5 | Q59: =VLOOKUP(N59,#REF!,7,FALSE) -> #REF! | T59: =K8/1000*Q59 -> #REF! | V59: =T59 -> #REF!
M60: 2.6. | N60: Общепроизводственные затраты | S60: =SUBTOTAL(9,S61:S66) -> 30700 | T60: =SUBTOTAL(9,T61:T66) -> 30700 | U60: =SUBTOTAL(9,U61:U66) -> 13200 | V60: =SUBTOTAL(9,V61:V66) -> 13200 | W60: =SUBTOTAL(9,W61:W66) -> 0
N61: ТО УРБ, СЗМ, Компрессора | S61: 15000 | T61: 15000 | U61: =S61/3 -> 5000 | V61: =T61/3 -> 5000
N62: ОСАГО (УРБ, СВМ, СЗМ) | S62: 500 | T62: 500 | U62: =S62 -> 500 | V62: =T62 -> 500
N63: Содержание базы | S63: 4000 | T63: 4000 | U63: =S63/2 -> 2000 | V63: =T63/2 -> 2000
N64: Запасные части и расходные материалы | S64: 8000 | T64: 8000 | U64: =S64/2 -> 4000 | V64: =T64/2 -> 4000
N65: Спецодежа и СИЗ | S65: 3000 | T65: 3000 | U65: =S65/2 -> 1500 | V65: =T65/2 -> 1500
N66: Проверка технического состояния СЗМ и медосмотр водителей | S66: 200 | T66: 200 | U66: =S66 -> 200 | V66: =T66 -> 200
N67: Производственная себестоимость, руб. | S67: =SUBTOTAL(9,S8:S66) -> #VALUE! | T67: =SUBTOTAL(9,T8:T66) -> #VALUE! | U67: =SUBTOTAL(9,U8:U66) -> #VALUE! | V67: =SUBTOTAL(9,V8:V66) -> #VALUE! | W67: =SUBTOTAL(9,W8:W66) -> 0
N68: Общехозяйственные расходы, руб. | P68: 0.1 | S68: =S67*$P$68 -> #VALUE! | T68: =T67*$P$68 -> #VALUE! | U68: =U67*$P$68 -> #VALUE! | V68: =V67*$P$68 -> #VALUE! | W68: =W67*$P$68 -> 0
N69: Полная себестоимость, руб. | S69: =S67+S68 -> #VALUE! | T69: =T67+T68 -> #VALUE! | U69: =U67+U68 -> #VALUE! | V69: =V67+V68 -> #VALUE! | W69: =W67+W68 -> 0
N70: Рентабельность, % | P70: 0.1 | S70: =S69*$P$70 -> #VALUE! | T70: =T69*$P$70 -> #VALUE! | U70: =U69*$P$70 -> #VALUE! | V70: =V69*$P$70 -> #VALUE! | W70: =W69*$P$70 -> 0
N71: Выручка, руб. (без НДС) | S71: =S69+S70 -> #VALUE! | T71: =T69+T70 -> #VALUE! | U71: =U69+U70 -> #VALUE! | V71: =V69+V70 -> #VALUE! | W71: =W69+W70 -> 0
N72: Цена за 1 м.куб. (без НДС) | S72: =S71/S5 -> #VALUE! | T72: =T71/T5 -> #VALUE! | U72: =U71/U5 -> #VALUE! | V72: =V71/V5 -> #VALUE! | W72: =W71/W5 -> 0
N73: Цена за 1 м.куб. (с НДС) | P73: 0.2 | S73: =S72+S72*$P$73 -> #VALUE! | T73: =T72+T72*$P$73 -> #VALUE! | U73: =U72+U72*$P$73 -> #VALUE! | V73: =V72+V72*$P$73 -> #VALUE! | W73: =W72+W72*$P$73 -> 0

Sheet смета расч. 0,93 1,2 D165
A1: Исходные данные, технические параметры для расчета | Q1: Смета затрат | W1: =#REF! -> #REF! | AA1: проверка расчетов | AC1: =(S7+T7+U7+V7+W7)-S8-T8-U8-V8-W8-W17-V17-U17-T17-S17+S26+T26+U26+V26+W26-S27-S33-S37-S48-S54-S62-T27-T33-T37-T48-T54-T62-U62-U54-U48-U37-U33-U27-V27-V33-V37-V48-V54-V62-W62-W54-W48-W37-W33-W27 -> #VALUE! | AE1: если не 0- ищем ошибку
Q2: на производство взрывных работ на объекте | T2: поставка вм | AC2: =S7+S26-S69+T7+T26-T69+U7+U26-U69+V7+V26-V69+W7+W26-W69 -> #VALUE!
H3: Показатель | I3: Ед.изм | J3: ANFO | K3: EMULS | Q3: "карьер м-ия Ломовское" АО "ТК" | W3: пм
A4: Сетка | B4: 3.7 | C4: 4 | D4: Сетка | E4: 4 | F4: 4 | H4: Объем блока | I4: м3 | J4: =S5 -> 20000 | K4: =T5 -> 20000 | R4: базовый тариф
A5: Глубина | B5: 11.5 | D5: Глубина | E5: 11.5 | H5: Кол-во скважин | I5: шт. | J5: =J4/B7 -> 128.70013 | K5: =K4/E7 -> 119.04762 | N5: К потерь | O5: 1 | R5: Объем справочно, м3 | S5: 20000 | T5: =S5 -> 20000 | U5: =S5 -> 20000 | V5: =T5 -> 20000 | W5: 10000
A6: Удельный | B6: =B8/B7 -> 0.89690868 | D6: Удельный | E6: =E8/E7 -> 1.1358174 | H6: Добавочные скважины | J6: 7 | K6: 7 | M6: № п/п | N6: Наименование | O6: Ед. изм. | P6: Норма const ANFO (кг./л.//1000 м3) | Q6: Норма const EMULS (кг./л.//1000 м3) | R6: Цена (руб./шт, тн) | S6: БВР сухие | T6: БВР обв | U6: ВР сухие | V6: ВР обв | W6: Бурение
A7: Выход | B7: =B4*C4*(B5-$J$18) -> 155.4 | D7: Выход | E7: =E4*F4*(E5-$J$18) -> 168 | H7: Кол-во п.м. | I7: п.м. | J7: =(J5+J6)*A10 -> 1560.5515 | K7: =(K5+K6)*D10 -> 1449.5476 | M7: 1 | N7: Переменные расходы | S7: =SUBTOTAL(9,S9:S25) -> #VALUE! | T7: =SUBTOTAL(9,T9:T25) -> #VALUE! | U7: =SUBTOTAL(9,U9:U25) -> #VALUE! | V7: =SUBTOTAL(9,V9:V25) -> #VALUE! | W7: =SUBTOTAL(9,W8:W17) -> 0
A8: Заряд | B8: =B21+B15 -> 139.37961 | D8: Заряд | E8: =E21+E15 -> 190.81732 | H8: Масса ВВ | I8: кг. | J8: =(J5+J6)*B21 -> 18913.831 | K8: =(K5+K6)*E21 -> 24052.069 | M8: 1.1. | N8: Расходы на ВМ | S8: =SUBTOTAL(9,S9:S16) -> #VALUE! | T8: =SUBTOTAL(9,T9:T16) -> #VALUE! | U8: =SUBTOTAL(9,U9:U16) -> #VALUE! | V8: =SUBTOTAL(9,V9:V16) -> #VALUE! | W8: =SUBTOTAL(9,W9:W16) -> 0
H9: Шашка ДПУ-ПТ600 | I9: шт. | J9: =J5+J6+4 -> 139.70013 | K9: =K5+K6+4 -> 130.04762 | N9: Гранулит АСП-1 | O9: тн | P9: =J32 -> 0.94569154 | Q9: 0 | R9: =VLOOKUP(N9,#REF!,16,0) -> #REF! | S9: =IF(ISERR($P$9*$R$9)," ",($P$9*$R$9))/1000*$S$5 -> #VALUE! | T9: =IF(ISERR($Q$9*$R$9)," ",($Q$9*$R$9))/1000*$T$5 -> #VALUE! | U9: =IF(ISERR($P$9*$R$9)," ",($P$9*$R$9))/1000*$U$5 -> #VALUE! | V9: =IF(ISERR($Q$9*$R$9)," ",($Q$9*$R$9))/1000*$V$5 -> #VALUE!
A10: =B5 -> 11.5 | C10: =A34*25 -> 4.275 | D10: =E5 -> 11.5 | F10: =A34*25 -> 4.275 | H10: Шашка ДПУ-ПТ600 | I10: кг. | J10: =J9*0.65 -> 90.805084 | K10: =K9*0.65 -> 84.530952 | N10: Березит Э-100 Рецептура № 1 | O10: тн | P10: 0 | Q10: =K32 -> 1.2026034 | R10: =VLOOKUP(N10,#REF!,16,0) -> #REF! | S10: =IF(ISERR($P$10*$R$10)," ",($P$10*$R$10))/1000*$S$5 -> #VALUE! | T10: =IF(ISERR($Q$10*$R$10)," ",($Q$10*$R$10))/1000*$T$5 -> #VALUE! | U10: =IF(ISERR($P$10*$R$10)," ",($P$10*$R$10))/1000*$U$5 -> #VALUE! | V10: =IF(ISERR($Q$10*$R$10)," ",($Q$10*$R$10))/1000*$V$5 -> #VALUE!
H11: Аммонит № 6ЖВ-200 | I11: шт. | J11: =J9 -> 139.70013 | K11: =K9 -> 130.04762 | N11: Детонатор промежуточный ДПУ-ПТ600 | O11: =VLOOKUP(N11,#REF!,2,FALSE) -> #REF! | P11: 0 | Q11: =K10/1000 -> 0.084530952 | R11: =VLOOKUP(N11,#REF!,15,0) -> #REF! | S11: =IF(ISERR($P$11*$R$11)," ",($P$11*$R$11)) | T11: =IF(ISERR($Q$11*$R$11)," ",($Q$11*$R$11)) | U11: =IF(ISERR($P$11*$R$11)," ",($P$11*$R$11)) | V11: =IF(ISERR($Q$11*$R$11)," ",($Q$11*$R$11))
H12: Аммонит № 6ЖВ-200 | I12: кг. | J12: =J11*0.4 -> 55.880051 | K12: =K11*0.4 -> 52.019048 | N12: Аммонит № 6ЖВ-200 ГОСТ 21984-76 | O12: =VLOOKUP(N12,#REF!,2,FALSE) -> #REF! | P12: =J12/1000 -> 0.055880051 | Q12: 0 | R12: =VLOOKUP(N12,#REF!,15,0) -> #REF! | S12: =IF(ISERR($P$12*$R$12)," ",($P$12*$R$12)) | T12: =IF(ISERR($Q$12*$R$12)," ",($Q$12*$R$12)) | U12: =IF(ISERR($P$12*$R$12)," ",($P$12*$R$12)) | V12: =IF(ISERR($Q$12*$R$12)," ",($Q$12*$R$12))
H13: С-500-15 | I13: шт. | J13: =J9 -> 139.70013 | K13: =K9 -> 130.04762 | N13: Hitronic II Standard 12 m | O13: =VLOOKUP(N13,#REF!,2,FALSE) -> #REF! | P13: =J13 -> 139.70013 | Q13: =K13 -> 130.04762 | R13: =VLOOKUP(N13,#REF!,15,0) -> #REF! | S13: =IF(ISERR($P$13*$R$13)," ",($P$13*$R$13)) | T13: =IF(ISERR($Q$13*$R$13)," ",($Q$13*$R$13)) | U13: =IF(ISERR($P$13*$R$13)," ",($P$13*$R$13)) | V13: =IF(ISERR($Q$13*$R$13)," ",($Q$13*$R$13))
H14: П-17-5 | I14: шт. | J14: =(J5+J6)/10+2 -> 15.570013 | K14: =(K5+K6)/10+2 -> 14.604762 | N14: 0 | O14: =VLOOKUP(N14,#REF!,2,FALSE) -> #REF! | P14: =J14 -> 15.570013 | Q14: =K14 -> 14.604762 | R14: =VLOOKUP(N14,#REF!,15,0) -> #REF! | S14: =IF(ISERR($P$14*$R$14)," ",($P$14*$R$14)) | T14: =IF(ISERR($Q$14*$R$14)," ",($Q$14*$R$14)) | U14: =IF(ISERR($P$14*$R$14)," ",($P$14*$R$14)) | V14: =IF(ISERR($Q$14*$R$14)," ",($Q$14*$R$14))
H15: П-25-5 | I15: шт. | J15: =J5+J6+2 -> 137.70013 | K15: =K5+K6+2 -> 128.04762 | N15: Провод медный 2-х жильный диаметром 0,60мм на напряжение 24В | O15: =VLOOKUP(N15,#REF!,2,FALSE) -> #REF! | P15: =J17 -> 558.80051 | Q15: =K17 -> 520.19048 | R15: =VLOOKUP(N15,#REF!,15,0) -> #REF! | S15: =IF(ISERR($P$15*$R$15)," ",($P$15*$R$15)) | T15: =IF(ISERR($Q$15*$R$15)," ",($Q$15*$R$15)) | U15: =IF(ISERR($P$15*$R$15)," ",($P$15*$R$15)) | V15: =IF(ISERR($Q$15*$R$15)," ",($Q$15*$R$15))
H16: ЭД-8М1 | I16: шт. | J16: 2 | K16: 2 | N16: Электродетонатор ЭД-8М1 | O16: =VLOOKUP(N16,#REF!,2,FALSE) -> #REF! | P16: =J16 -> 2 | Q16: =K16 -> 2 | R16: =VLOOKUP(N16,#REF!,15,0) -> #REF! | S16: =IF(ISERR($P$16*$R$16)," ",($P$16*$R$16)) | T16: =IF(ISERR($Q$16*$R$16)," ",($Q$16*$R$16)) | U16: =IF(ISERR($P$16*$R$16)," ",($P$16*$R$16)) | V16: =IF(ISERR($Q$16*$R$16)," ",($Q$16*$R$16))
H17: Провод медный | I17: м | J17: =J13*4 -> 558.80051 | K17: =K13*4 -> 520.19048 | M17: 1.2. | N17: Расходы на буровой инструмент | S17: =SUBTOTAL(9,S18:S25) -> 1100 | T17: =SUBTOTAL(9,T18:T25) -> 1100 | U17: =SUBTOTAL(9,U18:U25) -> 0 | V17: =SUBTOTAL(9,V18:V25) -> 0 | W17: =SUBTOTAL(9,W18:W25) -> 0
H18: Перебур | I18: м | J18: 1 | K18: 1 | N18: Пневмоударник DT-H4 DHD340 2-3/8 API Reg | O18: =VLOOKUP(N18,#REF!,2,FALSE) -> #REF! | P18: =J7/J24 -> 0.22293593 | Q18: =K7/K24 -> 0.20707823 | R18: =VLOOKUP(N18,#REF!,15,0) -> #REF! | S18: =IF(ISERR($P$18*$R$18)," ",($P$18*$R$18)) | T18: =IF(ISERR($Q$18*$R$18)," ",($Q$18*$R$18))
H19: Продолж-ть смены | I19: ч | J19: 10 | K19: 10 | N19: Ремкомплект DT-H4 DHD340 (внешний) | O19: =VLOOKUP(N19,#REF!,2,FALSE) -> #REF! | P19: =J7/J25 -> 0.3121103 | Q19: =K7/K25 -> 0.28990952 | R19: =VLOOKUP(N19,#REF!,15,0) -> #REF! | S19: =IF(ISERR($P$19*$R$19)," ",($P$19*$R$19)) | T19: =IF(ISERR($Q$19*$R$19)," ",($Q$19*$R$19))
H20: Скорость проходки | I20: п.м./ч | J20: 14 | K20: 14 | N20: Труба буровая ТБСУ 63,5х6,0х4700 мм | O20: =VLOOKUP(N20,#REF!,2,FALSE) -> #REF! | P20: =J7/J27 -> 0.3121103 | Q20: =K7/K27 -> 0.28990952 | R20: =VLOOKUP(N20,#REF!,15,0) -> #REF! | S20: =IF(ISERR($P$20*$R$20)," ",($P$20*$R$20)) | T20: =IF(ISERR($Q$20*$R$20)," ",($Q$20*$R$20))
B21: =C21*D34 -> 139.37961 | C21: =A10-C10-C15-C18 -> 7.225 | E21: =F21*D36 -> 190.81732 | F21: =D10-F10-F15-F18 -> 7.225 | H21: Произв-ть смены | I21: п.м./см | J21: =J19*J20 -> 140 | K21: =K19*K20 -> 140 | N21: Переводник З-50/З-66м(2паза) | O21: =VLOOKUP(N21,#REF!,2,FALSE) -> #REF! | P21: =J7/10000 -> 0.15605515 | Q21: =K7/10000 -> 0.14495476 | R21: =VLOOKUP(N21,#REF!,15,0) -> #REF! | S21: =IF(ISERR($P$21*$R$21)," ",($P$21*$R$21)) | T21: =IF(ISERR($Q$21*$R$21)," ",($Q$21*$R$21))
H22: Коэф-т исп-я обсадных | I22: % | J22: 0.1 | K22: 0.1 | N22: Труба техническая D125 SDR 26 ТУ 2248-001-49127551-2014 | O22: п.м. | P22: =J7*J22 -> 156.05515 | Q22: =K7*K22 -> 144.95476 | R22: =VLOOKUP(N22,#REF!,15,0) -> #REF! | S22: =IF(ISERR($P$22*$R$22)," ",($P$22*$R$22)) | T22: =IF(ISERR($Q$22*$R$22)," ",($Q$22*$R$22))
B23: АСП | H23: Норм. прох-ки коронки | I23: п.м. | J23: 700 | K23: 700 | N23: Коронка буровая DT-DHD340 125 мм CVD/SBL | O23: =VLOOKUP(N23,#REF!,2,FALSE) -> #REF! | P23: =J7/J23 -> 2.2293593 | Q23: =K7/K23 -> 2.0707823 | R23: =VLOOKUP(N23,#REF!,15,0) -> #REF! | S23: =IF(ISERR($P$23*$R$23)," ",($P$23*$R$23)) | T23: =IF(ISERR($Q$23*$R$23)," ",($Q$23*$R$23))
E24: ЭВВ | H24: Норм. прох-ки ППУ | I24: п.м. | J24: 7000 | K24: 7000
H25: Норм. проходки РК | I25: п.м. | J25: 5000 | K25: 5000 | N25: Доставка инструмента | O25: шт | P25: 0.5 | Q25: 0.5 | R25: 2200 | S25: =IF(ISERR($P$25*$R$25)," ",($P$25*$R$25)) -> 1100 | T25: =IF(ISERR($Q$25*$R$25)," ",($Q$25*$R$25)) -> 1100 | W25: 0
M26: 2 | N26: Постоянные расходы | S26: =SUBTOTAL(9,S28:S68) -> #REF! | T26: =SUBTOTAL(9,T28:T68) -> #REF! | U26: =SUBTOTAL(9,U28:U68) -> #REF! | V26: =SUBTOTAL(9,V28:V68) -> #REF! | W26: =SUBTOTAL(9,W28:W62) -> 0
H27: Норм. проходки штанга | I27: п.м. | J27: 5000 | K27: 5000 | M27: 2.1. | N27: Хранение, производство и доставка ВМ и СИ | S27: =SUBTOTAL(9,S28:S32) -> 48239.682 | T27: =SUBTOTAL(9,T28:T32) -> 95649.697 | U27: =SUBTOTAL(9,U28:U32) -> 48239.682 | V27: =SUBTOTAL(9,V28:V32) -> 95649.697 | W27: =SUBTOTAL(9,W28:W32) -> 0
H28: Непроизв. работа экипажа БУ | I28: см | J28: 1 | K28: 1 | N28: Стоимость хранения | S28: =S5*1.5 -> 30000 | T28: =T5*1.5 -> 30000 | U28: =U5*1.5 -> 30000 | V28: =V5*1.5 -> 30000
H29: Стоимость проживания | I29: руб | J29: 500 | K29: 500 | N29: Доставка , разгрузка ВМ | S29: 5000 | T29: 5000 | U29: 5000 | V29: 5000
H30: Выход ВГМ с 1 п.м. скважины | I30: м3 | J30: =B7/B5 -> 13.513043 | K30: =E7/E5 -> 14.608696 | N30: Энергозатраты на производство ЭВВ Березит | Q30: =Q10 -> 1.2026034 | R30: =$K$40 -> 1821.6 | T30: =K8/1000*R30 -> 43813.249 | V30: =K8/1000*R30 -> 43813.249
H31: Выход ВГМ с 1 п.м. с учетом доп. скв | I31: м3 | J31: =J4/J7 -> 12.815982 | K31: =K4/K7 -> 13.797408 | N31: Разгрузка, перевалка компонентов | P31: =P9 -> 0.94569154 | Q31: =Q10 -> 1.2026034 | R31: 700 | S31: =J8/1000*R31 -> 13239.682 | T31: =K8/1000*R31 -> 16836.448 | U31: =J8/1000*R31 -> 13239.682 | V31: =K8/1000*R31 -> 16836.448
A32: Диаметр заряда, м | D32: Вместимость, кг | H32: Удельный расход с учетом парносближенных | J32: =J8/J4 -> 0.94569154 | K32: =K8/K4 -> 1.2026034 | N32: Роялти
D33: ANFO | H33: Количество смен бурения | I33: см | J33: =J7/J21+J28 -> 12.146796 | K33: =K7/K21+K28 -> 11.353912 | M33: 2.2. | N33: Суточные, вахтовые, проживание | O33: чел | P33: кол-во см.бур. | S33: =SUBTOTAL(9,S34:S36) -> 32322.952 | T33: =SUBTOTAL(9,T34:T36) -> 36178.605 | U33: =SUBTOTAL(9,U34:U36) -> 5600 | V33: =SUBTOTAL(9,V34:V36) -> 11200 | W33: =SUBTOTAL(9,W34:W36) -> 0
A34: 0.171 | D34: =PI()*POWER(A34,2)/4*840 -> 19.291295 | H34: Количество смен заряжания | I34: см | J34: 1 | K34: 2 | N34: Суточные (хчел.*700 руб*х дней) | O34: 4 | R34: 700 | S34: =O34*J34*R34 -> 2800 | T34: =O34*K34*R34 -> 5600 | U34: =S34 -> 2800 | V34: =T34 -> 5600
D35: EMULS | N35: Вахтовые (хчел.*1500 руб*х дней) | O35: 4 | R35: 1500 | S35: =J33*$R$35 -> 18220.194 | T35: =K33*$R$35 -> 17030.867
D36: =PI()*POWER(A34,2)/4*1150 -> 26.410702 | N36: Проживание (хчел.*1000 руб*х дней) | O36: 4 | R36: 700 | S36: =$R$36*(J33+O36) -> 11302.757 | T36: =$R$36*(K33+(K34*O36)) -> 13547.738 | U36: =O36*R36*J34 -> 2800 | V36: =O36*R36*K34 -> 5600
H37: Энергозатраты на тонну ЭМ | M37: 2.3. | N37: Фонд оплаты труда | P37: кол-во чел. | S37: =SUBTOTAL(9,S38:S46) -> 165974.97 | T37: =SUBTOTAL(9,T38:T46) -> 172301.58 | U37: =SUBTOTAL(9,U38:U46) -> 53722.658 | V37: =SUBTOTAL(9,V38:V46) -> 65681.776 | W37: =SUBTOTAL(9,W38:W46) -> 0
H38: Электроэнергия, кВА | I38: 40 | J38: 7.14 | K38: =I38*J38 -> 285.6 | N38: Взрывники | P38: 3 | S38: =(S5*0.25+4500)/0.87*P38 -> 32758.621 | T38: =(T5*0.25+4500)/0.87*P38 -> 32758.621 | U38: =(U5*0.25+4500)/0.87*P38 -> 32758.621 | V38: =(V5*0.25+4500)/0.87*P38 -> 32758.621
H39: Дизельное топливо, л | I39: 32 | J39: 48 | K39: =I39*J39 -> 1536 | N39: Водитель СЗМ | P39: 1 | S39: =(P9*10*300+1500)/0.87 -> 4985.1432 | T39: =(Q10*10*300+3000)/0.87 -> 7595.1843 | U39: =(P9*10*300+2500)/0.87 -> 6134.5685 | V39: =(Q10*10*300+3000)/0.87 -> 7595.1843
K40: =K38+K39 -> 1821.6 | N40: Зав. складом ВМ | P40: 1 | S40: =30000/0.87/15 -> 2298.8506 | T40: =30000/0.87/10 -> 3448.2759 | U40: =30000/0.87/15 -> 2298.8506 | V40: =30000/0.87/10 -> 3448.2759
N41: Экипаж буровой установки | P41: 2 | S41: =J33*P41*3000/0.87 -> 83771.009 | T41: =K33*P41*3000/0.87 -> 78302.838
N42: Начальник бурового участка | P42: 1 | S42: =1*3000/0.87 -> 3448.2759 | T42: =1*3000/0.87 -> 3448.2759
N43: Оператор УМПП | P43: 1 | T43: =K8/11000*3000 -> 6559.6552 | V43: =T43 -> 6559.6552
N44: Итого заработная плата | P44: =SUM(P38:P43) -> 9 | S44: =SUBTOTAL(9,S38:S43) -> 127261.9 | T44: =SUBTOTAL(9,T38:T43) -> 132112.85 | U44: =SUBTOTAL(9,U38:U43) -> 41192.04 | V44: =SUBTOTAL(9,V38:V43) -> 50361.736 | W44: =SUBTOTAL(9,W38:W43) -> 0
N45: Отчисления от несчастного случая | P45: 0.0042 | S45: =S44*$P$45 -> 534.49998 | T45: =T44*$P$45 -> 554.87397 | U45: =U44*$P$45 -> 173.00657 | V45: =V44*$P$45 -> 211.51929
N46: Отчисления в фонды социального страхования | P46: 0.3 | S46: =S44*$P$46 -> 38178.57 | T46: =T44*$P$46 -> 39633.855 | U46: =U44*$P$46 -> 12357.612 | V46: =V44*$P$46 -> 15108.521
N47: Итого отчисления с заработной платы | S47: =SUBTOTAL(9,S45:S46) -> 38713.07 | T47: =SUBTOTAL(9,T45:T46) -> 40188.729 | U47: =SUBTOTAL(9,U45:U46) -> 12530.619 | V47: =SUBTOTAL(9,V45:V46) -> 15320.04 | W47: =SUBTOTAL(9,W45:W46) -> 0
M48: 2.4. | N48: ГСМ на бурение | S48: =SUBTOTAL(9,S49:S53) -> #REF! | T48: =SUBTOTAL(9,T49:T53) -> #REF! | U48: =SUBTOTAL(9,U49:U53) -> #REF! | V48: =SUBTOTAL(9,V49:V53) -> #REF! | W48: =SUBTOTAL(9,W49:W52) -> 0
N49: ГСМ на бурение | O49: л/час | P49: 40 | Q49: 40 | R49: =VLOOKUP($Q$3,'Объекты работ'!$A:$E,6,FALSE)/1000 -> #REF! | S49: =(J33-J28)*J19*P49*R49*0.85 -> #REF! | T49: =($K$33-$K$28)*K19*R49*Q49*0.85 -> #REF!
N50: Мобилизация буровой установки | O50: км | P50: =VLOOKUP(Q3,'Объекты работ'!$A:$C,2,FALSE) -> 220 | Q50: 0.4 | R50: =VLOOKUP($Q$3,'Объекты работ'!$A:$E,6,FALSE)/1000 -> #REF! | S50: =P50*Q50*R50*0.85 -> #REF! | T50: =P50*Q50*R50*0.85 -> #REF!
N51: ДТ СЗМ пробег до карьера + моточасы | O51: км | P51: =VLOOKUP(Q3,'Объекты работ'!$A:$C,2,FALSE) -> 220 | Q51: 0.45 | R51: =VLOOKUP(#REF!,#REF!,16,FALSE)/1000 -> #REF! | S51: =P51*Q51*R51*0.85 -> #REF! | T51: =P51*Q51*R51*0.85 -> #REF! | U51: =P51*Q51*R51*0.85 -> #REF! | V51: =P51*Q51*R51*0.85 -> #REF!
N52: ДТ Луидор пробег + моточасы | O52: км | P52: =VLOOKUP(Q3,'Объекты работ'!$A:$C,3,FALSE) -> 270 | Q52: 0.15 | R52: =VLOOKUP(#REF!,#REF!,16,FALSE)/1000 -> #REF! | S52: =P52*Q52*R52*0.85 -> #REF! | T52: =P52*Q52*R52*0.85 -> #REF! | U52: =P52*Q52*R52*0.85 -> #REF! | V52: =P52*Q52*R52*0.85 -> #REF!
K53: ссылка на справ | N53: ДТ для проезда на карьер на легковом а/м | O53: км | P53: =VLOOKUP(Q3,'Объекты работ'!$A:$C,3,FALSE) -> 270 | Q53: 0.15 | R53: =VLOOKUP(#REF!,#REF!,16,FALSE)/1000 -> #REF! | S53: =P53*Q53*R53*0.85 -> #REF! | T53: =P53*Q53*R53*0.85 -> #REF! | U53: =P53*Q53*R53*0.85 -> #REF! | V53: =P53*Q53*R53*0.85 -> #REF!
M54: 2.5. | N54: Амортизация | S54: =SUBTOTAL(9,S55:S61) -> #REF! | T54: =SUBTOTAL(9,T55:T61) -> #REF! | U54: =SUBTOTAL(9,U55:U61) -> #REF! | V54: =SUBTOTAL(9,V55:V61) -> #REF! | W54: =SUBTOTAL(9,W55:W61) -> 0
N55: Буровая установка УРБ-2Д2 с элементами 2Д3 на шасси КАМАЗ-43118 на модернизированной гидравлической | O55: смен | P55: =J33 -> 12.146796 | Q55: =VLOOKUP(N55,#REF!,7,FALSE) -> #REF! | S55: =Q55*$J$33 -> #REF! | T55: =Q55*K33 -> #REF!
N56: Компрессор XAXS277 CD SQE BOX WUX 691358 | O56: смен | P56: =J33 -> 12.146796 | Q56: =VLOOKUP(N56,#REF!,7,FALSE) -> #REF! | S56: =Q56*$J$33 -> #REF! | T56: =Q56*K33 -> #REF!
N57: СЗМ.TDR.PR-12 на базе шасси КАМАЗ (зав.номер 0340621) | O57: смен | P57: =K34 -> 2 | Q57: =VLOOKUP(N57,#REF!,7,FALSE) -> #REF! | S57: =$P$57*$Q$57 -> #REF! | T57: =$P$57*$Q$57 -> #REF! | U57: =$P$57*$Q$57 -> #REF! | V57: =$P$57*$Q$57 -> #REF!
N58: А/м для перевозки взрывчатых веществ категории EX/II класс опасности 1 на базе шасси ГАЗ-А32R32 | O58: смен | P58: =K34 -> 2 | Q58: =VLOOKUP(N58,#REF!,7,FALSE) -> #REF! | S58: =$P$58*$Q$58 -> #REF! | T58: =$P$58*$Q$58 -> #REF! | U58: =$P$58*$Q$58 -> #REF! | V58: =$P$58*$Q$58 -> #REF!
K59: ссылка на справ | N59: Тягач с КМУ и полуприцепом | O59: смен | P59: 1 | Q59: =VLOOKUP(N59,#REF!,7,FALSE) -> #REF! | T59: =Q59*P59 -> #REF! | V59: =Q59*P59 -> #REF!
N60: База и вспомогательное | O60: смен | P60: 1 | Q60: =VLOOKUP(N60,#REF!,7,FALSE) -> #REF! | S60: =$P$60*$Q$60 -> #REF! | T60: =$P$60*$Q$60 -> #REF! | U60: =$P$60*$Q$60 -> #REF! | V60: =$P$60*$Q$60 -> #REF!
N61: МПП 5 | O61: тн | Q61: =VLOOKUP(N61,#REF!,7,FALSE) -> #REF! | T61: =K8/1000*Q61 -> #REF! | V61: =T61 -> #REF!
M62: 2.6. | N62: Общепроизводственные затраты | S62: =SUBTOTAL(9,S63:S68) -> 45700 | T62: =SUBTOTAL(9,T63:T68) -> 45700 | U62: =SUBTOTAL(9,U63:U68) -> 18200 | V62: =SUBTOTAL(9,V63:V68) -> 18200 | W62: =SUBTOTAL(9,W63:W68) -> 0
N63: ТО УРБ, СЗМ, Компрессора | S63: 30000 | T63: 30000 | U63: =S63/3 -> 10000 | V63: =T63/3 -> 10000
N64: ОСАГО (УРБ, СВМ, СЗМ) | S64: 500 | T64: 500 | U64: =S64 -> 500 | V64: =T64 -> 500
N65: Содержание базы | S65: 4000 | T65: 4000 | U65: =S65/2 -> 2000 | V65: =T65/2 -> 2000
N66: Запасные части и расходные материалы | S66: 8000 | T66: 8000 | U66: =S66/2 -> 4000 | V66: =T66/2 -> 4000
N67: Спецодежа и СИЗ | S67: 3000 | T67: 3000 | U67: =S67/2 -> 1500 | V67: =T67/2 -> 1500
N68: Проверка технического состояния СЗМ и медосмотр водителей | S68: 200 | T68: 200 | U68: =S68 -> 200 | V68: =T68 -> 200
N69: Производственная себестоимость, руб. | S69: =SUBTOTAL(9,S8:S68) -> #VALUE! | T69: =SUBTOTAL(9,T8:T68) -> #VALUE! | U69: =SUBTOTAL(9,U8:U68) -> #VALUE! | V69: =SUBTOTAL(9,V8:V68) -> #VALUE! | W69: =SUBTOTAL(9,W8:W68) -> 0
N70: Общехозяйственные расходы, руб. | P70: 0.1 | S70: =S69*$P$70 -> #VALUE! | T70: =T69*$P$70 -> #VALUE! | U70: =U69*$P$70 -> #VALUE! | V70: =V69*$P$70 -> #VALUE! | W70: =W69*$P$70 -> 0
N71: Полная себестоимость, руб. | S71: =S69+S70 -> #VALUE! | T71: =T69+T70 -> #VALUE! | U71: =U69+U70 -> #VALUE! | V71: =V69+V70 -> #VALUE! | W71: =W69+W70 -> 0
N72: Рентабельность, % | P72: 0.1 | S72: =S71*$P$72 -> #VALUE! | T72: =T71*$P$72 -> #VALUE! | U72: =U71*$P$72 -> #VALUE! | V72: =V71*$P$72 -> #VALUE! | W72: =W71*$P$72 -> 0
N73: Выручка, руб. (без НДС) | S73: =S71+S72 -> #VALUE! | T73: =T71+T72 -> #VALUE! | U73: =U71+U72 -> #VALUE! | V73: =V71+V72 -> #VALUE! | W73: =W71+W72 -> 0
N74: Цена за 1 м.куб. (без НДС) | S74: =S73/S5 -> #VALUE! | T74: =T73/T5 -> #VALUE! | U74: =U73/U5 -> #VALUE! | V74: =V73/V5 -> #VALUE! | W74: =W73/W5 -> 0
N75: Цена за 1 м.куб. (с НДС) | P75: 0.2 | S75: =S74+S74*$P$75 -> #VALUE! | T75: =T74+T74*$P$75 -> #VALUE! | U75: =U74+U74*$P$75 -> #VALUE! | V75: =V74+V74*$P$75 -> #VALUE! | W75: =W74+W74*$P$75 -> 0

Sheet Расчет стоимости БВР
A1: Исходные данные, технические параметры для расчета | Q1: Смета затрат | Y1: =(SUM(S9:S16)+SUM(S18:S18)+SUM(S21:S22)+SUM(S24:S26)+SUM(S28:S37)+SUM(S39:S41)+SUM(S44:S47)+SUM(S49:S52)+SUM(S54:S59))*(100%+$P$61)-S62 -> 0 | Z1: =(SUM(T9:T16)+SUM(T18:T18)+SUM(T21:T22)+SUM(T24:T26)+SUM(T28:T37)+SUM(T39:T41)+SUM(T44:T47)+SUM(T49:T52)+SUM(T54:T59))*(100%+$P$61)-T62 -> 0 | AA1: =(SUM(U9:U16)+SUM(U18:U18)+SUM(U21:U22)+SUM(U24:U26)+SUM(U28:U37)+SUM(U39:U41)+SUM(U44:U47)+SUM(U49:U52)+SUM(U54:U59))*(100%+$P$61)-U62 -> 0 | AB1: =(SUM(V9:V16)+SUM(V18:V18)+SUM(V21:V22)+SUM(V24:V26)+SUM(V28:V37)+SUM(V39:V41)+SUM(V44:V47)+SUM(V49:V52)+SUM(V54:V59))*(100%+$P$61)-V62 -> 0 | AC1: =(SUM(#REF!)+SUM(#REF!)+SUM(#REF!)+SUM(#REF!)+SUM(#REF!)+SUM(#REF!)+SUM(#REF!)+SUM(#REF!)+SUM(#REF!))*(100%+$P$61)-#REF! -> #REF!
Q2: на производство взрывных работ на объекте | Y2: =S62*(100%+$P$63)-S64 -> 0 | Z2: =T62*(100%+$P$63)-T64 -> 0 | AA2: =U62*(100%+$P$63)-U64 -> 0 | AB2: =V62*(100%+$P$63)-V64 -> 0 | AC2: =(#REF!*($P$63))*1.5+#REF!-#REF! -> #REF!
Q3: "карьер Ломовского месторождения" АО "Теплогорский карьер" | Y3: проверка: если не 0 - ошибка в формулах в смете
A4: Сетка | B4: 4 | C4: 4 | D4: Сетка | E4: 3.8 | F4: 3.8
A5: Глубина | B5: 11.5 | D5: Глубина | E5: 11.5 | N5: К потерь | O5: 1
A6: Перебур | B6: 1 | D6: Перебур | E6: 1 | H6: Показатель | I6: Ед.изм | J6: ANFO | K6: EMULS | M6: № п/п | N6: Наименование | O6: Ед. изм. | P6: Норма | Q6: Норма | R6: Цена | S6: БВР сухие | T6: БВР обв | U6: ВР сухие | V6: ВР обв
A7: Удельный | B7: =B9/B8 -> 0.88088363 | D7: Удельный | E7: =E9/E8 -> 1.3362567 | H7: Объем блока | I7: м3 | J7: 30000 | K7: 30000 | M7: 1 | N7: Переменные расходы
A8: Выход | B8: =B4*C4*(B5-$B$6) -> 168 | D8: Выход | E8: =E4*F4*(E5-$E$6) -> 151.62 | H8: Кол-во скважин | I8: шт. | J8: =J7/$B$8 -> 178.57143 | K8: =K7/$E$8 -> 197.86308 | M8: 1.1. | N8: Расходы на ВМ
A9: Заряд | B9: =B22+B16 -> 147.98845 | D9: Заряд | E9: =E22+E16 -> 202.60324 | H9: Процент добавочных скважин | I9: % | J9: 0.03 | K9: 0.03 | N9: ГВВ Гранулит РП | O9: =LOOKUP(N9,ВВ!$A$3:$A$12,ВВ!$B$3:$B$12) -> кг | P9: =$J$35 -> 0.90731014 | Q9: X | R9: =LOOKUP(N9,ВВ!$A$3:$A$12,ВВ!$C$3:$C$12) -> 46 | S9: =P9*J7*R9 -> 1252088 | T9: Х | U9: =S9 -> 1252088 | V9: Х
H10: Добавочные скважины | I10: шт. | J10: =J8*J9 -> 5.3571429 | K10: =K8*K9 -> 5.9358924 | N10: ЭВВ Эверсин-100 | O10: =LOOKUP(N10,ВВ!$A$3:$A$12,ВВ!$B$3:$B$12) -> кг | P10: X | Q10: =K35 -> 1.3763444 | R10: =LOOKUP(N10,ВВ!$A$3:$A$12,ВВ!$C$3:$C$12) -> 48.9 | S10: Х | T10: =K7*Q10*R10 -> 2019097.2 | U10: Х | V10: =T10 -> 2019097.2
A11: =B5 -> 11.5 | C11: =A35*15 -> 2.3484 | D11: =E5 -> 11.5 | F11: =A35*15 -> 2.3484 | H11: Скважины конверта | I11: шт. | J11: 0 | K11: 0 | N11: Детонатор промежуточный "Сферит ДП" - 60 / 1,0 | O11: =LOOKUP(N11,ВВ!$A$3:$A$12,ВВ!$B$3:$B$12) -> кг | P11: =J22/J7*1000 -> 9.8095238 | Q11: Х | R11: =LOOKUP(N11,СВ!A3:A20,СВ!D3:D20) -> 0 | T11: Х | V11: Х
H12: Глубина скважин конверта | I12: м | J12: 0 | K12: 0 | N12: =H22 -> Детонатор промежуточный ДПУ-ПТ600 | O12: =LOOKUP(N12,ВВ!$A$3:$A$12,ВВ!$B$3:$B$12) -> кг | P12: Х | Q12: =K22/K7*1000 -> 10.869278 | S12: Х | U12: X
H13: Кол-во п.м. конверта | I13: п.м. | J13: =J11*J12 -> 0 | K13: =K11*K12 -> 0 | N13: =H28 -> Устройство Искра-С-*-12 | O13: =LOOKUP(N13,ВВ!$A$3:$A$12,ВВ!$B$3:$B$12) -> кг | P13: =J28/J7*1000 -> 6.1922619 | Q13: =K28/K7*1000 -> 6.793299 | R13: =LOOKUP(N13,ВВ!$A$3:$A$12,ВВ!$C$3:$C$12) -> 46 | S13: =IF(ISERR($P$13*$R$13)," ",($P$13*$R$13))/1000*$J$7 -> 8545.3214 | T13: =IF(ISERR($Q$13*$R$13)," ",($Q$13*$R$13))/1000*$K$7 -> 9374.7527 | U13: =IF(ISERR($P$13*$R$13)," ",($P$13*$R$13))/1000*$J$7 -> 8545.3214 | V13: =IF(ISERR($Q$13*$R$13)," ",($Q$13*$R$13))/1000*$K$7 -> 9374.7527
H14: Длина заряда | I14: м | J14: 0 | K14: 0 | N14: =H29 -> Устройство Искра-П-*-5 | O14: =LOOKUP(N14,ВВ!$A$3:$A$12,ВВ!$B$3:$B$12) -> кг | P14: =J29/J7*1000 -> 0.61922619 | Q14: =K29/K7*1000 -> 0.6861232 | R14: =LOOKUP(N14,ВВ!$A$3:$A$12,ВВ!$C$3:$C$12) -> 46 | S14: =IF(ISERR($P$14*$R$14)," ",($P$14*$R$14))/1000*$J$7 -> 854.53214 | T14: =IF(ISERR($Q$14*$R$14)," ",($Q$14*$R$14))/1000*$K$7 -> 946.85002 | U14: =IF(ISERR($P$14*$R$14)," ",($P$14*$R$14))/1000*$J$7 -> 854.53214 | V14: =IF(ISERR($Q$14*$R$14)," ",($Q$14*$R$14))/1000*$K$7 -> 946.85002
H15: Масса ВВ (конверт) | I15: кг. | N15: =H30 -> Устройство Искра-П-*-5 | O15: =LOOKUP(N15,ВВ!$A$3:$A$12,ВВ!$B$3:$B$12) -> кг | P15: =J30/J7*1000 -> 5.5730357 | Q15: =K30/K7*1000 -> 6.1751088 | R15: =LOOKUP(N15,ВВ!$A$3:$A$12,ВВ!$C$3:$C$12) -> 46 | S15: =IF(ISERR($P$15*$R$15)," ",($P$15*$R$15))/1000*$J$7 -> 7690.7893 | T15: =IF(ISERR($Q$15*$R$15)," ",($Q$15*$R$15))/1000*$K$7 -> 8521.6502 | U15: =IF(ISERR($P$15*$R$15)," ",($P$15*$R$15))/1000*$J$7 -> 7690.7893 | V15: =IF(ISERR($Q$15*$R$15)," ",($Q$15*$R$15))/1000*$K$7 -> 8521.6502
H16: Кол-во п.м. | I16: п.м. | J16: =(J8+J10)*B5 -> 2115.1786 | K16: =(K8+K10)*E5 -> 2343.6882 | N16: =H31 -> Устройство ИСКРА-СТАРТ-В-500 | O16: =LOOKUP(N16,ВВ!$A$3:$A$12,ВВ!$B$3:$B$12) -> кг | P16: =J31/J7*1000 -> 0.033333333 | Q16: =K31/K7*1000 -> 0.033333333 | R16: =LOOKUP(N16,ВВ!$A$3:$A$12,ВВ!$C$3:$C$12) -> 46 | S16: =IF(ISERR($P$16*$R$16)," ",($P$16*$R$16))/1000*$J$7 -> 46 | T16: =IF(ISERR($Q$16*$R$16)," ",($Q$16*$R$16))/1000*$K$7 -> 46 | U16: =IF(ISERR($P$16*$R$16)," ",($P$16*$R$16))/1000*$J$7 -> 46 | V16: =IF(ISERR($Q$16*$R$16)," ",($Q$16*$R$16))/1000*$K$7 -> 46
H17: Масса ВВ | I17: кг. | J17: =(J8+J10)*$B$9 -> 27219.304 | K17: =(K8+K10)*$E$9+(K11*K14*K15) -> 41290.331 | M17: 1.2. | N17: Расходы на бурение скважин | S17: =SUBTOTAL(9,S18:S18) -> 2133523.8 | T17: =SUBTOTAL(9,T18:T18) -> 2364015.3 | U17: =SUBTOTAL(9,U18:U18) -> 0 | V17: =SUBTOTAL(9,V18:V18) -> 0 | W17: =#REF! -> #REF! | X17: =W17 -> #REF!
H18: Общее количество скважин | I18: шт. | J18: =J8+J10 -> 183.92857 | K18: =K8+K10 -> 203.79897 | N18: Потребность в бурении | O18: п.м. | P18: =J34 -> 14.1832 | Q18: =K34 -> 12.800338 | R18: ='Расчет стоимости бурения'!D41 -> 1008.6731 | S18: =J7/P18*R18 -> 2133523.8 | T18: =K7/Q18*R18 -> 2364015.3 | U18: Х | V18: Х | W18: =S18/J7 -> 71.117461 | X18: =T18/K7 -> 78.800511
H19: Промежуточные детонаторы основных зарядов | M19: 2 | N19: Постоянные расходы | S19: =SUBTOTAL(9,S21:S59) -> 410987.33 | T19: =SUBTOTAL(9,T21:T59) -> 454706.14 | U19: =SUBTOTAL(9,U21:U59) -> 353165.33 | V19: =SUBTOTAL(9,V21:V59) -> 396884.14
H20: Резервирование | M20: 2.1. | N20: Хранение, производство и доставка ВМ и СИ | S20: =SUBTOTAL(9,S21:S22) -> 51000 | T20: =SUBTOTAL(9,T21:T22) -> 51000 | U20: =SUBTOTAL(9,U21:U22) -> 51000 | V20: =SUBTOTAL(9,V21:V22) -> 51000
H21: Дублирование | I21: X | J21: 2 | K21: 2 | N21: Стоимость хранения | S21: =J7*1.5 -> 45000 | T21: =K7*1.5 -> 45000 | U21: =J7*1.5 -> 45000 | V21: =K7*1.5 -> 45000
B22: =C22*D35 -> 147.98845 | C22: =A11-C11-C16-C19 -> 9.1516 | E22: =F22*D37 -> 202.60324 | F22: =D11-F11-F16-F19 -> 9.1516 | H22: Детонатор промежуточный ДПУ-ПТ600 | I22: кг. | J22: =LOOKUP($H$22,СВ!$A$3:$A$20,СВ!$C$3:$C$20)*$J$18*$J$21 -> 294.28571 | K22: =LOOKUP($H$22,СВ!$A$3:$A$18,СВ!$C$3:$C$18)*$K$18*$K$21 -> 326.07835 | N22: Доставка , разгрузка ВМ | S22: =J7*0.2 -> 6000 | T22: =K7*0.2 -> 6000 | U22: =J7*0.2 -> 6000 | V22: =K7*0.2 -> 6000
H23: Промежуточные детонаторы для зарядов конверта | M23: 2.2. | N23: Суточные, вахтовые, проживание | P23: чел | Q23: чел | S23: =SUBTOTAL(9,S24:S26) -> 5000 | T23: =SUBTOTAL(9,T24:T26) -> 12000 | U23: =SUBTOTAL(9,U24:U26) -> 5000 | V23: =SUBTOTAL(9,V24:V26) -> 12000
B24: АСП | H24: Детонатор промежуточный "Сферит ДП" - 60 / 0,8 | I24: кг. | J24: =LOOKUP(H24,СВ!A3:A20,СВ!C3:C20)*$J$11 -> 0 | K24: =LOOKUP(H24,СВ!A3:A20,СВ!C3:C20)*$K$11 -> 0 | N24: Суточные (хчел.*1000 руб*х дней) | P24: =P28+P29+P31+P32 -> 5 | Q24: =P28+P29+P30+P31+P32 -> 6 | R24: 1000 | S24: =P24*(J36/2)*R24 -> 5000 | T24: =Q24*(K36/2)*R24 -> 6000 | U24: =P24*(J36/2)*R24 -> 5000 | V24: =Q24*(K36/2)*R24 -> 6000
E25: ЭВВ | H25: Средства инициирования | N25: Вахтовые (хчел.*1500 руб*х дней) | S25: Х | T25: Х | U25: Х | V25: Х
H26: Резервирование | I26: % | J26: 1.01 | K26: 1.01 | N26: Проживание (хчел.*1000 руб*х дней) | Q26: =Q24 -> 6 | R26: 1000 | S26: Х | T26: =$R$26*(K36/2)*Q26 -> 6000 | U26: =O26*R26*J33 -> 0 | V26: =$Q$26*(K36/2)*R26 -> 6000
H27: Дублирование | I27: X | J27: 1 | K27: 1 | M27: 2.3. | N27: Фонд оплаты труда | P27: кол-во чел. | Q27: Оклад | R27: Сдельная расценка | S27: =SUBTOTAL(9,S28:S41) -> 193018.38 | T27: =SUBTOTAL(9,T28:T41) -> 229737.19 | U27: =SUBTOTAL(9,U28:U41) -> 193018.38 | V27: =SUBTOTAL(9,V28:V41) -> 229737.19
H28: Устройство Искра-С-*-12 | I28: шт. | J28: =J$18*J27*(J26) -> 185.76786 | K28: =K$18 -> 203.79897 | M28: 1 | N28: Руководитель взрывных работ (мастер БВР) | P28: 1 | Q28: 80000 | R28: 0.25 | S28: =(($J$7*$R$28+$Q$28/5)*$P$28)/0.85 -> 27647.059 | T28: =(($K$7*$R$28+$Q$28/5)*$P$28)/0.85 -> 27647.059 | U28: =(($J$7*$R$28+$Q$28/5)*$P$28)/0.85 -> 27647.059 | V28: =(($K$7*$R$28+$Q$28/5)*$P$28)/0.85 -> 27647.059
H29: Устройство Искра-П-*-5 | I29: шт. | J29: =J$18*0.1*J26 -> 18.576786 | K29: =K$18*0.1*K26 -> 20.583696 | M29: =M28+1 -> 2 | N29: Взрывники | P29: 2 | Q29: 55000 | R29: 0.25 | S29: =(($J$7*$R$29+$Q$29/5)*$P$29)/0.85 -> 43529.412 | T29: =(($K$7*$R$29+$Q$29/5)*$P$29)/0.85 -> 43529.412 | U29: =(($J$7*$R$29+$Q$29/5)*$P$29)/0.85 -> 43529.412 | V29: =(($K$7*$R$29+$Q$29/5)*$P$29)/0.85 -> 43529.412
H30: Устройство Искра-П-*-5 | I30: шт. | J30: =J$18*0.9*J26 -> 167.19107 | K30: =K$18*0.9*K26 -> 185.25326 | M30: =M29+1 -> 3 | N30: Горнорабочий | P30: 1 | Q30: 35000 | R30: 0.15 | S30: Х | T30: =(($K$7*$R$30+$Q$30/5)*$P$30)/0.85 -> 13529.412 | U30: Х | V30: =(($K$7*$R$30+$Q$30/5)*$P$30)/0.85 -> 13529.412
H31: Устройство ИСКРА-СТАРТ-В-500 | I31: шт. | J31: 1 | K31: 1 | M31: =M30+1 -> 4 | N31: Водитель СЗМ | P31: 1 | Q31: 60000 | R31: 0.3 | S31: =(($J$17*$R$31+$Q$31/5)*$P$31)/0.85 -> 23724.46 | T31: =(($K$17*$R$31+$Q$31/5)*$P$31)/0.85 -> 28690.705 | U31: =(($J$17*$R$31+$Q$31/5)*$P$31)/0.85 -> 23724.46 | V31: =(($K$17*$R$31+$Q$31/5)*$P$31)/0.85 -> 28690.705
M32: =M31+1 -> 5 | N32: Водитель доставщика | P32: 1 | Q32: 80000 | R32: 0.3 | S32: =(($J$17*$R$32+$Q$32/5)*$P$32)/0.85 -> 28430.343 | T32: =(($K$17*$R$32+$Q$32/5)*$P$32)/0.85 -> 33396.587 | U32: =(($J$17*$R$32+$Q$32/5)*$P$32)/0.85 -> 28430.343 | V32: =(($K$17*$R$32+$Q$32/5)*$P$32)/0.85 -> 33396.587
A33: Диаметр заряда, м | D33: Вместимость, кг | H33: Выход ВГМ с 1 п.м. скважины | I33: м3 | J33: =$B$8/$B$5 -> 14.608696 | K33: =$B$8/$B$5 -> 14.608696 | M33: =M32+1 -> 6
D34: ANFO | H34: Выход ВГМ с 1 п.м. с учетом доп. скв | I34: м3 | J34: =$J$7/$J$16 -> 14.1832 | K34: =$K$7/$K$16 -> 12.800338 | M34: =M33+1 -> 7
A35: =0.152*1.03 -> 0.15656 | D35: =PI()*POWER(A35,2)/4*840 -> 16.170773 | H35: Удельный расход с учетом парносближенных | J35: =$J$17/$J$7 -> 0.90731014 | K35: =$K$17/$K$7 -> 1.3763444 | M35: =M34+1 -> 8 | W35: =#REF! -> #REF! | X35: =W35 -> #REF!
D36: EMULS | H36: Количество смен заряжания | I36: см | J36: 2 | K36: 2 | M36: =M35+1 -> 9
D37: =PI()*POWER(A35,2)/4*1150 -> 22.138559 | M37: =M36+1 -> 10 | W37: =#REF! -> #REF! | X37: =W37 -> #REF!
N38: Итого заработная плата | P38: =SUM(P28:P37) -> 6 | S38: =SUBTOTAL(9,S28:S37) -> 123331.27 | T38: =SUBTOTAL(9,T28:T37) -> 146793.17 | U38: =SUBTOTAL(9,U28:U37) -> 123331.27 | V38: =SUBTOTAL(9,V28:V37) -> 146793.17
N39: Отчисления от несчастного случая | P39: 0.0042 | S39: =S38*$P$39 -> 517.99135 | T39: =T38*$P$39 -> 616.53133 | U39: =U38*$P$39 -> 517.99135 | V39: =V38*$P$39 -> 616.53133
D40: S | E40: a | F40: b | G40: V | H40: q | I40: ВР | J40: БВР | K40: Цена за метр | N40: Отчисления в фонды социального страхования | P40: 0.3 | S40: =S38*$P$40 -> 36999.382 | T40: =T38*$P$40 -> 44037.952 | U40: =U38*$P$40 -> 36999.382 | V40: =V38*$P$40 -> 44037.952
D41: =E41*F41 -> 12.25 | E41: 3.5 | F41: 3.5 | G41: =E41*F41*($E$5-$E$6) -> 128.625 | H41: =($E$9/G41)*(1+$K$9) -> 1.622401 | I41: 79.3 | J41: 187.5 | K41: 904 | N41: Резерв отпусков | S41: =(S38+S39+S40)/5 -> 32169.729 | T41: =(T38+T39+T40)/5 -> 38289.532 | U41: =(U38+U39+U40)/5 -> 32169.729 | V41: =(V38+V39+V40)/5 -> 38289.532
D42: =E42*F42 -> 12.96 | E42: =E41+0.1 -> 3.6 | F42: =F41+0.1 -> 3.6 | G42: =E42*F42*($E$5-$E$6) -> 136.08 | H42: =($E$9/G42)*(1+$K$9) -> 1.5335195 | I42: 75.47 | J42: 178.05 | K42: 907 | N42: Итого отчисления с заработной платы | S42: =SUBTOTAL(9,S39:S41) -> 69687.103 | T42: =SUBTOTAL(9,T39:T41) -> 82944.015 | U42: =SUBTOTAL(9,U39:U41) -> 69687.103 | V42: =SUBTOTAL(9,V39:V41) -> 82944.015
D43: =E43*F43 -> 13.69 | E43: =E42+0.1 -> 3.7 | F43: =F42+0.1 -> 3.7 | G43: =E43*F43*($E$5-$E$6) -> 143.745 | H43: =($E$9/G43)*(1+$K$9) -> 1.4517467 | I43: 71.94 | J43: 169.11 | K43: 910 | M43: 2.4. | N43: ГСМ на бурение | S43: =SUBTOTAL(9,S44:S47) -> 24480 | T43: =SUBTOTAL(9,T44:T47) -> 24480 | U43: =SUBTOTAL(9,U44:U47) -> 20808 | V43: =SUBTOTAL(9,V44:V47) -> 20808
D44: =E44*F44 -> 14.44 | E44: =E43+0.1 -> 3.8 | F44: =F43+0.1 -> 3.8 | G44: =E44*F44*($E$5-$E$6) -> 151.62 | H44: =($E$9/G44)*(1+$K$9) -> 1.3763444 | I44: 68.69 | J44: 160.88 | K44: 913 | N44: ДТ СЗМ пробег до карьера + моточасы | O44: км | P44: =_xlfn.XLOOKUP($Q$3, 'Объекты работ'!$A$2:$A$29, 'Объекты работ'!$C$2:$C$29) -> 300 | Q44: 0.45 | R44: =_xlfn.XLOOKUP($Q$3, 'Объекты работ'!$A$2:$A$29, 'Объекты работ'!$E$2:$E$29)*0.85/1000 -> 68 | S44: =P44*Q44*R44 -> 9180 | T44: =P44*Q44*R44 -> 9180 | U44: =P44*Q44*R44*0.85 -> 7803 | V44: =P44*Q44*R44*0.85 -> 7803
D45: =E45*F45 -> 15.21 | E45: =E44+0.1 -> 3.9 | F45: =F44+0.1 -> 3.9 | G45: =E45*F45*($E$5-$E$6) -> 159.705 | H45: =($E$9/G45)*(1+$K$9) -> 1.3066675 | I45: 65.69 | J45: 153.27 | K45: 916 | N45: ДТ тягач робег до карьера + моточасы | O45: км | P45: =_xlfn.XLOOKUP($Q$3, 'Объекты работ'!$A$2:$A$29, 'Объекты работ'!$C$2:$C$29) -> 300 | Q45: 0.45 | R45: =_xlfn.XLOOKUP($Q$3, 'Объекты работ'!$A$2:$A$29, 'Объекты работ'!$E$2:$E$29)*0.85/1000 -> 68 | S45: =P45*Q45*R45 -> 9180 | T45: =P45*Q45*R45 -> 9180 | U45: =P45*Q45*R45*0.85 -> 7803 | V45: =P45*Q45*R45*0.85 -> 7803
D46: =E46*F46 -> 16 | E46: =E45+0.1 -> 4 | F46: =F45+0.1 -> 4 | G46: =E46*F46*($E$5-$E$6) -> 168 | H46: =($E$9/G46)*(1+$K$9) -> 1.2421508 | I46: 62.91 | J46: 146.22 | K46: 919 | N46: ДТ Луидор пробег + моточасы | O46: км | P46: =_xlfn.XLOOKUP($Q$3, 'Объекты работ'!$A$2:$A$29, 'Объекты работ'!$C$2:$C$29) -> 300 | Q46: 0.15 | R46: =_xlfn.XLOOKUP($Q$3, 'Объекты работ'!$A$2:$A$29, 'Объекты работ'!$E$2:$E$29)*0.85/1000 -> 68 | S46: =P46*Q46*R46 -> 3060 | T46: =P46*Q46*R46 -> 3060 | U46: =P46*Q46*R46*0.85 -> 2601 | V46: =P46*Q46*R46*0.85 -> 2601
D47: =E47*F47 -> 16.81 | E47: =E46+0.1 -> 4.1 | F47: =F46+0.1 -> 4.1 | G47: =E47*F47*($E$5-$E$6) -> 176.505 | H47: =($E$9/G47)*(1+$K$9) -> 1.182297 | I47: 60.33 | J47: 139.68 | K47: 923 | N47: ДТ для проезда на карьер на легковом а/м | O47: км | P47: =_xlfn.XLOOKUP($Q$3, 'Объекты работ'!$A$2:$A$29, 'Объекты работ'!$C$2:$C$29) -> 300 | Q47: 0.15 | R47: =_xlfn.XLOOKUP($Q$3, 'Объекты работ'!$A$2:$A$29, 'Объекты работ'!$E$2:$E$29)*0.85/1000 -> 68 | S47: =P47*Q47*R47 -> 3060 | T47: =P47*Q47*R47 -> 3060 | U47: =P47*Q47*R47*0.85 -> 2601 | V47: =P47*Q47*R47*0.85 -> 2601
D48: =E48*F48 -> 17.64 | E48: =E47+0.1 -> 4.2 | F48: =F47+0.1 -> 4.2 | G48: =E48*F48*($E$5-$E$6) -> 185.22 | H48: =($E$9/G48)*(1+$K$9) -> 1.1266674 | I48: 57.93 | J48: 133.6 | K48: 926 | M48: 2.5. | N48: Амортизация | S48: =SUBTOTAL(9,S49:S52) -> 59788.955 | T48: =SUBTOTAL(9,T49:T52) -> 59788.955 | U48: =SUBTOTAL(9,U49:U52) -> 59788.955 | V48: =SUBTOTAL(9,V49:V52) -> 59788.955
D49: =E49*F49 -> 18.49 | E49: =E48+0.1 -> 4.3 | F49: =F48+0.1 -> 4.3 | G49: =E49*F49*($E$5-$E$6) -> 194.145 | H49: =($E$9/G49)*(1+$K$9) -> 1.0748736 | I49: 55.7 | J49: 127.95 | K49: 930 | N49: Специализированный автомобиль для перевозки опасных грузов ГАЗ 5796М1 (VIN ***5212) | O49: смен | P49: 2 | Q49: =VLOOKUP(N49,'5.амортизация новая'!$A$5:$J$75,10,0) -> 4984.3189 | S49: =$P$49*$Q$49 -> 9968.6379 | T49: =$P$49*$Q$49 -> 9968.6379 | U49: =$P$49*$Q$49 -> 9968.6379 | V49: =$P$49*$Q$49 -> 9968.6379
D50: =E50*F50 -> 19.36 | E50: =E49+0.1 -> 4.4 | F50: =F49+0.1 -> 4.4 | G50: =E50*F50*($E$5-$E$6) -> 203.28 | H50: =($E$9/G50)*(1+$K$9) -> 1.0265709 | I50: 53.62 | J50: 122.67 | K50: 933 | N50: СЗМ.TDR.PR-12 на базе шасси КАМАЗ (зав.номер 0340621) | O50: смен | P50: 2 | Q50: =VLOOKUP(N50,'5.амортизация новая'!$A$5:$J$75,10,0) -> 9426.0689 | S50: =$P$50*$Q$50 -> 18852.138 | T50: =$P$50*$Q$50 -> 18852.138 | U50: =$P$50*$Q$50 -> 18852.138 | V50: =$P$50*$Q$50 -> 18852.138
D51: =E51*F51 -> 20.25 | E51: =E50+0.1 -> 4.5 | F51: =F50+0.1 -> 4.5 | G51: =E51*F51*($E$5-$E$6) -> 212.625 | H51: =($E$9/G51)*(1+$K$9) -> 0.98145248 | I51: 51.67 | J51: 117.74 | K51: 936 | N51: База и вспомогательное | O51: смен | P51: 1 | Q51: =VLOOKUP(N51,'5.амортизация новая'!$A$5:$J$75,10,0) -> 15539.983 | S51: =$P$51*$Q$51 -> 15539.983 | T51: =$P$51*$Q$51 -> 15539.983 | U51: =$P$51*$Q$51 -> 15539.983 | V51: =$P$51*$Q$51 -> 15539.983
N52: Специальный седельный тягач с КМУ УСТ 54531U (шасси ХТС652255NR462147, VIN: Z0V54531UN5000560) | O52: смен | P52: 1.5 | Q52: =VLOOKUP(N52,'5.амортизация новая'!$A$5:$J$75,10,0) -> 10285.464 | S52: =$P$52*$Q$52 -> 15428.196 | T52: =$P$52*$Q$52 -> 15428.196 | U52: =$P$52*$Q$52 -> 15428.196 | V52: =$P$52*$Q$52 -> 15428.196 | W52: =#REF! -> #REF!
M53: 2.6. | N53: Общепроизводственные затраты | S53: =SUBTOTAL(9,S54:S59) -> 77700 | T53: =SUBTOTAL(9,T54:T59) -> 77700 | U53: =SUBTOTAL(9,U54:U59) -> 23550 | V53: =SUBTOTAL(9,V54:V59) -> 23550
N54: ТОиР СЗМ, Доставщика | S54: 15000 | T54: 15000 | U54: =S54*0.3 -> 4500 | V54: =T54*0.3 -> 4500
N55: ОСАГО (СВМ, СЗМ) | S55: 500 | T55: 500 | U55: =S55*0.5 -> 250 | V55: =T55*0.5 -> 250
N56: Содержание базы | S56: 4000 | T56: 4000 | U56: =S56*0.3 -> 1200 | V56: =T56*0.3 -> 1200
N57: Запасные части и расходные материалы | S57: 55000 | T57: 55000 | U57: =S57*0.3 -> 16500 | V57: =T57*0.3 -> 16500
N58: Спецодежа и СИЗ | S58: 3000 | T58: 3000 | U58: =S58*0.3 -> 900 | V58: =T58*0.3 -> 900
N59: Проверка технического состояния СЗМ и медосмотр водителей | S59: 200 | T59: 200 | U59: =S59 -> 200 | V59: =T59 -> 200
N60: Производственная себестоимость, руб. | S60: =SUBTOTAL(9,S8:S59) -> 3813735.8 | T60: =SUBTOTAL(9,T8:T59) -> 4856707.9 | U60: =SUBTOTAL(9,U8:U59) -> 1622390 | V60: =SUBTOTAL(9,V8:V59) -> 2434870.6
N61: Общехозяйственные расходы, руб. | P61: 0.1 | S61: =S60*$P$61 -> 381373.58 | T61: =T60*$P$61 -> 485670.79 | U61: =U60*$P$61 -> 162239 | V61: =V60*$P$61 -> 243487.06 | W61: =#REF! -> #REF! | X61: =W61 -> #REF!
L62: 4984 | N62: Полная себестоимость, руб. | S62: =S60+S61 -> 4195109.4 | T62: =T60+T61 -> 5342378.7 | U62: =U60+U61 -> 1784629 | V62: =V60+V61 -> 2678357.6
N63: Рентабельность, % | P63: 0.1 | S63: =S62*$P$63 -> 419510.94 | T63: =T62*$P$63 -> 534237.87 | U63: =U62*$P$63 -> 178462.9 | V63: =V62*$P$63 -> 267835.76
N64: Выручка, руб. (без НДС) | S64: =S62+S63 -> 4614620.3 | T64: =T62+T63 -> 5876616.6 | U64: =U62+U63 -> 1963091.9 | V64: =V62+V63 -> 2946193.4
N65: Цена за 1 м.куб. (без НДС) без разделки негабарита | S65: =S64/J7 -> 153.82068 | T65: =T64/K7 -> 195.88722 | U65: =U64/J7 -> 65.436395 | V65: =V64/K7 -> 98.206447
N66: Цена за 1 м.куб. (с НДС) без разделки негабарита | P66: 0.22 | S66: =S65+S65*$P$66 -> 187.66123 | T66: =T65+T65*$P$66 -> 238.98241 | U66: =U65+U65*$P$66 -> 79.832402 | V66: =V65+V65*$P$66 -> 119.81187
N67: Разделка негабарита | P67: =S5*0.1/200 -> 0 | Q67: 33500 | S67: =$P$67*$Q$67 -> 0 | T67: =$P$67*$Q$67 -> 0 | U67: =$P$67*$Q$67 -> 0 | V67: =$P$67*$Q$67 -> 0 | W67: =#REF! -> #REF! | X67: =W67 -> #REF!
N68: Цена за 1 м.куб. (без НДС) с разделкой негабарита | S68: =S65+S67*((100%+$P$61)*(100%+$P$63))/S5 -> #DIV/0! | T68: =T65+T67*((100%+$P$61)*(100%+$P$63))/T5 -> #DIV/0! | U68: =U65+U67*((100%+$P$61)*(100%+$P$63))/U5 -> #DIV/0! | V68: =V65+V67*((100%+$P$61)*(100%+$P$63))/V5 -> #DIV/0!
N69: Цена за 1 м.куб. (с НДС) с разделкой негабарита | P69: 0.2 | S69: =S68+S68*$P$69 -> #DIV/0! | T69: =T68+T68*$P$69 -> #DIV/0! | U69: =U68+U68*$P$69 -> #DIV/0! | V69: =V68+V68*$P$69 -> #DIV/0!
W73: =W17+W35+W37+W52+W61+W67 -> #REF! | X73: =X17+X35+X37+X52+X61+X67 -> #REF!
W74: =#REF! -> #REF! | X74: =W74 -> #REF!
T75: =S67*(100%+$P$61) -> 0 | U75: =T67*(100%+$P$61) -> 0 | V75: =U67*(100%+$P$61) -> 0 | W75: =W73+W74 -> #REF! | X75: =X73+X74 -> #REF!
N76: СТРУКТУРА | T76: =T75*(100%+$P$63) -> 0 | U76: =U75*(100%+$P$63) -> 0 | V76: =V75*(100%+$P$63) -> 0 | W76: =#REF! -> #REF! | X76: =X75*$P$63*1.5 -> #REF!
T77: =T76/S5 -> #DIV/0! | U77: =U76/T5 -> #DIV/0! | V77: =V76/U5 -> #DIV/0! | W77: =W75+W76 -> #REF! | X77: =X75+X76 -> #REF!
P78: проверка: если не 0 - ошибка в формулах в смете | T78: =S68-T77-S65 -> #DIV/0! | U78: =T68-U77-T65 -> #DIV/0! | V78: =U68-V77-U65 -> #DIV/0! | W78: =W77/#REF! -> #REF! | X78: =X77/#REF! -> #REF!
T79: тыс.руб. | U79: % | V79: тыс.руб.
S80: Расходы на ВМ | T80: =S8/1000 -> 0 | U80: =T80/$T$90 -> 0 | V80: =T8/1000 -> 0
S81: Расходы на буровой инструмент | T81: =S17/1000 -> 2133.5238 | U81: =T81/$T$90 -> 0.46234006 | V81: =T17/1000 -> 2364.0153
S82: Хранение, производство и доставка ВМ и СИ | T82: =S20/1000 -> 51 | U82: =T82/$T$90 -> 0.01105183 | V82: =T20/1000 -> 51
S83: Суточные, вахтовые, проживание | T83: =S23/1000 -> 5 | U83: =T83/$T$90 -> 0.0010835128 | V83: =T23/1000 -> 12
S84: Фонд оплаты труда | T84: =S27/1000 -> 193.01838 | U84: =T84/$T$90 -> 0.041827575 | V84: =T27/1000 -> 229.73719
S85: ГСМ на бурение | T85: =S43/1000 -> 24.48 | U85: =T85/$T$90 -> 0.0053048785 | V85: =T43/1000 -> 24.48
S86: Амортизация | T86: =S48/1000 -> 59.788955 | U86: =T86/$T$90 -> 0.012956419 | V86: =T48/1000 -> 59.788955
S87: Общепроизводственные затраты | T87: =S53/1000 -> 77.7 | U87: =T87/$T$90 -> 0.016837788 | V87: =T53/1000 -> 77.7
S88: Общехозяйственные расходы, руб. | T88: =S61/1000 -> 381.37358 | U88: =T88/$T$90 -> 0.082644628 | V88: =T61/1000 -> 485.67079 | W88: =#REF!*1.1 -> #REF!
S89: Рентабельность, % | T89: =S63/1000 -> 419.51094 | U89: =T89/$T$90 -> 0.090909091 | V89: =T63/1000 -> 534.23787 | W89: =W88*1.2 -> #REF!
S90: Выручка, руб. (без НДС) | T90: =S64/1000 -> 4614.6203 | U90: =T90/$T$90 -> 1 | V90: =T64/1000 -> 5876.6166 | W90: =W89/#REF! -> #REF!
S91: проверка: если не 0 - ошибка в формулах в смете | T91: =T90-SUM(T80:T89) -> 1269.2246 | V91: =V90-SUM(V80:V89) -> 2037.9864 | W91: =#REF!-W90-#REF! -> #REF! | Z91: Бурение
S92: проверка: если не 0 - ошибка в формулах в смете | T92: =T90*1000-S64 -> 0 | U92: =U90-100% -> 0 | V92: =V90*1000-T64 -> 0 | W92: тыс.руб. | X92: тыс.руб. | Y92: % | Z92: тыс.руб. | AA92: %
W93: =U8/1000 -> 0 | X93: =V8/1000 -> 0 | Y93: =X93/$X$103 -> 0 | Z93: =#REF!/1000 -> #REF! | AA93: =Z93/$Z$103 -> #REF!
W94: =U17/1000 -> 0 | X94: =V17/1000 -> 0 | Y94: =X94/$X$103 -> 0 | Z94: =#REF!/1000 -> #REF! | AA94: =Z94/$Z$103 -> #REF!
W95: =U20/1000 -> 51 | X95: =V20/1000 -> 51 | Y95: =X95/$X$103 -> 0.017310473 | Z95: =#REF!/1000 -> #REF! | AA95: =Z95/$Z$103 -> #REF!
W96: =U23/1000 -> 5 | X96: =V23/1000 -> 12 | Y96: =X96/$X$103 -> 0.0040730524 | Z96: =#REF!/1000 -> #REF! | AA96: =Z96/$Z$103 -> #REF!
W97: =U27/1000 -> 193.01838 | X97: =V27/1000 -> 229.73719 | Y97: =X97/$X$103 -> 0.077977634 | Z97: =#REF!/1000 -> #REF! | AA97: =Z97/$Z$103 -> #REF!
W98: =U43/1000 -> 20.808 | X98: =V43/1000 -> 20.808 | Y98: =X98/$X$103 -> 0.0070626728 | Z98: =#REF!/1000 -> #REF! | AA98: =Z98/$Z$103 -> #REF!
W99: =U48/1000 -> 59.788955 | X99: =V48/1000 -> 59.788955 | Y99: =X99/$X$103 -> 0.020293629 | Z99: =#REF!/1000 -> #REF! | AA99: =Z99/$Z$103 -> #REF!
W100: =U53/1000 -> 23.55 | X100: =V53/1000 -> 23.55 | Y100: =X100/$X$103 -> 0.0079933653 | Z100: =#REF!/1000 -> #REF! | AA100: =Z100/$Z$103 -> #REF!
W101: =U61/1000 -> 162.239 | X101: =V61/1000 -> 243.48706 | Y101: =X101/$X$103 -> 0.082644628 | Z101: =#REF!/1000 -> #REF! | AA101: =Z101/$Z$103 -> #REF!
W102: =U63/1000 -> 178.4629 | X102: =V63/1000 -> 267.83576 | Y102: =X102/$X$103 -> 0.090909091 | Z102: =#REF!/1000 -> #REF! | AA102: =Z102/$Z$103 -> #REF!
W103: =U64/1000 -> 1963.0919 | X103: =V64/1000 -> 2946.1934 | Y103: =X103/$X$103 -> 1 | Z103: =#REF!/1000 -> #REF! | AA103: =Z103/$Z$103 -> #REF!
...

Sheet Тарифная сетка
C1: Сетка | F1: Стоимость единицы продукции без учета НДС, руб.
A2: Площадь, м2 | B2: Диаметр, м | C2: А, м | D2: B, м | E2: Погонаж, м | F2: ВР на м3 | G2: БВР | H2: БР на п.м. | I2: БР на м3 | J2: Комплекс | K2: Удельный
A3: 12.25 | B3: 0.16 | C3: =SQRT(A3) -> 3.5 | D3: =C3 -> 3.5 | E3: =70027*A3^(-1.006) -> 5631.1956 | F3: =-3.4054*A3+118.76 -> 77.04385 | G3: =1913.2*A3^(-0.927) -> 187.52459 | H3: =(4.0554*A3 + 800)*1.2 -> 1019.6144 | I3: =E3*H3/'Расчет стоимости БВР'!$K$7 -> 191.38827 | J3: =F3+I3 -> 268.43212 | K3: 1.653904
A4: 12.96 | B4: 0.16 | C4: =SQRT(A4) -> 3.6 | D4: =C4 -> 3.6 | E4: =70027*A4^(-1.006) -> 5320.8975 | F4: =-3.4054*A4+118.76 -> 74.626016 | G4: =1913.2*A4^(-0.927) -> 177.98178 | H4: =(4.0554*A4 + 800)*1.2 -> 1023.0696 | I4: =E4*H4/'Расчет стоимости БВР'!$K$7 -> 181.45494 | J4: =F4+I4 -> 256.08096 | K4: 1.5632966
A5: 13.69 | B5: 0.16 | C5: =SQRT(A5) -> 3.7 | D5: =C5 -> 3.7 | E5: =70027*A5^(-1.006) -> 5035.5122 | F5: =-3.4054*A5+118.76 -> 72.140074 | G5: =1913.2*A5^(-0.927) -> 169.1665 | H5: =(4.0554*A5 + 800)*1.2 -> 1026.6221 | I5: =E5*H5/'Расчет стоимости БВР'!$K$7 -> 172.31894 | J5: =F5+I5 -> 244.45901 | K5: 1.479936
A6: 14.44 | B6: 0.16 | C6: =SQRT(A6) -> 3.8 | D6: =C6 -> 3.8 | E6: =70027*A6^(-1.006) -> 4772.4449 | F6: =-3.4054*A6+118.76 -> 69.586024 | G6: =1913.2*A6^(-0.927) -> 161.00582 | H6: =(4.0554*A6 + 800)*1.2 -> 1030.272 | I6: =E6*H6/'Расчет стоимости БВР'!$K$7 -> 163.89721 | J6: =F6+I6 -> 233.48323 | K6: 1.4030695
A7: 15.21 | B7: 0.16 | C7: =SQRT(A7) -> 3.9 | D7: =C7 -> 3.9 | E7: =70027*A7^(-1.006) -> 4529.4298 | F7: =-3.4054*A7+118.76 -> 66.963866 | G7: =1913.2*A7^(-0.927) -> 153.43576 | H7: =(4.0554*A7 + 800)*1.2 -> 1034.0192 | I7: =E7*H7/'Расчет стоимости БВР'!$K$7 -> 156.11724 | J7: =F7+I7 -> 223.08111 | K7: 1.3320397
A8: 16 | B8: 0.16 | C8: =SQRT(A8) -> 4 | D8: =C8 -> 4 | E8: =70027*A8^(-1.006) -> 4304.4812 | F8: =-3.4054*A8+118.76 -> 64.2736 | G8: =1913.2*A8^(-0.927) -> 146.40002 | H8: =(4.0554*A8 + 800)*1.2 -> 1037.8637 | I8: =E8*H8/'Расчет стоимости БВР'!$K$7 -> 148.91549 | J8: =F8+I8 -> 213.18909 | K8: 1.2662702
A9: 16.81 | B9: 0.16 | C9: =SQRT(A9) -> 4.1 | D9: =C9 -> 4.1 | E9: =70027*A9^(-1.006) -> 4095.8534 | F9: =-3.4054*A9+118.76 -> 61.515226 | G9: =1913.2*A9^(-0.927) -> 139.84892 | H9: =(4.0554*A9 + 800)*1.2 -> 1041.8055 | I9: =E9*H9/'Расчет стоимости БВР'!$K$7 -> 142.23609 | J9: =F9+I9 -> 203.75132 | K9: 1.2052542
A10: 17.64 | B10: 0.16 | C10: =SQRT(A10) -> 4.2 | D10: =C10 -> 4.2 | E10: =70027*A10^(-1.006) -> 3902.0061 | F10: =-3.4054*A10+118.76 -> 58.688744 | G10: =1913.2*A10^(-0.927) -> 133.73842 | H10: =(4.0554*A10 + 800)*1.2 -> 1045.8447 | I10: =E10*H10/'Расчет стоимости БВР'!$K$7 -> 136.02975 | J10: =F10+I10 -> 194.71849 | K10: 1.1485444
A11: 18.49 | B11: 0.16 | C11: =SQRT(A11) -> 4.3 | D11: =C11 -> 4.3 | E11: =70027*A11^(-1.006) -> 3721.5768 | F11: =-3.4054*A11+118.76 -> 55.794154 | G11: =1913.2*A11^(-0.927) -> 128.02944 | H11: =(4.0554*A11 + 800)*1.2 -> 1049.9812 | I11: =E11*H11/'Расчет стоимости БВР'!$K$7 -> 130.25286 | J11: =F11+I11 -> 186.04701 | K11: 1.0957449
A12: 19.36 | B12: 0.16 | C12: =SQRT(A12) -> 4.4 | D12: =C12 -> 4.4 | E12: =70027*A12^(-1.006) -> 3553.3561 | F12: =-3.4054*A12+118.76 -> 52.831456 | G12: =1913.2*A12^(-0.927) -> 122.68716 | H12: =(4.0554*A12 + 800)*1.2 -> 1054.2151 | I12: =E12*H12/'Расчет стоимости БВР'!$K$7 -> 124.86672 | J12: =F12+I12 -> 177.69817 | K12: 1.0465043
A13: 20.25 | B13: 0.16 | C13: =SQRT(A13) -> 4.5 | D13: =C13 -> 4.5 | E13: =70027*A13^(-1.006) -> 3396.2679 | F13: =-3.4054*A13+118.76 -> 49.80065 | G13: =1913.2*A13^(-0.927) -> 117.68046 | H13: =(4.0554*A13 + 800)*1.2 -> 1058.5462 | I13: =E13*H13/'Расчет стоимости БВР'!$K$7 -> 119.83689 | J13: =F13+I13 -> 169.63754 | K13: 1.0005098
B16: Примечание | C16: Фактический толеранс по удельному расходу +-0,1 кг/м3

Sheet Расчет стоимости бурения
B1: Объект | C1: "карьер Ломовского месторождения" АО "Теплогорский карьер" | D1: Цена за ед, руб.
B3: Объем буровых работ, м | C3: ='Расчет стоимости БВР'!K16 -> 2343.6882
B5: Диаметр коронки, мм | C5: 152
B6: Тип буровой установки | C6: JK 830-3
B7: Технологическая скорость бурения, м/час | C7: 12
B8: Непроизводительное время в смену, час | C8: 1
B9: Коммерческая скорость бурения, м/смену | C9: =C7*(11-C8) -> 120
B10: Расход дизельного топлива, л/час | C10: =_xlfn.XLOOKUP(C6,Таблица1[Нименование],Таблица1[Норма расхода ДТ, л.]) -> 50
B11: Расход дизельного топлива, л/метр | C11: =C10/C7 -> 4.1666667
B12: Аммортизация, руб./смену | C12: =_xlfn.XLOOKUP('Расчет стоимости бурения'!C6, 'ОС Буровые'!B2:B7, 'ОС Буровые'!G2:G7) -> 11854.167 | D12: =C12*(C20+C21+C22)/C3 -> 113.95846
B13: Расход буровой коронки, метров/шт | C13: 700 | D13: 25000
B14: Расход буровой коронки, шт/метр | C14: =1/C13 -> 0.0014285714 | D14: =C14*D13 -> 35.714286
B15: Расход ППУ, метров/шт | C15: 7000 | D15: 100000
B16: Расход ППУ, шт/метр | C16: =1/C15 -> 0.00014285714 | D16: =C16*D15 -> 14.285714
B17: Расход буровой оснастки, метров/компл. | C17: 15000 | D17: =60000+70000+25000 -> 155000
B18: Расход буровой оснастки (штанги, переводники, ремкомплекты), компл./метр | C18: =1/15000 -> 6.6666667e-05 | D18: =C18*D17 -> 10.333333
B19: Расход обсадной трубы, метр/метр | C19: 0.03 | D19: =C19*450 -> 13.5
B20: Количество смен бурения, смены | C20: =C3/C9 -> 19.530735
B21: Количество смен на ТОиР, смены | C21: 2
B22: Количество смен на прочистку скв., смены | C22: 1
B23: Запасные части, руб. | C23: =C3*30 -> 70310.645 | D23: =C23/C3 -> 30
B24: Расходные материалы (ГСМ, фильтры), руб. | C24: =C3*10 -> 23436.882 | D24: =C24/C3 -> 10
B25: ФОТ основного персонала с НДФЛ, руб | C25: =(C3*150)/0.85 -> 413592.03
B26: Отчисления ФОТ, руб. | C26: =C25*1.42 -> 587300.68 | D26: =C26/C3 -> 250.58824
B27: Цена ДТ, руб./тн | C27: =_xlfn.XLOOKUP(C1, 'Объекты работ'!A2:A29, 'Объекты работ'!E2:E29) -> 80000
B28: Расход ДТ общий, л | C28: =C3*C11 -> 9765.3674
B29: Стоимость ДТ, руб. | C29: =C28*0.85*C27/1000 -> 664044.98 | D29: =C29/C3 -> 283.33333
B30: Расстояние мобилизации, км | C30: =_xlfn.XLOOKUP(C1, 'Объекты работ'!A2:A29, 'Объекты работ'!B2:B29) -> 300
B31: Стоиомсть мобилизации буровой установки, руб. | C31: =C30*450 -> 135000 | D31: =C31/(C3 * 6) -> 9.6002533
B32: Выпуск на линию (тех. осмотр), руб. | C32: =(C20+C21+C22)*2*100 -> 4506.1469 | D32: =C32/C3 -> 1.9226734
B33: Медосмотры, руб. | C33: =C32 -> 4506.1469 | D33: =C33/C3 -> 1.9226734
B34: Суточные/вахтовые, руб.
B35: Питание, руб.
B36: Проживание, руб.
B37: Итого прямые расходы | D37: =D14+D16+D19+D12+D23+D24+D26+D29+D32+D33 -> 755.22537
B38: Общепроизводственные расходы, руб. | C38: 100000 | D38: =C38/C3 -> 42.667792
B39: Накладные расходы, руб. | C39: 100000 | D39: =C39/C3 -> 42.667792
B40: Итого себестоимость | D40: =D37+D38+D39 -> 840.56096
B41: Прибыль, руб. | D41: =D40*1.2 -> 1008.6731
B42: Доля дизельного топлива, % | D42: =C29/C3/D41 -> 0.28089707

Sheet ОС Буровые
A1: № п/п | B1: Нименование | C1: Дата ввода | D1: Первоначальная стоимость, руб. | E1: СПИ | F1: Ам норма/мес, руб. | G1: Ам норма/смену, руб. | H1: Норма расхода ДТ, л.
A2: 1 | B2: Soosan JD-2000 | D2: 34200000 | E2: 60 | F2: =D2/E2 -> 570000 | G2: =F2/40 -> 14250 | H2: 55
A3: 2 | B3: ZEGA D480A | D3: 30000000 | E3: 60 | F3: =D3/E3 -> 500000 | G3: =F3/40 -> 12500 | H3: 55
A4: 3 | B4: JK 830-3 | D4: 28450000 | E4: 60 | F4: =D4/E4 -> 474166.67 | G4: =F4/40 -> 11854.167 | H4: 50
A5: 4 | B5: TM255-T | D5: 18000000 | E5: 60 | F5: =D5/E5 -> 300000 | G5: =F5/40 -> 7500 | H5: 26
A6: 5 | B6: УРБ-2А2 + компрессор | D6: 8500000 | E6: 60 | F6: =D6/E6 -> 141666.67 | G6: =F6/40 -> 3541.6667 | H6: 45
A7: 6 | B7: УРБ-2А2 + компрессор | D7: 5500000 | E7: 60 | F7: =D7/E7 -> 91666.667 | G7: =F7/40 -> 2291.6667 | H7: 30

Sheet Объекты работ
A1: Наименование объекта | B1: Расстояние от базы | C1: Расстояние от склада | E1: цена ДТ за тн без учета НДС
A2: "карьер м-ия Анна" ООО "СУПБ" | B2: 650 | C2: 600
A3: "карьер м-ия С-Саркаевское" ООО "Ергач" | B3: 350 | C3: 410
A4: "карьер м-ия В-Вильвенское" ООО "ГХК" | B4: 270 | C4: 350
A5: "карьер м-ия Заготовкинское" ООО "ГДК" | B5: 100 | C5: 170
A6: "карьер м-ия Ломовское" АО "ТК" | B6: 220 | C6: 270 | E6: 52200
A7: "карьер м-ия гора Матюковая" ПАО "АВИСМА" | B7: 290 | C7: 320
A8: "карьер Чаньвинский" АО "БСЗ" | B8: 320 | C8: 350
A9: "карьер Разепинский" ООО "ПГК" | B9: 300 | C9: 400
A10: "карьер м-ия Дружининское" ООО "АПИ Транзит" | B10: 700 | C10: 800
A11: "карьер м-ия Пудлинговое" ООО "ПуЩЗ" | B11: 570 | C11: 650
A12: "карьер месторождения Чинья-Ворыкское" ООО "Автодор" | B12: 2600 | C12: 2800
A13: "карьер месторождения Бельгопское" ООО "УЗСМ" | B13: 2800 | C13: 3000
A14: "вертолетная площадка Усть-Лыжа" | B14: 3500 | C14: 3700
A15: "карьер месторождения Пикинское" АО "ЧК" | B15: 1600 | C15: 1800
A16: "карьер месторождения Шипичатское" ООО "ВК-Трейд" | B16: 1500 | C16: 1700
A17: "карьер месторождения Пещерное" ООО "СГТ" | B17: 700 | C17: 620
A18: "карьер месторождения Заплотный камень ООО "ЗК" | B18: 620 | C18: 570
... A27: "карьер Малодегтярского месторождения" ООО "МК" | B27: 600 | C27: 700
A28: "карьер Чаньвинского месторождения известняков" АО "БСЗ" | B28: 320 | C28: 360 | E28: 68000
A29: "карьер Ломовского месторождения" АО "Теплогорский карьер" | B29: 300 | C29: 300 | E29: 80000

Sheet Лист5

Sheet расчет 165 4,0х4,5
A1: Исходные данные, технические параметры для расчета | Q1: Смета затрат | Z1: =(SUM(S9:S16)+SUM(S18:S25)+SUM(S28:S32)+SUM(S34:S36)+SUM(S38:S47)+SUM(S49:S50)+SUM(S53:S58)+SUM(S60:S65)+SUM(S67:S72))*(100%+$P$78)-S79 -> 0 | AA1: =(SUM(T9:T16)+SUM(T18:T25)+SUM(T28:T32)+SUM(T34:T36)+SUM(T38:T47)+SUM(T49:T50)+SUM(T53:T58)+SUM(T60:T65)+SUM(T67:T72))*(100%+$P$78)-T79 -> 0 | AB1: =(SUM(U9:U16)+SUM(U18:U25)+SUM(U28:U32)+SUM(U34:U36)+SUM(U38:U47)+SUM(U49:U50)+SUM(U53:U58)+SUM(U60:U65)+SUM(U67:U72))*(100%+$P$78)-U79 -> 0 | AC1: =(SUM(V9:V16)+SUM(V18:V25)+SUM(V28:V32)+SUM(V34:V36)+SUM(V38:V47)+SUM(V49:V50)+SUM(V53:V58)+SUM(V60:V65)+SUM(V67:V72))*(100%+$P$78)-V79 -> 0 | AD1: =(SUM(W9:W16)+SUM(W18:W25)+SUM(W28:W32)+SUM(W34:W36)+SUM(W38:W47)+SUM(W49:W50)+SUM(W53:W58)+SUM(W60:W65)+SUM(W67:W72))*(100%+$P$78)-W79 -> 0
Q2: на производство взрывных работ на объекте | Z2: =S79*(100%+$P$80)-S81 -> 0 | AA2: =T79*(100%+$P$80)-T81 -> 0 | AB2: =U79*(100%+$P$80)-U81 -> 0 | AC2: =V79*(100%+$P$80)-V81 -> 0 | AD2: =(W79*($P$80))*1.5+W79-W81 -> 0
H3: Показатель | I3: Ед.изм | J3: ANFO | K3: EMULS | Q3: ='Объекты работ'!A6 -> "карьер м-ия Ломовское" АО "ТК" | W3: пм | Z3: проверка: если не 0 - ошибка в формулах в смете
A4: Сетка | B4: 3.7 | C4: 4.2 | D4: Сетка | E4: 3.8 | F4: 3.8 | H4: Объем блока | I4: м3 | J4: =S5 -> 30000 | K4: =T5 -> 30000 | R4: базовый тариф
A5: Глубина | B5: 11 | D5: Глубина | E5: 11 | H5: Кол-во скважин | I5: шт. | J5: =J4/B7 -> 203.21073 | K5: =K4/E7 -> 218.69077 | N5: К потерь | O5: 1 | R5: Объем справочно, м3 | S5: 30000 | T5: =S5 -> 30000 | U5: =S5 -> 30000 | V5: =T5 -> 30000 | W5: =S5/((J36+K36)/2) -> 2394.4347
A6: Удельный | B6: =B8/B7 -> 0.86579764 | D6: Удельный | E6: =E8/E7 -> 1.4539711 | H6: Добавочные скважины | I6: шт. | J6: 7 | K6: 7 | M6: № п/п | N6: Наименование | O6: Ед. изм. | P6: Норма const ANFO (кг./л.//1000 м3) | Q6: Норма const EMULS (кг./л.//1000 м3) | R6: Цена (руб./шт, тн) | S6: БВР сухие | T6: БВР обв | U6: ВР сухие | V6: ВР обв | W6: Бурение
A7: Выход | B7: =B4*C4*(B5-$J$23) -> 147.63 | D7: Выход | E7: =E4*F4*(E5-$J$23) -> 137.18 | H7: Скважины конверта | I7: шт. | J7: 0 | K7: 0 | M7: 1 | N7: Переменные расходы
A8: Заряд | B8: =B21+B15 -> 127.81771 | D8: Заряд | E8: =E21+E15 -> 199.45575 | H8: Глубина | I8: м | J8: 0 | K8: 0 | M8: 1.1. | N8: Расходы на ВМ | S8: =SUBTOTAL(9,S9:S16) -> 866372.73 | T8: =SUBTOTAL(9,T9:T16) -> 140858.58 | U8: =SUBTOTAL(9,U9:U16) -> 893935.62 | V8: =SUBTOTAL(9,V9:V16) -> 2367469.5 | W8: =SUBTOTAL(9,W9:W16) -> 0
H9: Кол-во п.м. конверта | I9: п.м. | J9: =J7*J8 -> 0 | K9: =K7*K8 -> 0 | N9: Гранулит АСП-1 | O9: тн | P9: =J37 -> 0.89562177 | Q9: 0 | R9: =VLOOKUP(N9, '3.сырье'!B27:Q35,16,0) -> 22640 | S9: =IF(ISERR($P$9*$R$9)," ",($P$9*$R$9))/1000*$S$5 -> 608306.31 | T9: =IF(ISERR($Q$9*$R$9)," ",($Q$9*$R$9))/1000*$T$5 -> 0 | U9: =IF(ISERR($P$9*$R$9)," ",($P$9*$R$9))/1000*$U$5 -> 608306.31 | V9: =IF(ISERR($Q$9*$R$9)," ",($Q$9*$R$9))/1000*$V$5 -> 0
A10: =B5 -> 11 | C10: =A34*20 -> 3.14 | D10: =E5 -> 11 | F10: =A34*13 -> 2.041 | H10: Длина заряда | I10: м | J10: 0 | K10: 0 | N10: Эмульсионная матрица | O10: тн | P10: 0 | Q10: =K37 -> 1.5005107 | R10: 48.9 | S10: =IF(ISERR($P$10*$R$10)," ",($P$10*$R$10))/1000*$S$5 -> 0 | T10: =IF(ISERR($Q$10*$R$10)," ",($Q$10*$R$10))/1000*$T$5 -> 2201.2493 | U10: =IF(ISERR($P$10*$R$10)," ",($P$10*$R$10))/1000*$U$5 -> 0 | V10: =K4*Q10*R10 -> 2201249.3
H11: Масса ВВ (конверт) | I11: кг. | J11: 0 | K11: =K10*D36 -> 0 | N11: Детонатор промежуточный "Сферит ДП" - 60/1,5 | O11: кг | P11: 0 | Q11: =K15/K4 -> 0.0061250872 | R11: 150 | S11: =IF(ISERR($P$11*$R$11)," ",($P$11*$R$11)) -> 0 | U11: =K4*Q11*R11 -> 27562.893 | V11: =K4*Q11*R11 -> 27562.893
H12: Кол-во п.м. | I12: п.м. | J12: =(J5+J6)*A10 -> 2312.318 | K12: =(K5+K6)*D10+K9 -> 2482.5985 | P12: =J17/1000 -> 0.085684292 | Q12: 0 | S12: =IF(ISERR($P$12*$R$12)," ",($P$12*$R$12)) -> 0 | T12: =IF(ISERR($Q$12*$R$12)," ",($Q$12*$R$12)) -> 0 | U12: =IF(ISERR($P$12*$R$12)," ",($P$12*$R$12)) -> 0 | V12: =IF(ISERR($Q$12*$R$12)," ",($Q$12*$R$12)) -> 0
H13: Масса ВВ | I13: кг. | J13: =(J5+J6)*B21 -> 26868.653 | K13: =(K5+K6)*E21+(K7*K10*K11) -> 45015.322 | N13: Устройство Искра-С-*-12 | P13: =J18 -> 420.42146 | Q13: =K18 -> 225.69077 | R13: =_xlfn.XLOOKUP('расчет 165 4,0х4,5'!N13,СИ!$A$3:$A$491,СИ!$E$3:$E$491,0) -> 335.2 | S13: =IF(ISERR($P$13*$R$13)," ",($P$13*$R$13)) -> 140925.27 | T13: =IF(ISERR($Q$13*$R$13)," ",($Q$13*$R$13)) -> 75651.547 | U13: =IF(ISERR($P$13*$R$13)," ",($P$13*$R$13)) -> 140925.27 | V13: =IF(ISERR($Q$13*$R$13)," ",($Q$13*$R$13)) -> 75651.547
H14: Общее количество скважин | I14: шт. | J14: =J5+J6 -> 210.21073 | K14: =K5+K6 -> 225.69077 | N14: Устройство Искра-П-*-5 | P14: =J19 -> 46.042146 | Q14: =K19 -> 26.569077 | R14: =_xlfn.XLOOKUP('расчет 165 4,0х4,5'!N14,СИ!$A$3:$A$491,СИ!$E$3:$E$491,0) -> 240 | S14: =IF(ISERR($P$14*$R$14)," ",($P$14*$R$14)) -> 11050.115 | T14: =IF(ISERR($Q$14*$R$14)," ",($Q$14*$R$14)) -> 6376.5785 | U14: =IF(ISERR($P$14*$R$14)," ",($P$14*$R$14)) -> 11050.115 | V14: =IF(ISERR($Q$14*$R$14)," ",($Q$14*$R$14)) -> 6376.5785
H15: Детонатор промежуточный "Сферит ДП" - 60 / 1,0 | I15: кг. | J15: =(J14+4)*1.5*2 -> 642.63219 | K15: =(K14+4)*0.8 -> 183.75262 | N15: Устройство Искра-П-*-5 | P15: =J20 -> 380.37931 | Q15: =K20 -> 205.12169 | R15: =_xlfn.XLOOKUP('расчет 165 4,0х4,5'!N15,СИ!$A$3:$A$491,СИ!$E$3:$E$491,0) -> 240 | S15: =IF(ISERR($P$15*$R$15)," ",($P$15*$R$15)) -> 91291.035 | T15: =IF(ISERR($Q$15*$R$15)," ",($Q$15*$R$15)) -> 49229.207 | U15: =IF(ISERR($P$15*$R$15)," ",($P$15*$R$15)) -> 91291.035 | V15: =IF(ISERR($Q$15*$R$15)," ",($Q$15*$R$15)) -> 49229.207
H16: Аммонит № 6ЖВ-200 ГОСТ 21984-76 | I16: шт. | J16: =J14+4 -> 214.21073 | K16: =K14+4 -> 229.69077 | N16: Устройство ИСКРА-СТАРТ-В-500 | O16: =VLOOKUP(N16,'[326]2. ном.справочник ВМ+БИ'!$B$3:$I$46,2,FALSE) -> шт | P16: =J21 -> 2 | Q16: 1 | R16: =_xlfn.XLOOKUP('расчет 165 4,0х4,5'!N16,СИ!$A$3:$A$491,СИ!$E$3:$E$491,0) -> 7400 | S16: =IF(ISERR($P$16*$R$16)," ",($P$16*$R$16)) -> 14800 | T16: =IF(ISERR($Q$16*$R$16)," ",($Q$16*$R$16)) -> 7400 | U16: =IF(ISERR($P$16*$R$16)," ",($P$16*$R$16)) -> 14800 | V16: =IF(ISERR($Q$16*$R$16)," ",($Q$16*$R$16)) -> 7400
H17: Аммонит № 6ЖВ-200 ГОСТ 21984-76 | I17: кг. | J17: =J16*0.4 -> 85.684292 | K17: =K16*0.4 -> 91.876308 | M17: 1.2. | N17: Расходы на буровой инструмент | S17: =SUBTOTAL(9,S18:S25) -> 0 | T17: =SUBTOTAL(9,T18:T25) -> 0 | U17: =SUBTOTAL(9,U18:U25) -> 0 | V17: =SUBTOTAL(9,V18:V25) -> 0 | W17: =SUBTOTAL(9,W18:W25) -> 0
H18: Устройство Искра-С-500-14 | I18: шт. | J18: =J14*2 -> 420.42146 | K18: =K14 -> 225.69077 | N18: Пневмоударник TH6 (QL60) 3-1/2 API Reg | O18: =VLOOKUP(N18,ТМЦ!$B$54:$C$136,2,FALSE) -> шт | P18: =J12/J29 -> 0.33033115 | Q18: =K12/K29 -> 0.35465693 | R18: =VLOOKUP(N18,ТМЦ!$B$3:$P$132,15,0) -> 89587
H19: Устройство Искра-П-25-4,4 | I19: шт. | J19: =2*J14*0.1+4 -> 46.042146 | K19: =K14*0.1+4 -> 26.569077 | N19: Ремкомплект DT-H6 D QL 60 3-1/2 API Reg | O19: =VLOOKUP(N19,ТМЦ!$B$54:$C$136,2,FALSE) -> шт | P19: =J12/J30 -> 0.4624636 | Q19: =K12/K30 -> 0.4965197 | R19: =VLOOKUP(N19,ТМЦ!$B$3:$P$132,15,0) -> 12000
H20: Устройство Искра-П-42-6 | I20: шт. | J20: =2*J14*0.9+2 -> 380.37931 | K20: =K14*0.9+2 -> 205.12169 | N20: Труба буровая 114х9х6000 2-3/8 API Reg | O20: =VLOOKUP(N20,ТМЦ!$B$54:$C$136,2,FALSE) -> шт | P20: =J12/J32 -> 0.4624636 | Q20: =K12/K32 -> 0.4965197 | R20: =VLOOKUP(N20,ТМЦ!$B$3:$P$132,15,0) -> 58000
B21: =C21*D34 -> 127.81771 | C21: =A10-C10-C15-C18 -> 7.86 | E21: =F21*D36 -> 199.45575 | F21: =D10-F10-F15-F18 -> 8.959 | H21: Электродетонатор ЭД-8М1 | I21: шт. | J21: 2 | K21: 2 | N21: 0 | O21: =VLOOKUP(N21,ТМЦ!$B$54:$C$136,2,FALSE) -> 0 | R21: =VLOOKUP(N21,ТМЦ!$B$3:$P$132,15,0) -> 0
N22: Труба техническая D180*6.9 SDR 26 (п.м.) | O22: =VLOOKUP(N22,ТМЦ!$B$54:$C$136,2,FALSE) -> м | P22: =J12*J27 -> 69.369541 | Q22: =K12*K27 -> 74.477955 | R22: =VLOOKUP(N22,ТМЦ!$B$3:$P$132,15,0) -> 415
B23: АСП | H23: Перебур | I23: м | J23: 1.5 | K23: 1.5 | N23: Коронка буровая QL60 165мм сфера | O23: =VLOOKUP(N23,ТМЦ!$B$54:$C$136,2,FALSE) -> шт | P23: =J12/J28 -> 3.3033115 | Q23: =K12/K28 -> 3.5465693 | R23: =VLOOKUP(N23,ТМЦ!$B$3:$P$132,15,0) -> 29200
E24: ЭВВ | H24: Продолж-ть смены | I24: ч | J24: 10 | K24: 10
H25: Экспл.скорость | I25: п.м./ч | J25: 11 | K25: 11 | N25: Доставка инструмента | O25: шт | P25: 0.5 | Q25: 0.5 | R25: 2200
H26: Среднетех.скорость | I26: п.м./см | J26: =J24*J25 -> 110 | K26: =K24*K25 -> 110 | M26: 2 | N26: Постоянные расходы
H27: Коэф-т исп-я обсадных | I27: % | J27: 0.03 | K27: 0.03 | M27: 2.1. | N27: Хранение, производство и доставка ВМ и СИ | S27: =SUM(S28:S32) -> 55000 | T27: =SUM(T28:T32) -> 55000 | U27: =SUM(U28:U32) -> 55000 | V27: =SUM(V28:V32) -> 55000
H28: Норм. прох-ки коронки | I28: п.м. | J28: 700 | K28: 700 | N28: Стоимость хранения | S28: =S5*1.5 -> 45000 | T28: =T5*1.5 -> 45000 | U28: =U5*1.5 -> 45000 | V28: =V5*1.5 -> 45000
H29: Норм. прох-ки ППУ | I29: п.м. | J29: 7000 | K29: 7000 | N29: Доставка , разгрузка ВМ | S29: 10000 | T29: 10000 | U29: 10000 | V29: 10000
H30: Норм. проходки РК | I30: п.м. | J30: 5000 | K30: 5000 | N30: Энергозатраты на производство ЭВВ Березит
N31: Разгрузка, перевалка компонентов
A32: Диаметр заряда, м | D32: Вместимость, кг | H32: Норм. проходки штанга | I32: п.м. | J32: 5000 | K32: 5000 | N32: Роялти
D33: ANFO | H33: Непроизв. работа экипажа БУ | I33: см | J33: 2 | K33: 2 | M33: 2.2. | N33: Суточные, вахтовые, проживание | O33: чел | P33: кол-во см.бур. | S33: =SUM(S34:S36) -> 8700 | T33: =SUM(T34:T36) -> 8700 | U33: =SUM(U34:U36) -> 8700 | V33: =SUM(V34:V36) -> 8700
A34: 0.157 | D34: =PI()*POWER(A34,2)/4*840 -> 16.261795 | H34: Стоимость проживания | I34: руб | J34: 500 | K34: 500 | N34: Суточные (хчел.*700 руб*х дней) | O34: =P38+P39+P41+P42 -> 3 | R34: 700 | S34: =O34*J39*R34 -> 4200 | T34: =O34*K39*R34 -> 4200 | U34: =S34 -> 4200 | V34: =T34 -> 4200
D35: EMULS | H35: Выход ВГМ с 1 п.м. скважины | I35: м3 | J35: =B7/B5 -> 13.420909 | K35: =E7/E5 -> 12.470909 | N35: Вахтовые (хчел.*1500 руб*х дней) | O35: 4
D36: =PI()*POWER(A34,2)/4*1150 -> 22.263171 | H36: Выход ВГМ с 1 п.м. с учетом доп. скв | I36: м3 | J36: =J4/J12 -> 12.973994 | K36: =K4/K12 -> 12.084113 | N36: Проживание (хчел.*1000 руб*х дней) | O36: =O34 -> 3 | R36: 1500 | S36: =R36*O36 -> 4500 | T36: =S36 -> 4500 | U36: =T36 -> 4500 | V36: =U36 -> 4500
H37: Удельный расход с учетом парносближенных | J37: =J13/J4 -> 0.89562177 | K37: =K13/K4 -> 1.5005107 | M37: 2.3. | N37: Фонд оплаты труда | P37: кол-во чел. | Q37: Оклад | R37: Сдельная расценка | S37: =S48+S51 -> 133418.16 | T37: =T48+T51 -> 133418.16 | U37: =U48+U51 -> 133418.16 | V37: =V48+V51 -> 133418.16
H38: Количество смен бурения | I38: см | J38: =J12/J26+J33 -> 23.021073 | K38: =K12/K26+K33 -> 24.569077 | M38: 1 | N38: Руководитель взрывных работ | P38: 1 | Q38: 30000 | S38: =Q38*P38/0.87 -> 34482.759 | T38: =S38 -> 34482.759 | U38: =T38 -> 34482.759 | V38: =U38 -> 34482.759
H39: Количество смен заряжания | I39: см | J39: 2 | K39: 2 | M39: =M38+1 -> 2 | N39: Взрывники | P39: 2 | Q39: 20000 | S39: =Q39*P39/0.87 -> 45977.011 | T39: =S39 -> 45977.011 | U39: =T39 -> 45977.011 | V39: =U39 -> 45977.011
M40: =M39+1 -> 3 | N40: Горнорабочий | P40: 3 | Q40: 5000 | S40: =Q40*P40/0.87 -> 17241.379 | T40: =S40 -> 17241.379 | U40: =T40 -> 17241.379 | V40: =U40 -> 17241.379
M41: =M40+1 -> 4 | N41: Водитель СЗМ | P41: 0 | Q41: 25000 | S41: =Q41*P41/0.87 -> 0 | T41: =S41 -> 0 | U41: =T41 -> 0 | V41: =U41 -> 0
H42: Энергозатраты на тонну ЭМ | M42: =M41+1 -> 5 | N42: Водитель доставщика | P42: 0 | Q42: 30000 | S42: =Q42*P42/0.87 -> 0 | T42: =S42 -> 0 | U42: =T42 -> 0 | V42: =U42 -> 0
H43: Электроэнергия, кВА | I43: 40 | J43: 8.14 | K43: =I43*J43 -> 325.6 | M43: =M42+1 -> 6 | N43: Зав. складом ВМ | P43: 1 | Q43: 4000 | S43: =Q43*P43/0.87 -> 4597.7011 | T43: =S43 -> 4597.7011 | U43: =T43 -> 4597.7011 | V43: =U43 -> 4597.7011
H44: Дизельное топливо, л | I44: 32 | J44: 64.5 | K44: =I44*J44 -> 2064 | M44: =M43+1 -> 7
K45: =K43+K44 -> 2389.6 | M45: =M44+1 -> 8
M46: =M45+1 -> 9
M47: =M46+1 -> 10
N48: Итого заработная плата | P48: =SUM(P38:P47) -> 7 | S48: =SUM(S38:S47) -> 102298.85 | T48: =SUBTOTAL(9,T38:T47) -> 102298.85 | U48: =SUBTOTAL(9,U38:U47) -> 102298.85 | V48: =SUBTOTAL(9,V38:V47) -> 102298.85
N49: Отчисления от несчастного случая | P49: 0.0042 | S49: =S48*$P$49 -> 429.65517 | T49: =T48*$P$49 -> 429.65517 | U49: =U48*$P$49 -> 429.65517 | V49: =V48*$P$49 -> 429.65517
N50: Отчисления в фонды социального страхования | P50: 0.3 | S50: =S48*$P$50 -> 30689.655 | T50: =T48*$P$50 -> 30689.655 | U50: =U48*$P$50 -> 30689.655 | V50: =V48*$P$50 -> 30689.655
N51: Итого отчисления с заработной платы | S51: =SUBTOTAL(9,S49:S50) -> 31119.31 | T51: =SUBTOTAL(9,T49:T50) -> 31119.31 | U51: =SUBTOTAL(9,U49:U50) -> 31119.31 | V51: =SUBTOTAL(9,V49:V50) -> 31119.31
I52: Норма на м3 | J52: Литры | K52: Цена | L52: Стоимость | M52: 2.4. | N52: Дизельное топливо | S52: =SUM(S53:S58) -> 24200 | T52: =SUM(T53:T58) -> 24200 | U52: =SUM(U53:U58) -> 24200 | V52: =SUM(V53:V58) -> 24200
H53: Потребность в дизельном топливе для БУ | I53: 0.4 | J53: =K4*I53 -> 12000 | K53: 47 | L53: =J53*K53 -> 564000
N54: ДТ МСЗ пробег до карьера + моточасы | O54: км | P54: 220 | Q54: 1 | R54: 50 | S54: =P54*R54 -> 11000 | T54: =S54 -> 11000 | U54: =T54 -> 11000 | V54: =U54 -> 11000
N55: ДТ ДВМ пробег + моточасы | O55: км | P55: 220 | Q55: 1 | R55: 15 | S55: =P55*Q55*R55 -> 3300 | T55: =S55 -> 3300 | U55: =T55 -> 3300 | V55: =U55 -> 3300
N56: ДТ Легковой автомобиль | O56: км | P56: 220 | Q56: 3 | R56: 15 | S56: =P56*Q56*R56 -> 9900 | T56: =S56 -> 9900 | U56: =T56 -> 9900 | V56: =U56 -> 9900
M59: 2.5. | N59: Амортизация | S59: =SUM(S60:S65) -> 4880.9524 | T59: =SUM(T60:T65) -> 4880.9524 | U59: =SUM(U60:U65) -> 4880.9524 | V59: =SUM(V60:V65) -> 4880.9524
N60: Машина смесительно-зарядная | O60: смен | P60: 0 | Q60: {=_xlfn.XLOOKUP(N60,'Амортизация ОС'!$B$2:$B$41,'Амортизация ОС'!$I$2:I$41,0)} -> 12500 | S60: =Q60*P60 -> 0 | T60: =S60 -> 0 | U60: =T60 -> 0 | V60: =U60 -> 0
N61: Автомобиль легковой специализироованный для перевозки ВМ | O61: смен | P61: 2 | Q61: {=_xlfn.XLOOKUP(N61,'Амортизация ОС'!$B$2:$B$41,'Амортизация ОС'!$I$2:I$41,0)} -> 2440.4762 | S61: =P61*Q61 -> 4880.9524 | T61: =S61 -> 4880.9524 | U61: =T61 -> 4880.9524 | V61: =U61 -> 4880.9524
H62: Поставить амортизационную норму для недавно приобретенной машины | L62: 4984 | N62: Установка буровая самоходная | O62: смен | P62: 0 | Q62: {=_xlfn.XLOOKUP(N62,'Амортизация ОС'!$B$2:$B$41,'Амортизация ОС'!$I$2:I$41,0)} -> 17857.143 | S62: =$P$62*$Q$62 -> 0 | T62: =$P$62*$Q$62 -> 0 | U62: =$P$62*$Q$62 -> 0 | V62: =$P$62*$Q$62 -> 0
O63: смен | Q63: {=_xlfn.XLOOKUP(N63,'Амортизация ОС'!$B$2:$B$41,'Амортизация ОС'!$H$2:H$41,0)} -> 0 | S63: =$P$63*$Q$63 -> 0 | T63: =$P$63*$Q$63 -> 0 | U63: =$P$63*$Q$63 -> 0 | V63: =$P$63*$Q$63 -> 0
O64: смен | Q64: {=_xlfn.XLOOKUP(N64,'Амортизация ОС'!$B$2:$B$41,'Амортизация ОС'!$H$2:H$41,0)} -> 0 | S64: =$P$64*$Q$64 -> 0 | T64: =$P$64*$Q$64 -> 0 | U64: =$P$64*$Q$64 -> 0 | V64: =$P$64*$Q$64 -> 0
O65: смен | Q65: {=_xlfn.XLOOKUP(N65,'Амортизация ОС'!$B$2:$B$41,'Амортизация ОС'!$H$2:H$41,0)} -> 0 | S65: =$P$65*$Q$65 -> 0 | T65: =$P$65*$Q$65 -> 0 | U65: =$P$65*$Q$65 -> 0 | V65: =$P$65*$Q$65 -> 0
M66: 2.6. | N66: Общепроизводственные затраты | S66: =SUM(S67:S72) -> 66000 | T66: =SUM(T67:T72) -> 66000 | U66: =SUM(U67:U72) -> 66000 | V66: =SUM(V67:V72) -> 31000
N67: ТОиР Материалы | S67: 30000 | T67: =S67 -> 30000 | U67: =T67 -> 30000 | V67: 10000
N68: ТОиР Сервис | S68: 20000 | T68: =S68 -> 20000 | U68: =T68 -> 20000 | V68: 10000
N69: Амортизация ОПР | S69: 10000 | T69: =S69 -> 10000 | U69: =T69 -> 10000 | V69: 5000
N71: Спецодежа и СИЗ | S71: 3000 | T71: =S71 -> 3000 | U71: =T71 -> 3000 | V71: =U71 -> 3000
N72: Выпуск на линию и сменный медосмотр | S72: 3000 | T72: =S72 -> 3000 | U72: =S72 -> 3000 | V72: =T72 -> 3000
M73: 2.7. | N73: Услуги производственного харатера
N74: Услуги тралла | Q74: 60000
N75: Услуги гидросмолота
N77: Производственная себестоимость, руб. | S77: =S8+S27+S33+S37+S52+S59+S66 -> 1158571.8 | T77: =T8+T27+T33+T37+T52+T59+T66 -> 433057.69 | U77: =U8+U27+U33+U37+U52+U59+U66 -> 1186134.7 | V77: =V8+V27+V33+V37+V52+V59+V66 -> 2624668.6
N78: Общехозяйственные расходы, руб. | P78: 0.05 | S78: =S77*$P$78 -> 57928.592 | T78: =T77*$P$78 -> 21652.885 | U78: =U77*$P$78 -> 59306.737 | V78: =V77*$P$78 -> 131233.43 | W78: =W77*$P$78 -> 0
N79: Полная себестоимость, руб. | S79: =S77+S78 -> 1216500.4 | T79: =T77+T78 -> 454710.58 | U79: =U77+U78 -> 1245441.5 | V79: =V77+V78 -> 2755902 | W79: =W77+W78 -> 0
N80: Рентабельность, % | P80: 0.05 | S80: =S79*$P$80 -> 60825.022 | T80: =T79*$P$80 -> 22735.529 | U80: =U79*$P$80 -> 62272.074 | V80: =V79*$P$80 -> 137795.1 | W80: =W79*$P$80*1.5 -> 0
N81: Выручка, руб. (без НДС) | S81: =S79+S80 -> 1277325.5 | T81: =T79+T80 -> 477446.11 | U81: =U79+U80 -> 1307713.5 | V81: =V79+V80 -> 2893697.1 | W81: =W79+W80 -> 0
N82: Цена за 1 м.куб. (без НДС) без разделки негабарита | S82: =S81/S5 -> 42.577515 | T82: =T81/T5 -> 15.91487 | U82: =U81/U5 -> 43.590452 | V82: =V81/V5 -> 96.456571 | W82: =W81/W5 -> 0
N83: Цена за 1 м.куб. (с НДС) без разделки негабарита | P83: 0.22 | S83: =S82+S82*$P$83 -> 51.944569 | T83: =T82+T82*$P$83 -> 19.416142 | U83: =U82+U82*$P$83 -> 53.180351 | V83: =V82+V82*$P$83 -> 117.67702 | W83: =W82+W82*$P$83 -> 0
N84: Разделка негабарита | S84: =$P$84*$Q$84 -> 0 | T84: =$P$84*$Q$84 -> 0 | U84: =$P$84*$Q$84 -> 0 | V84: =$P$84*$Q$84 -> 0
N85: Цена за 1 м.куб. (без НДС) с разделкой негабарита | S85: =S82+S84*((100%+$P$78)*(100%+$P$80))/S5 -> 42.577515 | T85: =T82+T84*((100%+$P$78)*(100%+$P$80))/T5 -> 15.91487 | U85: =U82+U84*((100%+$P$78)*(100%+$P$80))/U5 -> 43.590452 | V85: =V82+V84*((100%+$P$78)*(100%+$P$80))/V5 -> 96.456571 | W85: =W82+W84*((100%+$P$78)*(100%+$P$80))/W5 -> 0
N86: Цена за 1 м.куб. (с НДС) с разделкой негабарита | P86: 0.2 | S86: =S85+S85*$P$86 -> 51.093018 | T86: =T85+T85*$P$86 -> 19.097844 | U86: =U85+U85*$P$86 -> 52.308542 | V86: =V85+V85*$P$86 -> 115.74789 | W86: =W85+W85*$P$86 -> 0
X88: =W84*1.1 -> 0
X89: =X88*1.2 -> 0
X90: =X89/W5 -> 0
X91: =W85-X90-W82 -> 0 | AA91: Бурение
T92: =S84*(100%+$P$78) -> 0 | U92: =T84*(100%+$P$78) -> 0 | V92: =U84*(100%+$P$78) -> 0 | W92: =V84*(100%+$P$78) -> 0 | X92: тыс.руб. | Y92: тыс.руб. | Z92: % | AA92: тыс.руб. | AB92: %
N93: СТРУКТУРА | T93: =T92*(100%+$P$80) -> 0 | U93: =U92*(100%+$P$80) -> 0 | V93: =V92*(100%+$P$80) -> 0 | W93: =W92*(100%+$P$80) -> 0 | X93: =U8/1000 -> 893.93562 | Y93: =V8/1000 -> 2367.4695 | Z93: =Y93/$Y$103 -> 0.81814695 | AA93: =W8/1000 -> 0 | AB93: =AA93/$AA$103 -> #DIV/0!
T94: =T93/S5 -> 0 | U94: =U93/T5 -> 0 | V94: =V93/U5 -> 0 | W94: =W93/V5 -> 0 | X94: =U17/1000 -> 0 | Y94: =V17/1000 -> 0 | Z94: =Y94/$Y$103 -> 0 | AA94: =W17/1000 -> 0 | AB94: =AA94/$AA$103 -> #DIV/0!
P95: проверка: если не 0 - ошибка в формулах в смете | T95: =S85-T94-S82 -> 0 | U95: =T85-U94-T82 -> 0 | V95: =U85-V94-U82 -> 0 | W95: =V85-W94-V82 -> 0 | X95: =U27/1000 -> 55 | Y95: =V27/1000 -> 55 | Z95: =Y95/$Y$103 -> 0.019006827 | AA95: =W27/1000 -> 0 | AB95: =AA95/$AA$103 -> #DIV/0!
T96: тыс.руб. | U96: % | V96: тыс.руб. | W96: % | X96: =U33/1000 -> 8.7 | Y96: =V33/1000 -> 8.7 | Z96: =Y96/$Y$103 -> 0.0030065344 | AA96: =W33/1000 -> 0 | AB96: =AA96/$AA$103 -> #DIV/0!
S97: Расходы на ВМ | T97: =S8/1000 -> 866.37273 | U97: =T97/$T$107 -> 0.67827093 | V97: =T8/1000 -> 140.85858 | W97: =V97/$V$107 -> 0.29502509 | X97: =U37/1000 -> 133.41816 | Y97: =V37/1000 -> 133.41816 | Z97: =Y97/$Y$103 -> 0.04610647 | AA97: =W37/1000 -> 0 | AB97: =AA97/$AA$103 -> #DIV/0!
S98: Расходы на буровой инструмент | T98: =S17/1000 -> 0 | U98: =T98/$T$107 -> 0 | V98: =T17/1000 -> 0 | W98: =V98/$V$107 -> 0 | X98: =U52/1000 -> 24.2 | Y98: =V52/1000 -> 24.2 | Z98: =Y98/$Y$103 -> 0.0083630038 | AA98: =W52/1000 -> 0 | AB98: =AA98/$AA$103 -> #DIV/0!
S99: Хранение, производство и доставка ВМ и СИ | T99: =S27/1000 -> 55 | U99: =T99/$T$107 -> 0.043058721 | V99: =T27/1000 -> 55 | W99: =V99/$V$107 -> 0.11519625 | X99: =U59/1000 -> 4.8809524 | Y99: =V59/1000 -> 4.8809524 | Z99: =Y99/$Y$103 -> 0.001686753 | AA99: =W59/1000 -> 0 | AB99: =AA99/$AA$103 -> #DIV/0!
S100: Суточные, вахтовые, проживание | T100: =S33/1000 -> 8.7 | U100: =T100/$T$107 -> 0.0068111067 | V100: =T33/1000 -> 8.7 | W100: =V100/$V$107 -> 0.018221952 | X100: =U66/1000 -> 66 | Y100: =V66/1000 -> 31 | Z100: =Y100/$Y$103 -> 0.010712939 | AA100: =W66/1000 -> 0 | AB100: =AA100/$AA$103 -> #DIV/0!
S101: Фонд оплаты труда | T101: =S37/1000 -> 133.41816 | U101: =T101/$T$107 -> 0.10445119 | V101: =T37/1000 -> 133.41816 | W101: =V101/$V$107 -> 0.2794413 | X101: =U78/1000 -> 59.306737 | Y101: =V78/1000 -> 131.23343 | Z101: =Y101/$Y$103 -> 0.045351474 | AA101: =W78/1000 -> 0 | AB101: =AA101/$AA$103 -> #DIV/0!
S102: ГСМ на бурение | T102: =S52/1000 -> 24.2 | U102: =T102/$T$107 -> 0.018945837 | V102: =T52/1000 -> 24.2 | W102: =V102/$V$107 -> 0.050686349 | X102: =U80/1000 -> 62.272074 | Y102: =V80/1000 -> 137.7951 | Z102: =Y102/$Y$103 -> 0.047619048 | AA102: =W80/1000 -> 0 | AB102: =AA102/$AA$103 -> #DIV/0!
S103: Амортизация | T103: =S59/1000 -> 4.8809524 | U103: =T103/$T$107 -> 0.0038212284 | V103: =T59/1000 -> 4.8809524 | W103: =V103/$V$107 -> 0.010223044 | X103: =U81/1000 -> 1307.7135 | Y103: =V81/1000 -> 2893.6971 | Z103: =Y103/$Y$103 -> 1 | AA103: =W81/1000 -> 0 | AB103: =AA103/$AA$103 -> #DIV/0!
S104: Общепроизводственные затраты | T104: =S66/1000 -> 66 | U104: =T104/$T$107 -> 0.051670465 | V104: =T66/1000 -> 66 | W104: =V104/$V$107 -> 0.1382355 | X104: =X103-SUM(X93:X102) -> 0 | Y104: =Y103-SUM(Y93:Y102) -> 0 | AA104: =AA103-SUM(AA93:AA102) -> 0
S105: Общехозяйственные расходы, руб. | T105: =S78/1000 -> 57.928592 | U105: =T105/$T$107 -> 0.045351474 | V105: =T78/1000 -> 21.652885 | W105: =V105/$V$107 -> 0.045351474 | X105: =X103*1000-U81 -> 0 | Y105: =Y103*1000-V81 -> 0 | Z105: =Z103-100% -> 0 | AA105: =AA103*1000-W81 -> 0 | AB105: =AB103-100% -> #DIV/0!
...

Sheet 3.сырье
B1: Наименование | C1: Ед. изм. | D1: 44927 | E1: 44958 | F1: 44986 | G1: 45017 | H1: 45047 | I1: 45078 | J1: 45108 | K1: 45139 | L1: 45170 | M1: 45200 | N1: 45231 | O1: 45261 | P1: среднее | Q1: на дату расчета
B2: Селитра аммиачная пористая CPT Чусовская | C2: тн | D2: 30200 | E2: 30200 | F2: 32530 | G2: 24000 | H2: 20000 | I2: 0 | J2: 0 | K2: 0 | L2: 0 | M2: 0 | N2: 0 | O2: 0 | P2: =IFERROR(SUM(D2:O2)/(12-COUNTIF(D2:O2,0)),0) -> 27386 | Q2: =SUMIFS(D2:O2,$D$1:$O$1,$H$1) -> 20000
B3: Селитра аммиачная пористая CPT Предшахтная | C3: тн | D3: 0 | E3: 0 | F3: 0 | G3: 0 | H3: 0 | I3: 0 | J3: 0 | K3: 0 | L3: 0 | M3: 0 | N3: 0 | O3: 0 | P3: =IFERROR(SUM(D3:O3)/(12-COUNTIF(D3:O3,0)),0) -> 0 | Q3: =SUMIFS(D3:O3,$D$1:$O$1,$H$1) -> 0
B4: Селитра аммиачная ГОСТ 2-2013 CPT Чусовская | C4: тн | D4: 21000 | E4: 21000 | F4: 21300 | G4: 21300 | H4: 21000 | I4: 0 | J4: 0 | K4: 0 | L4: 0 | M4: 0 | N4: 0 | O4: 0 | P4: =IFERROR(SUM(D4:O4)/(12-COUNTIF(D4:O4,0)),0) -> 21120 | Q4: =SUMIFS(D4:O4,$D$1:$O$1,$H$1) -> 21000
B5: Селитра аммиачная ГОСТ 2-2013 CPT Чусовская (село) | C5: тн | D5: 18500 | E5: 18500 | F5: =D5 -> 18500 | G5: 0 | H5: 0 | I5: 0 | J5: 0 | K5: 0 | L5: 0 | M5: 0 | N5: 0 | O5: 0 | P5: =IFERROR(SUM(D5:O5)/(12-COUNTIF(D5:O5,0)),0) -> 18500 | Q5: =SUMIFS(D5:O5,$D$1:$O$1,$H$1) -> 0
B6: Селитра ГОСТ 2-2013 (сырье) Урал-Поволжье | C6: тн | D6: 20500 | E6: 20500 | F6: 21300 | G6: 21300 | H6: 21000 | I6: 0 | J6: 0 | K6: 0 | L6: 0 | M6: 0 | N6: 0 | O6: 0 | P6: =IFERROR(SUM(D6:O6)/(12-COUNTIF(D6:O6,0)),0) -> 20920 | Q6: =SUMIFS(D6:O6,$D$1:$O$1,$H$1) -> 21000
B7: Селитра пористая (сырье) Урал-Поволжье | C7: тн | D7: 32530 | E7: 32530 | F7: =E7 -> 32530 | G7: 24000 | H7: 20000 | I7: 0 | J7: 0 | K7: 0 | L7: 0 | M7: 0 | N7: 0 | O7: 0 | P7: =IFERROR(SUM(D7:O7)/(12-COUNTIF(D7:O7,0)),0) -> 28318 | Q7: =SUMIFS(D7:O7,$D$1:$O$1,$H$1) -> 20000
B8: Вода | C8: тн | D8: 50 | E8: 50 | F8: 50 | G8: 50 | H8: 50 | I8: 0 | J8: 0 | K8: 0 | L8: 0 | M8: 0 | N8: 0 | O8: 0 | P8: =IFERROR(SUM(D8:O8)/(12-COUNTIF(D8:O8,0)),0) -> 50 | Q8: =SUMIFS(D8:O8,$D$1:$O$1,$H$1) -> 50
B9: Кислота уксусная 70% | C9: тн | D9: 79170 | E9: 79170 | F9: =E9 -> 79170 | G9: =F9 -> 79170 | H9: =G9 -> 79170 | I9: 0 | J9: 0 | K9: 0 | L9: 0 | M9: 0 | N9: 0 | O9: 0 | P9: =IFERROR(SUM(D9:O9)/(12-COUNTIF(D9:O9,0)),0) -> 79170 | Q9: =SUMIFS(D9:O9,$D$1:$O$1,$H$1) -> 79170
B10: Тиомочевина | C10: тн | D10: 283940 | E10: 283940 | F10: 286660 | G10: 234202 | H10: 280840 | I10: 0 | J10: 0 | K10: 0 | L10: 0 | M10: 0 | N10: 0 | O10: 0 | P10: =IFERROR(SUM(D10:O10)/(12-COUNTIF(D10:O10,0)),0) -> 273916.4 | Q10: =SUMIFS(D10:O10,$D$1:$O$1,$H$1) -> 280840
B11: Масло индустриальное И-20 | C11: тн | D11: 62942.5 | E11: 62942.5 | F11: 67150 | G11: 67150 | H11: 67240 | I11: 0 | J11: 0 | K11: 0 | L11: 0 | M11: 0 | N11: 0 | O11: 0 | P11: =IFERROR(SUM(D11:O11)/(12-COUNTIF(D11:O11,0)),0) -> 65485 | Q11: =SUMIFS(D11:O11,$D$1:$O$1,$H$1) -> 67240
B12: Эмульгатор "Березит-7" | C12: тн | D12: 230380 | E12: 230380 | F12: 230380 | G12: 193600 | H12: 206660 | I12: 0 | J12: 0 | K12: 0 | L12: 0 | M12: 0 | N12: 0 | O12: 0 | P12: =IFERROR(SUM(D12:O12)/(12-COUNTIF(D12:O12,0)),0) -> 218280 | Q12: =SUMIFS(D12:O12,$D$1:$O$1,$H$1) -> 206660
B13: Этиленгликоль МЭГ | C13: тн | D13: 80620 | E13: 80620 | F13: 80620 | G13: 80620 | H13: 80620 | I13: 0 | J13: 0 | K13: 0 | L13: 0 | M13: 0 | N13: 0 | O13: 0 | P13: =IFERROR(SUM(D13:O13)/(12-COUNTIF(D13:O13,0)),0) -> 80620 | Q13: =SUMIFS(D13:O13,$D$1:$O$1,$H$1) -> 80620
B14: Кислота лимонная моногидрат (25кг) | C14: тн | D14: 0 | E14: 0 | F14: 0 | G14: 0 | H14: 0 | I14: 0 | J14: 0 | K14: 0 | L14: 0 | M14: 0 | N14: 0 | O14: 0 | P14: =IFERROR(SUM(D14:O14)/(12-COUNTIF(D14:O14,0)),0) -> 0 | Q14: =SUMIFS(D14:O14,$D$1:$O$1,$H$1) -> 0
B15: Кислота сульфаминовая (40кг) | C15: тн | D15: 0 | E15: 0 | F15: 0 | G15: 0 | H15: 0 | I15: 0 | J15: 0 | K15: 0 | L15: 0 | M15: 0 | N15: 0 | O15: 0 | P15: =IFERROR(SUM(D15:O15)/(12-COUNTIF(D15:O15,0)),0) -> 0 | Q15: =SUMIFS(D15:O15,$D$1:$O$1,$H$1) -> 0
B16: Нитрит натрия технический | C16: тн | D16: 57240 | E16: 57240 | F16: =E16 -> 57240 | G16: 57083 | H16: 58033 | I16: 0 | J16: 0 | K16: 0 | L16: 0 | M16: 0 | N16: 0 | O16: 0 | P16: =IFERROR(SUM(D16:O16)/(12-COUNTIF(D16:O16,0)),0) -> 57367.2 | Q16: =SUMIFS(D16:O16,$D$1:$O$1,$H$1) -> 58033
B17: Карбамид | C17: тн | D17: 0 | E17: 0 | F17: 0 | G17: 0 | H17: 0 | I17: 0 | J17: 0 | K17: 0 | L17: 0 | M17: 0 | N17: 0 | O17: 0 | P17: =IFERROR(SUM(D17:O17)/(12-COUNTIF(D17:O17,0)),0) -> 0 | Q17: =SUMIFS(D17:O17,$D$1:$O$1,$H$1) -> 0
B18: Антистатическая присадка | C18: тн | D18: 0 | E18: 0 | F18: 0 | G18: 0 | H18: 0 | I18: 0 | J18: 0 | K18: 0 | L18: 0 | M18: 0 | N18: 0 | O18: 0 | P18: =IFERROR(SUM(D18:O18)/(12-COUNTIF(D18:O18,0)),0) -> 0 | Q18: =SUMIFS(D18:O18,$D$1:$O$1,$H$1) -> 0
B19: Топливо дизельное Чусовой (НХП-ОПТ) | C19: тн | D19: 60050.06 | E19: =D19 -> 60050.06 | F19: 57083 | G19: 57083 | H19: 64000 | I19: 0 | J19: 0 | K19: 0 | L19: 0 | M19: 0 | N19: 0 | O19: 0 | P19: =IFERROR(SUM(D19:O19)/(12-COUNTIF(D19:O19,0)),0) -> 59653.224 | Q19: =SUMIFS(D19:O19,$D$1:$O$1,$H$1) -> 64000
B20: Топливо дизельное АЗС Лукойл Пермский край | C20: тн | D20: 58226.19 | E20: 58508 | F20: 59393 | G20: 59393 | H20: 59393 | I20: 0 | J20: 0 | K20: 0 | L20: 0 | M20: 0 | N20: 0 | O20: 0 | P20: =IFERROR(SUM(D20:O20)/(12-COUNTIF(D20:O20,0)),0) -> 58982.638 | Q20: =SUMIFS(D20:O20,$D$1:$O$1,$H$1) -> 59393
B21: Топливо дизельное АЗС ГПНефть (Свердловская обл) | C21: тн | D21: 0 | E21: 0 | F21: 0 | G21: 0 | H21: 0 | I21: 0 | J21: 0 | K21: 0 | L21: 0 | M21: 0 | N21: 0 | O21: 0 | P21: =IFERROR(SUM(D21:O21)/(12-COUNTIF(D21:O21,0)),0) -> 0 | Q21: =SUMIFS(D21:O21,$D$1:$O$1,$H$1) -> 0
B22: Топливо дизельное Пермский щебень (Теплая Гора) | C22: тн | D22: 52200 | E22: 52200 | F22: 52200 | G22: 52200 | H22: 55500 | I22: 0 | J22: 0 | K22: 0 | L22: 0 | M22: 0 | N22: 0 | O22: 0 | P22: =IFERROR(SUM(D22:O22)/(12-COUNTIF(D22:O22,0)),0) -> 52860 | Q22: =SUMIFS(D22:O22,$D$1:$O$1,$H$1) -> 55500
B23: Топливо дизельное Чимбулатский карьер (Пермский край) | C23: тн | D23: 0 | E23: 0 | F23: 0 | G23: 0 | H23: 0 | I23: 0 | J23: 0 | K23: 0 | L23: 0 | M23: 0 | N23: 0 | O23: 0 | P23: =IFERROR(SUM(D23:O23)/(12-COUNTIF(D23:O23,0)),0) -> 0 | Q23: =SUMIFS(D23:O23,$D$1:$O$1,$H$1) -> 0
B24: Топливо дизельное Жуков Камень (Свердловская область) | C24: тн | D24: 0 | E24: 0 | F24: 0 | G24: 0 | H24: 0 | I24: 0 | J24: 0 | K24: 0 | L24: 0 | M24: 0 | N24: 0 | O24: 0 | P24: =IFERROR(SUM(D24:O24)/(12-COUNTIF(D24:O24,0)),0) -> 0 | Q24: =SUMIFS(D24:O24,$D$1:$O$1,$H$1) -> 0
B25: Топливо дизельное УралСтройКомплекс (Свердловская область) | C25: тн | D25: 0 | E25: 0 | F25: 0 | G25: 0 | H25: 0 | I25: 0 | J25: 0 | K25: 0 | L25: 0 | M25: 0 | N25: 0 | O25: 0 | P25: =IFERROR(SUM(D25:O25)/(12-COUNTIF(D25:O25,0)),0) -> 0 | Q25: =SUMIFS(D25:O25,$D$1:$O$1,$H$1) -> 0
B26: Топливо дизельное АЗС Лукойл Воркута | C26: тн | D26: 0 | E26: 0 | F26: 0 | G26: 0 | H26: 0 | I26: 0 | J26: 0 | K26: 0 | L26: 0 | M26: 0 | N26: 0 | O26: 0 | P26: =IFERROR(SUM(D26:O26)/(12-COUNTIF(D26:O26,0)),0) -> 0 | Q26: =SUMIFS(D26:O26,$D$1:$O$1,$H$1) -> 0
B27: Топливо дизельное Пудлинговый карьер (Свердловская область) | C27: тн | D27: 0 | E27: 0 | F27: 0 | G27: 0 | H27: 0 | I27: 0 | J27: 0 | K27: 0 | L27: 0 | M27: 0 | N27: 0 | O27: 0 | P27: =IFERROR(SUM(D27:O27)/(12-COUNTIF(D27:O27,0)),0) -> 0 | Q27: =SUMIFS(D27:O27,$D$1:$O$1,$H$1) -> 0
Q28: =SUMIFS(D28:O28,$D$1:$O$1,$H$1) -> 0
B29: Гранулит АСП-1 | C29: тн | D29: =SUM(D30:D33) -> 31991.004 | E29: =SUM(E30:E33) -> 31991.004 | F29: =SUM(F30:F33) -> 34003.18 | G29: =SUM(G30:G33) -> 25984.98 | H29: =SUM(H30:H33) -> 22640 | I29: =SUM(I30:I33) -> 0 | J29: =SUM(J30:J33) -> 0 | K29: =SUM(K30:K33) -> 0 | ... O29: =SUM(O30:O33) -> 0 | P29: =IFERROR(SUM(D29:O29)/(12-COUNTIF(D29:O29,0)),0) -> 29322.033 | Q29: =SUMIFS(D29:O29,$D$1:$O$1,$H$1) -> 22640
B30: Селитра аммиачная пористая CPT Чусовская | C30: 0.94 | D30: =SUMIF($B$2:$B$27,$B$30,D2:D27)*$C$30 -> 28388 | E30: =SUMIF($B$2:$B$27,$B$30,E2:E27)*$C$30 -> 28388 | F30: =SUMIF($B$2:$B$27,$B$30,F2:F27)*$C$30 -> 30578.2 | G30: =SUMIF($B$2:$B$27,$B$30,G2:G27)*$C$30 -> 22560 | H30: =SUMIF($B$2:$B$27,$B$30,H2:H27)*$C$30 -> 18800 | I30: =SUMIF($B$2:$B$27,$B$30,I2:I27)*$C$30 -> 0 | J30: =SUMIF($B$2:$B$27,$B$30,J2:J27)*$C$30 -> 0 | K30: =SUMIF($B$2:$B$27,$B$30,K2:K27)*$C$30 -> 0 | ... O30: =SUMIF($B$2:$B$27,$B$30,O2:O27)*$C$30 -> 0 | P30: =IFERROR(SUM(D30:O30)/(12-COUNTIF(D30:O30,0)),0) -> 25742.84 | Q30: =SUMIFS(D30:O30,$D$1:$O$1,$H$1) -> 18800
B31: Топливо дизельное Чусовой (НХП-ОПТ) | C31: 0.06 | D31: =SUMIF($B$2:$B$27,$B$31,D2:D27)*$C$31 -> 3603.0036 | E31: =SUMIF($B$2:$B$27,$B$31,E2:E27)*$C$31 -> 3603.0036 | F31: =SUMIF($B$2:$B$27,$B$31,F2:F27)*$C$31 -> 3424.98 | G31: =SUMIF($B$2:$B$27,$B$31,G2:G27)*$C$31 -> 3424.98 | H31: =SUMIF($B$2:$B$27,$B$31,H2:H27)*$C$31 -> 3840 | I31: =SUMIF($B$2:$B$27,$B$31,I2:I27)*$C$31 -> 0 | J31: =SUMIF($B$2:$B$27,$B$31,J2:J27)*$C$31 -> 0 | K31: =SUMIF($B$2:$B$27,$B$31,K2:K27)*$C$31 -> 0 | ... O31: =SUMIF($B$2:$B$27,$B$31,O2:O27)*$C$31 -> 0 | P31: =IFERROR(SUM(D31:O31)/(12-COUNTIF(D31:O31,0)),0) -> 3579.1934 | Q31: =SUMIFS(D31:O31,$D$1:$O$1,$H$1) -> 3840
B32: Карбамид | C32: 0 | D32: =SUMIF($B$2:$B$27,$B$32,D2:D27)*$C$32 -> 0 | E32: =SUMIF($B$2:$B$27,$B$32,E2:E27)*$C$32 -> 0 | F32: =SUMIF($B$2:$B$27,$B$32,F2:F27)*$C$32 -> 0 | G32: =SUMIF($B$2:$B$27,$B$32,G2:G27)*$C$32 -> 0 | H32: =SUMIF($B$2:$B$27,$B$32,H2:H27)*$C$32 -> 0 | I32: =SUMIF($B$2:$B$27,$B$32,I2:I27)*$C$32 -> 0 | J32: =SUMIF($B$2:$B$27,$B$32,J2:J27)*$C$32 -> 0 | K32: =SUMIF($B$2:$B$27,$B$32,K2:K27)*$C$32 -> 0 | ... O32: =SUMIF($B$2:$B$27,$B$32,O2:O27)*$C$32 -> 0 | P32: =IFERROR(SUM(D32:O32)/(12-COUNTIF(D32:O32,0)),0) -> 0 | Q32: =SUMIFS(D32:O32,$D$1:$O$1,$H$1) -> 0
B33: Антистатическая присадка | C33: 0 | D33: =SUMIF($B$2:$B$27,$B$33,D2:D27)*$C$33 -> 0 | E33: =SUMIF($B$2:$B$27,$B$33,E2:E27)*$C$33 -> 0 | F33: =SUMIF($B$2:$B$27,$B$33,F2:F27)*$C$33 -> 0 | G33: =SUMIF($B$2:$B$27,$B$33,G2:G27)*$C$33 -> 0 | H33: =SUMIF($B$2:$B$27,$B$33,H2:H27)*$C$33 -> 0 | I33: =SUMIF($B$2:$B$27,$B$33,I2:I27)*$C$33 -> 0 | J33: =SUMIF($B$2:$B$27,$B$33,J2:J27)*$C$33 -> 0 | K33: =SUMIF($B$2:$B$27,$B$33,K2:K27)*$C$33 -> 0 | ... O33: =SUMIF($B$2:$B$27,$B$33,O2:O27)*$C$33 -> 0 | P33: =IFERROR(SUM(D33:O33)/(12-COUNTIF(D33:O33,0)),0) -> 0 | Q33: =SUMIFS(D33:O33,$D$1:$O$1,$H$1) -> 0
Q34: =SUMIFS(D34:O34,$D$1:$O$1,$H$1) -> 0
Q35: =SUMIFS(D35:O35,$D$1:$O$1,$H$1) -> 0
B36: Березит Э-100 Рецептура № 1 | C36: тн | D36: =SUM(D37:D46) -> 22967.287 | E36: =SUM(E37:E46) -> 22967.287 | F36: =SUM(F37:F46) -> 23185.187 | G36: =SUM(G37:G46) -> 22638.906 | H36: =SUM(H37:H46) -> 22840.928 | I36: =SUM(I37:I46) -> 0 | J36: =SUM(J37:J46) -> 0 | K36: =SUM(K37:K46) -> 0 | ... O36: =SUM(O37:O46) -> 0 | P36: =IFERROR(SUM(D36:O36)/(12-COUNTIF(D36:O36,0)),0) -> 22919.919 | Q36: =SUMIFS(D36:O36,$D$1:$O$1,$H$1) -> 22840.928 | Z36: Гранулит АСП-1
B37: Селитра аммиачная ГОСТ 2-2013 CPT Чусовская | C37: 0.77937 | D37: =SUMIF($B$2:$B$27,$B$37,D2:D27)*$C$37 -> 16366.77 | E37: =SUMIF($B$2:$B$27,$B$37,E2:E27)*$C$37 -> 16366.77 | F37: =SUMIF($B$2:$B$27,$B$37,F2:F27)*$C$37 -> 16600.581 | G37: =SUMIF($B$2:$B$27,$B$37,G2:G27)*$C$37 -> 16600.581 | H37: =SUMIF($B$2:$B$27,$B$37,H2:H27)*$C$37 -> 16366.77 | I37: =SUMIF($B$2:$B$27,$B$37,I2:I27)*$C$37 -> 0 | J37: =SUMIF($B$2:$B$27,$B$37,J2:J27)*$C$37 -> 0 | K37: =SUMIF($B$2:$B$27,$B$37,K2:K27)*$C$37 -> 0 | ... O37: =SUMIF($B$2:$B$27,$B$37,O2:O27)*$C$37 -> 0 | P37: =IFERROR(SUM(D37:O37)/(12-COUNTIF(D37:O37,0)),0) -> 16460.294 | Q37: =SUMIFS(D37:O37,$D$1:$O$1,$H$1) -> 16366.77 | Z37: Березит Э-100 Рецептура № 1
B38: Вода | C38: 0.15963 | D38: =SUMIF($B$2:$B$27,$B$38,D2:D27)*$C$38 -> 7.9815 | E38: =SUMIF($B$2:$B$27,$B$38,E2:E27)*$C$38 -> 7.9815 | F38: =SUMIF($B$2:$B$27,$B$38,F2:F27)*$C$38 -> 7.9815 | G38: =SUMIF($B$2:$B$27,$B$38,G2:G27)*$C$38 -> 7.9815 | H38: =SUMIF($B$2:$B$27,$B$38,H2:H27)*$C$38 -> 7.9815 | I38: =SUMIF($B$2:$B$27,$B$38,I2:I27)*$C$38 -> 0 | J38: =SUMIF($B$2:$B$27,$B$38,J2:J27)*$C$38 -> 0 | K38: =SUMIF($B$2:$B$27,$B$38,K2:K27)*$C$38 -> 0 | ... O38: =SUMIF($B$2:$B$27,$B$38,O2:O27)*$C$38 -> 0 | P38: =IFERROR(SUM(D38:O38)/(12-COUNTIF(D38:O38,0)),0) -> 7.9815 | Q38: =SUMIFS(D38:O38,$D$1:$O$1,$H$1) -> 7.9815
B39: Эмульгатор "Березит-7" | C39: 0.01342 | D39: =SUMIF($B$2:$B$27,$B$39,D2:D27)*$C$39 -> 3091.6996 | E39: =SUMIF($B$2:$B$27,$B$39,E2:E27)*$C$39 -> 3091.6996 | F39: =SUMIF($B$2:$B$27,$B$39,F2:F27)*$C$39 -> 3091.6996 | G39: =SUMIF($B$2:$B$27,$B$39,G2:G27)*$C$39 -> 2598.112 | H39: =SUMIF($B$2:$B$27,$B$39,H2:H27)*$C$39 -> 2773.3772 | I39: =SUMIF($B$2:$B$27,$B$39,I2:I27)*$C$39 -> 0 | J39: =SUMIF($B$2:$B$27,$B$39,J2:J27)*$C$39 -> 0 | K39: =SUMIF($B$2:$B$27,$B$39,K2:K27)*$C$39 -> 0 | ... O39: =SUMIF($B$2:$B$27,$B$39,O2:O27)*$C$39 -> 0 | P39: =IFERROR(SUM(D39:O39)/(12-COUNTIF(D39:O39,0)),0) -> 2929.3176 | Q39: =SUMIFS(D39:O39,$D$1:$O$1,$H$1) -> 2773.3772
B40: Топливо дизельное Чусовой (НХП-ОПТ) | C40: 0.0305 | D40: =SUMIF($B$2:$B$27,$B$40,D2:D27)*$C$40 -> 1831.5268 | E40: =SUMIF($B$2:$B$27,$B$40,E2:E27)*$C$40 -> 1831.5268 | F40: =SUMIF($B$2:$B$27,$B$40,F2:F27)*$C$40 -> 1741.0315 | G40: =SUMIF($B$2:$B$27,$B$40,G2:G27)*$C$40 -> 1741.0315 | H40: =SUMIF($B$2:$B$27,$B$40,H2:H27)*$C$40 -> 1952 | I40: =SUMIF($B$2:$B$27,$B$40,I2:I27)*$C$40 -> 0 | J40: =SUMIF($B$2:$B$27,$B$40,J2:J27)*$C$40 -> 0 | K40: =SUMIF($B$2:$B$27,$B$40,K2:K27)*$C$40 -> 0 | ... O40: =SUMIF($B$2:$B$27,$B$40,O2:O27)*$C$40 -> 0 | P40: =IFERROR(SUM(D40:O40)/(12-COUNTIF(D40:O40,0)),0) -> 1819.4233 | Q40: =SUMIFS(D40:O40,$D$1:$O$1,$H$1) -> 1952
B41: Масло индустриальное И-20 | C41: 0.01708 | D41: =SUMIF($B$2:$B$27,$B$41,D2:D27)*$C$41 -> 1075.0579 | E41: =SUMIF($B$2:$B$27,$B$41,E2:E27)*$C$41 -> 1075.0579 | F41: =SUMIF($B$2:$B$27,$B$41,F2:F27)*$C$41 -> 1146.922 | G41: =SUMIF($B$2:$B$27,$B$41,G2:G27)*$C$41 -> 1146.922 | H41: =SUMIF($B$2:$B$27,$B$41,H2:H27)*$C$41 -> 1148.4592 | I41: =SUMIF($B$2:$B$27,$B$41,I2:I27)*$C$41 -> 0 | J41: =SUMIF($B$2:$B$27,$B$41,J2:J27)*$C$41 -> 0 | K41: =SUMIF($B$2:$B$27,$B$41,K2:K27)*$C$41 -> 0 | ... O41: =SUMIF($B$2:$B$27,$B$41,O2:O27)*$C$41 -> 0 | P41: =IFERROR(SUM(D41:O41)/(12-COUNTIF(D41:O41,0)),0) -> 1118.4838 | Q41: =SUMIFS(D41:O41,$D$1:$O$1,$H$1) -> 1148.4592
B42: Кислота уксусная 70% | C42: 0.0013 | D42: =SUMIF($B$2:$B$27,$B$42,D2:D27)*$C$42 -> 102.921 | E42: =SUMIF($B$2:$B$27,$B$42,E2:E27)*$C$42 -> 102.921 | F42: =SUMIF($B$2:$B$27,$B$42,F2:F27)*$C$42 -> 102.921 | G42: =SUMIF($B$2:$B$27,$B$42,G2:G27)*$C$42 -> 102.921 | H42: =SUMIF($B$2:$B$27,$B$42,H2:H27)*$C$42 -> 102.921 | I42: =SUMIF($B$2:$B$27,$B$42,I2:I27)*$C$42 -> 0 | J42: =SUMIF($B$2:$B$27,$B$42,J2:J27)*$C$42 -> 0 | K42: =SUMIF($B$2:$B$27,$B$42,K2:K27)*$C$42 -> 0 | ... O42: =SUMIF($B$2:$B$27,$B$42,O2:O27)*$C$42 -> 0 | P42: =IFERROR(SUM(D42:O42)/(12-COUNTIF(D42:O42,0)),0) -> 102.921 | Q42: =SUMIFS(D42:O42,$D$1:$O$1,$H$1) -> 102.921
B43: Тиомочевина | C43: 0.001 | D43: =SUMIF($B$2:$B$27,$B$43,D2:D27)*$C$43 -> 283.94 | E43: =SUMIF($B$2:$B$27,$B$43,E2:E27)*$C$43 -> 283.94 | F43: =SUMIF($B$2:$B$27,$B$43,F2:F27)*$C$43 -> 286.66 | G43: =SUMIF($B$2:$B$27,$B$43,G2:G27)*$C$43 -> 234.202 | H43: =SUMIF($B$2:$B$27,$B$43,H2:H27)*$C$43 -> 280.84 | I43: =SUMIF($B$2:$B$27,$B$43,I2:I27)*$C$43 -> 0 | J43: =SUMIF($B$2:$B$27,$B$43,J2:J27)*$C$43 -> 0 | K43: =SUMIF($B$2:$B$27,$B$43,K2:K27)*$C$43 -> 0 | ... O43: =SUMIF($B$2:$B$27,$B$43,O2:O27)*$C$43 -> 0 | P43: =IFERROR(SUM(D43:O43)/(12-COUNTIF(D43:O43,0)),0) -> 273.9164 | Q43: =SUMIFS(D43:O43,$D$1:$O$1,$H$1) -> 280.84
B44: Вода | C44: 0.012 | D44: =SUMIF($B$2:$B$27,$B$44,D2:D27)*$C$44 -> 0.6 | E44: =SUMIF($B$2:$B$27,$B$44,E2:E27)*$C$44 -> 0.6 | F44: =SUMIF($B$2:$B$27,$B$44,F2:F27)*$C$44 -> 0.6 | G44: =SUMIF($B$2:$B$27,$B$44,G2:G27)*$C$44 -> 0.6 | H44: =SUMIF($B$2:$B$27,$B$44,H2:H27)*$C$44 -> 0.6 | I44: =SUMIF($B$2:$B$27,$B$44,I2:I27)*$C$44 -> 0 | J44: =SUMIF($B$2:$B$27,$B$44,J2:J27)*$C$44 -> 0 | K44: =SUMIF($B$2:$B$27,$B$44,K2:K27)*$C$44 -> 0 | ... O44: =SUMIF($B$2:$B$27,$B$44,O2:O27)*$C$44 -> 0 | P44: =IFERROR(SUM(D44:O44)/(12-COUNTIF(D44:O44,0)),0) -> 0.6 | Q44: =SUMIFS(D44:O44,$D$1:$O$1,$H$1) -> 0.6
B45: Нитрит натрия технический | C45: 0.0015 | D45: =SUMIF($B$2:$B$27,$B$45,D2:D27)*$C$45 -> 85.86 | E45: =SUMIF($B$2:$B$27,$B$45,E2:E27)*$C$45 -> 85.86 | F45: =SUMIF($B$2:$B$27,$B$45,F2:F27)*$C$45 -> 85.86 | G45: =SUMIF($B$2:$B$27,$B$45,G2:G27)*$C$45 -> 85.6245 | H45: =SUMIF($B$2:$B$27,$B$45,H2:H27)*$C$45 -> 87.0495 | I45: =SUMIF($B$2:$B$27,$B$45,I2:I27)*$C$45 -> 0 | J45: =SUMIF($B$2:$B$27,$B$45,J2:J27)*$C$45 -> 0 | K45: =SUMIF($B$2:$B$27,$B$45,K2:K27)*$C$45 -> 0 | ... O45: =SUMIF($B$2:$B$27,$B$45,O2:O27)*$C$45 -> 0 | P45: =IFERROR(SUM(D45:O45)/(12-COUNTIF(D45:O45,0)),0) -> 86.0508 | Q45: =SUMIFS(D45:O45,$D$1:$O$1,$H$1) -> 87.0495
B46: Этиленгликоль МЭГ | C46: 0.0015 | D46: =SUMIF($B$2:$B$27,$B$46,D2:D27)*$C$46 -> 120.93 | E46: =SUMIF($B$2:$B$27,$B$46,E2:E27)*$C$46 -> 120.93 | F46: =SUMIF($B$2:$B$27,$B$46,F2:F27)*$C$46 -> 120.93 | G46: =SUMIF($B$2:$B$27,$B$46,G2:G27)*$C$46 -> 120.93 | H46: =SUMIF($B$2:$B$27,$B$46,H2:H27)*$C$46 -> 120.93 | I46: =SUMIF($B$2:$B$27,$B$46,I2:I27)*$C$46 -> 0 | J46: =SUMIF($B$2:$B$27,$B$46,J2:J27)*$C$46 -> 0 | K46: =SUMIF($B$2:$B$27,$B$46,K2:K27)*$C$46 -> 0 | ... O46: =SUMIF($B$2:$B$27,$B$46,O2:O27)*$C$46 -> 0 | P46: =IFERROR(SUM(D46:O46)/(12-COUNTIF(D46:O46,0)),0) -> 120.93 | Q46: =SUMIFS(D46:O46,$D$1:$O$1,$H$1) -> 120.93

Sheet ВВ
A2: Наименование | B2: Ед. изм. | C2: Цена без учета НДС, руб. кг
A3: ГВВ Гранулит РП | B3: кг | C3: 46
A4: ЭВВ Березит Э-100 | B4: кг | C4: 47
A5: ЭВВ Нитронит Э-100 | B5: кг | C5: 40
A6: ЭВВ Протолит-100 | B6: кг | C6: 45
A7: ЭВВ Эверсин-100 | B7: кг | C7: 48.9
A13: БЛАСТИТ 1000 55 В ПАТРОНАХ ГОСТ21984-76
A14: Эмульсолит П-А-20 ф 90 (кг)
A15: ЭМУЛЬСОЛИТ П-Ф--20 120 В ПАТРОНАХ
A16: КАРТРИДЖ AUTOSTEM GEN III - 17MM X 30G
A17: КАРТРИДЖ AUTOSTEM GEN III - 35MM X 300G
A18: КАРТРИДЖ AUTOSTEM GEN III - 87MM X 1700G
A19: КАРТРИДЖ AUTOSTEM GEN III DET READY - 35MM X 300G
A20: КАРТРИДЖ AUTOSTEM GEN III DET READY - 43MM X 550G
A21: ЗАРЯД ВЗРЫВАНИЯ ЭКВ-Б-3/50/30
A22: ЗАРЯД КОНТУРНОГО ВЗРЫВАНИЯ ЗКВ-Б 3/50/27

Sheet СВ
A2: Наименование | B2: Ед. изм. | C2: Масса патрона | D2: Цена на дату расчета без учета НДС, руб. кг
A3: Детонатор промежуточный ДПУ-ПТ600 | B3: кг | C3: 0.65
A4: Детонатор промежуточный "Сибирит-ПД" - 80/1,0 | B4: кг | C4: 0.8
A5: Нитронит П марки "С" D-45-0,8 кг | B5: кг | C5: 0.45
A6: Нитронит П марки "С" D-60-1.0 кг | B6: кг | C6: 0.6
A7: Аммонит № 6ЖВ-200 ГОСТ 21984-76 | B7: кг | C7: 0.2
A8: Заряды ЭВВ в патронах НПГМ-П-II-М-60-800 | B8: кг | C8: 0.8 | D8: 120.6
A9: Шашка-детонатор ЭПД-70-1000 | B9: кг | C9: 1 | D9: 240
A10: ДЭПУ Протолит М-800 | B10: кг | C10: 0.8 | D10: 240
A11: ДЭПУ Протолит М-1000 | B11: кг | C11: 1 | D11: 240
A12: ДЭПУ Протолит М-500 | B12: кг | C12: 0.5 | D12: 240
A13: Детонатор промежуточный пентолитовый ПДП-62/600-100
A14: ШАШКА ПТ-П750
A15: ПАТРОН НИТРОНИТ П МАРКА С D60ММ 0,8 КГ
A16: ПАТРОН НИТРОНИТ П МАРКА С D60ММ 1КГ
A17: Детонатор промежуточный "Сферит ДП" - 60 / 1,0 | B17: кг | C17: 1 | D17: 150
A18: Детонатор промежуточный "Сферит ДП" - 60 / 0,8 | B18: кг | C18: 0.8 | D18: 150

Sheet СИ
A2: Наименование | B2: Ед. изм. | C2: Назначение | D2: Производитель | E2: на дату расчета
A3: НСИ "Rionel" серии MS-20-18 м. (в упаковке 1.4 S) | B3: шт | C3: С | D3: ВСИ (MAXAM) | E3: 146.76
A4: НСИ "Rionel" серии MS-20-15 м. (в упаковке 1.4 S) | B4: шт | C4: С | D4: ВСИ (MAXAM) | E4: 0
A5: НСИ "Rionel" серии MS-20-9 м. (в упаковке 1.4 S) | B5: шт | C5: С | D5: ВСИ (MAXAM) | E5: 99.91
A6: НСИ "Rionel" серии MS-20-6 м. (в упаковке 1.4 S) | B6: шт | C6: С | D6: ВСИ (MAXAM) | E6: 99.08
A7: НСИ "Rionel" серии Х-*-7,2 м. (в упаковке 1.4 S) | B7: шт | C7: П | D7: ВСИ (MAXAM) | E7: 109.65
A8: НСИ "Rionel" серии Х-*-4,8 м. (в упаковке 1.4 S) | B8: шт | C8: П | D8: ВСИ (MAXAM) | E8: 103.16
A9: НСИ "Rionel" серии Х-*-4,2 м. (в упаковке 1.4 S) | B9: шт | C9: П | D9: ВСИ (MAXAM) | E9: 74.06
A10: НСИ "Rionel" серии Х-*-3,6 м. (в упаковке 1.4 S) | B10: шт | C10: П | D10: ВСИ (MAXAM) | E10: 77.09
A11: НСИ "Rionel" серии Х-*- 60 м. (в упаковке 1.4 S) | B11: шт | C11: СТАРТ | D11: ВСИ (MAXAM) | E11: 0
A12: НСИ "Rionel" серии Х-*- 200 м. (в упаковке 1.4 S) | B12: шт | C12: СТАРТ | D12: ВСИ (MAXAM) | E12: 0
A13: НСИ "Rionel" серии Х-*- 600 м. (в упаковке 1.1 B) | B13: шт | C13: СТАРТ | D13: ВСИ (MAXAM) | E13: 0
A14: НСИ "Rionel" серии X-42-7,2 м( упаковке 1,4S) | B14: шт | C14: П | D14: ВСИ (MAXAM) | E14: 113.14
A23: Электродетонатор ЭД-8М1 | B23: шт | C23: ЭД | E23: 33.28
A24: Электродетонатор ЭД-З-Н-0 | B24: шт | C24: ЭД | E24: 144.66225
A25: Рукав зарядный | B25: шт | C25: Р | E25: 0
A26: Устройство Искра-С-*-18 | B26: шт | C26: С | D26: НМЗ ИСКРА (ТМС)
A27: Устройство Искра-С-*-15 | B27: шт | C27: С | D27: НМЗ ИСКРА (ТМС) | E27: 389
A28: Устройство Искра-С-*-12 | B28: шт | C28: С | D28: НМЗ ИСКРА (ТМС) | E28: 335.2
A29: Устройство Искра-С-*-8,5 | B29: шт | C29: С | D29: НМЗ ИСКРА (ТМС)
A30: Устройство Искра-С-*-6 | B30: шт | C30: С | D30: НМЗ ИСКРА (ТМС)
A31: Устройство Искра-С-*-6 | B31: шт | C31: С | D31: НМЗ ИСКРА (ТМС)
A32: Устройство Искра-С-*-10 | B32: шт | C32: С | D32: НМЗ ИСКРА (ТМС)
A33: Устройство Искра-П-*-4 | B33: шт | C33: П | D33: НМЗ ИСКРА (ТМС) | E33: 214
A34: Устройство Искра-П-*-5 | E34: 240
A35: Устройство Искра-П-*-6 | B35: шт | C35: П | D35: НМЗ ИСКРА (ТМС) | E35: 265
A36: Устройство Искра-П-*-7 | B36: шт | C36: П | D36: НМЗ ИСКРА (ТМС) | E36: 163.3
A37: Устройство Искра-П-*-8 | B37: шт | C37: П | D37: НМЗ ИСКРА (ТМС) | E37: 188.8
A38: Устройство Искра-П-*-9 | B38: шт | C38: П | D38: НМЗ ИСКРА (ТМС) | E38: 188.8
A39: Устройство Искра-П-*-10 | B39: шт | C39: П | D39: НМЗ ИСКРА (ТМС) | E39: 290
A40: Устройство ИСКРА-СТАРТ-В-200 | B40: шт | C40: П | D40: НМЗ ИСКРА (ТМС) | E40: 3210
A41: Устройство ИСКРА-СТАРТ-В-500 | B41: шт | C41: СТАРТ | D41: НМЗ ИСКРА (ТМС) | E41: 7400
A42: Устройство стартовое ИСКРА-Старт-ВШ-100 | B42: шт | C42: СТАРТ | D42: НМЗ ИСКРА (ТМС) | E42: 0
A43: Устройство стартовое ИСКРА-Старт-ВШ-200 | B43: шт | C43: СТАРТ | D43: НМЗ ИСКРА (ТМС) | E43: 2126.98
A44: Устройство стартовое ИСКРА-Старт-ВШ-300 | B44: шт | C44: СТАРТ | D44: НМЗ ИСКРА (ТМС) | E44: 2951.78
A45: Устройство стартовое ИСКРА-Старт-ВШ-500 | B45: шт | C45: СТАРТ | D45: НМЗ ИСКРА (ТМС) | E45: 5645.42
A46: Устройство инициирования ИСКРА-П-0-4
A50: Устройство инициирования ИСКРА-С-450-12
A51: Устройство инициирования ИСКРА-С-450-15
A55: НСИ "Коршун" ДИН-С-500-15 | B55: шт | C55: С | D55: АЗОТ-ВЗРЫВ | E55: 238
A56: НСИ "Коршун" ДИН-П-42-6 | B56: шт | C56: П | D56: АЗОТ-ВЗРЫВ | E56: 163
A57: НСИ "Коршун" ДИН-П-25-5 | B57: шт | C57: П | D57: АЗОТ-ВЗРЫВ | E57: 147
A58: Hitronic II Standard 12 m | B58: шт | C58: С | D58: HANWA | E58: 0
A59: Hitronic II Standard 15 m | B59: шт | C59: С | D59: HANWA | E59: 0
A60: Hitronic II Standard 18 m | B60: шт | C60: С | D60: HANWA | E60: 0
A61: Hitronic II Standard 20 m | B61: шт | C61: С | D61: HANWA | E61: 0
A62: Провод медный 2-х жильный диаметром 0,60мм на напряжение 24В | B62: м | C62: М | D62: HANWA | E62: 0
A63: Провод медный, 2-жильный, диаметром 0,75 мм
A65: Средство инициирования HiNEL Plus DHD 12m 500 mc
A66: Средство инициирования HiNEL Plus SDD 4.8m 25 mc
A67: Средство инициирования HiNEL Plus Starter 500m 0 mc
A68: Устройство зарядное L14, диаметр 170 мм
A69: Зарядное устройство L 12 метров
A70: Зарядное устройство L 6 метров
A72: Реле пиротехническое РП-Д-30 ДИШВ.773919.009ТУ
A73: Соединитель ИВШП 143.000.000-03
A74: Шнур детонирующий ДШМ-Э
A75: НСИ ЭКСЭЛ КОННЕКТЕД SL-0-500
A76: НСИ ЭКСЭЛ КОННЕКТЕД SL-25-4 8 | F76: штанга
A77: НСИ ЭКСЭЛ КОННЕКТЕД SL-25-9 0
A78: СИСТЕМА ЭКСЭЛ ТУ287-005-23308410-2006
A79: НСИ ЭКСЭЛ MS-500-15.0
A80: НСИ ЭКСЭЛ MS-475-21.0
A81: НСИ ЭКСЭЛ КОННЕКТЕД SL-67-9.0
A82: НСИ ЭКСЭЛ КОННЕКТЕД SL-0-1000
A83: НСИ ЭКСЭЛ MS-475-27.0
A84: НСИ ЭКСЭЛ КОННЕКТЕД SL-17-9.0
A85: НСИ ЭКСЭЛ SL-42-9.0
A86: НСИ ЭКСЭЛ КОННЕКТЕД SL-109-9.0
A87: НСИ ЭКСЭЛ КОННЕКТЕД SL-176-9.0
A88: НСИ ЭКСЭЛ MS-500-10.2
... A491: Электрод сменный

Sheet ТМЦ
B2: Наименование | C2: Ед. изм. | D2: 44927 | E2: 44958 | F2: 44986 | G2: 45017 | H2: 45047 | I2: 45078 | J2: 45108 | K2: 45139 | L2: 45170 | M2: 45200 | N2: 45231 | O2: 45261 | P2: на дату расчета
A3: ВМ | B3: Детонатор промежуточный ДПУ-ПТ600 | C3: тн | D3: 307700 | E3: 307700 | F3: 307700 | G3: 307700 | H3: 307700 | P3: =SUMIFS(D3:O3,$D$2:$O$2,$R$3) -> 307700 | R3: 45047
A4: ВМ | B4: Детонатор промежуточный "Сибирит-ПД" - 80/1,0 ТУ 3602-042-05608605-2018 | C4: тн | E4: 245000 | F4: 245000 | G4: 245000 | H4: 245000 | P4: =SUMIFS(D4:O4,$D$2:$O$2,$R$3) -> 245000
B5: Нитронит П марки "С" d-45-0,8 кг по ТУ 7276-019-58995878-2015 | C5: тн | H5: 137000 | P5: =SUMIFS(D5:O5,$D$2:$O$2,$R$3) -> 137000
B6: Нитронит П марки "С" D-60-1.0 кг по ТУ 7276-019-58995878-2015 | C6: тн | H6: 142000 | P6: =SUMIFS(D6:O6,$D$2:$O$2,$R$3) -> 142000
A7: ВМ | B7: Аммонит № 6ЖВ-200 ГОСТ 21984-76 | C7: тн | D7: 192000 | E7: 192000 | F7: 192000 | G7: 192000 | H7: 192000 | P7: =SUMIFS(D7:O7,$D$2:$O$2,$R$3) -> 192000
A8: ВМ | B8: Аммонит 6ЖВ в патронах (d=32мм) ОСП Камчатка | C8: тн | E8: 304370 | F8: 304370 | G8: 304370 | H8: 304370 | P8: =SUMIFS(D8:O8,$D$2:$O$2,$R$3) -> 304370
A9: ВМ | B9: НСИ "Rionel" серии MS-20-18 м. (в упаковке 1.4 S) | C9: шт | D9: 116.64 | E9: 146.76 | F9: 146.76 | G9: 146.76 | H9: 146.76 | P9: =SUMIFS(D9:O9,$D$2:$O$2,$R$3) -> 146.76
A10: ВМ | B10: НСИ "Rionel" серии MS-20-15 м. (в упаковке 1.4 S) | C10: шт | D10: 107.11 | E10: 0 | F10: 0 | G10: 0 | H10: 0 | P10: =SUMIFS(D10:O10,$D$2:$O$2,$R$3) -> 0
A11: ВМ | B11: НСИ "Rionel" серии MS-20-9 м. (в упаковке 1.4 S) | C11: шт | D11: 87.91 | E11: 99.91 | F11: 99.91 | G11: 99.91 | H11: 99.91 | P11: =SUMIFS(D11:O11,$D$2:$O$2,$R$3) -> 99.91
A12: ВМ | B12: НСИ "Rionel" серии MS-20-6 м. (в упаковке 1.4 S) | C12: шт | D12: 78.38 | E12: 99.08 | F12: 99.08 | G12: 99.08 | H12: 99.08 | P12: =SUMIFS(D12:O12,$D$2:$O$2,$R$3) -> 99.08
A13: ВМ | B13: НСИ "Rionel" серии Х-*-7,2 м. (в упаковке 1.4 S) | C13: шт | D13: 86.97 | E13: 109.65 | F13: 109.65 | G13: 109.65 | H13: 109.65 | P13: =SUMIFS(D13:O13,$D$2:$O$2,$R$3) -> 109.65
A14: ВМ | B14: НСИ "Rionel" серии Х-*-4,8 м. (в упаковке 1.4 S) | C14: шт | D14: 79.29 | E14: 103.16 | F14: 103.16 | G14: 103.16 | H14: 103.16 | P14: =SUMIFS(D14:O14,$D$2:$O$2,$R$3) -> 103.16
A15: ВМ | B15: НСИ "Rionel" серии Х-*-4,2 м. (в упаковке 1.4 S) | C15: шт | D15: 77.39 | E15: 74.06 | F15: 74.06 | G15: 74.06 | H15: 74.06 | P15: =SUMIFS(D15:O15,$D$2:$O$2,$R$3) -> 74.06
A16: ВМ | B16: НСИ "Rionel" серии Х-*-3,6 м. (в упаковке 1.4 S) | C16: шт | D16: 75.49 | E16: 77.09 | F16: 77.09 | G16: 77.09 | H16: 77.09 | P16: =SUMIFS(D16:O16,$D$2:$O$2,$R$3) -> 77.09
A17: ВМ | B17: НСИ "Rionel" серии Х-*- 60 м. (в упаковке 1.4 S) | C17: шт | D17: 250.22 | E17: 0 | F17: 0 | G17: 0 | H17: 0 | P17: =SUMIFS(D17:O17,$D$2:$O$2,$R$3) -> 0
A18: ВМ | B18: НСИ "Rionel" серии Х-*- 200 м. (в упаковке 1.4 S) | C18: шт | D18: 812.92 | E18: 0 | F18: 0 | G18: 0 | H18: 0 | P18: =SUMIFS(D18:O18,$D$2:$O$2,$R$3) -> 0
A19: ВМ | B19: НСИ "Rionel" серии Х-*- 600 м. (в упаковке 1.1 B) | C19: шт | D19: 0 | E19: 0 | F19: 0 | G19: 0 | H19: 0 | P19: =SUMIFS(D19:O19,$D$2:$O$2,$R$3) -> 0
A20: ВМ | B20: НСИ "Rionel" серии X-42-7,2 м( упаковке 1,4S) | C20: шт | E20: 113.14 | F20: 113.14 | G20: 113.14 | H20: 113.14 | P20: =SUMIFS(D20:O20,$D$2:$O$2,$R$3) -> 113.14
A21: ВМ | B21: Электродетонатор ЭД-8М1 | C21: шт | D21: 50 | E21: 33.28 | F21: 33.28 | G21: 33.28 | H21: 33.28 | P21: =SUMIFS(D21:O21,$D$2:$O$2,$R$3) -> 33.28
A22: ВМ | B22: Электродетонатор ЭД-З-Н-0 | C22: шт | E22: 144.66225 | F22: 144.66225 | G22: 144.66225 | H22: 144.66225 | P22: =SUMIFS(D22:O22,$D$2:$O$2,$R$3) -> 144.66225
A23: ВМ | B23: Рукав зарядный | C23: шт | D23: 300 | E23: 0 | F23: 0 | G23: 0 | H23: 0 | P23: =SUMIFS(D23:O23,$D$2:$O$2,$R$3) -> 0
A24: ВМ | B24: Устройство Искра-С-500-18 | C24: шт | D24: 301.16 | E24: 301.16 | F24: 301.16 | G24: 301.16 | H24: 301.16 | P24: =SUMIFS(D24:O24,$D$2:$O$2,$R$3) -> 301.16
A25: ВМ | B25: Устройство Искра-С-500-14 | C25: шт | D25: 268.71 | E25: 268.71 | F25: 268.71 | G25: 268.71 | H25: 290 | P25: =SUMIFS(D25:O25,$D$2:$O$2,$R$3) -> 290
A26: ВМ | B26: Устройство Искра-С-500-12 | C26: шт | D26: 238.52 | E26: 0 | F26: 0 | G26: 0 | H26: 0 | P26: =SUMIFS(D26:O26,$D$2:$O$2,$R$3) -> 0
A27: ВМ | B27: Устройство Искра-С-500-8,5 | C27: шт | D27: 211.63 | E27: 211.63 | F27: 211.63 | G27: 211.63 | H27: 211.63 | P27: =SUMIFS(D27:O27,$D$2:$O$2,$R$3) -> 211.63
A28: ВМ | B28: Устройство Искра-С-500-6 | C28: шт | D28: 160.7 | E28: 160.7 | F28: 160.7 | G28: 160.7 | H28: 160.7 | P28: =SUMIFS(D28:O28,$D$2:$O$2,$R$3) -> 160.7
A29: ВМ | B29: Устройство Искра-С-450-6 | C29: шт | D29: 0 | E29: 0 | F29: 0 | G29: 0 | H29: 0 | P29: =SUMIFS(D29:O29,$D$2:$O$2,$R$3) -> 0
A30: ВМ | B30: Устройство Искра-С-450-10 | C30: шт | D30: 0 | E30: 118.01 | F30: 118.01 | G30: 118.01 | H30: 118.01 | P30: =SUMIFS(D30:O30,$D$2:$O$2,$R$3) -> 118.01
A31: ВМ | B31: Устройство Искра-П-9-4 | C31: шт | D31: 152.12 | E31: 152.12 | F31: 152.12 | G31: 152.12 | H31: 152.12 | P31: =SUMIFS(D31:O31,$D$2:$O$2,$R$3) -> 152.12
A32: ВМ | B32: Устройство Искра-П-17-4 | C32: шт | D32: 152.12 | E32: 152.12 | F32: 152.12 | G32: 152.12 | H32: 152.12 | P32: =SUMIFS(D32:O32,$D$2:$O$2,$R$3) -> 152.12
A33: ВМ | B33: Устройство Искра-П-25-4,4 | C33: шт | D33: 161.47 | E33: 161.47 | F33: 161.47 | G33: 161.47 | H33: 290 | P33: =SUMIFS(D33:O33,$D$2:$O$2,$R$3) -> 290
A34: ВМ | B34: Устройство Искра-П-17-6 | C34: шт | D34: 0 | E34: 163.3 | F34: 163.3 | G34: 163.3 | H34: 163.3 | P34: =SUMIFS(D34:O34,$D$2:$O$2,$R$3) -> 163.3
... A42: ВМ | B42: Устройство стартовое ИСКРА-Старт-ВШ-500 | C42: шт | D42: 0 | E42: 5645.42 | F42: 5645.42 | G42: 5645.42 | H42: 5645.42 | P42: =SUMIFS(D42:O42,$D$2:$O$2,$R$3) -> 5645.42
B43: НСИ "Коршун" ДИН-С-500-15 | C43: шт | D43: 238 | E43: 238 | F43: 238 | G43: 238 | H43: 238 | P43: =SUMIFS(D43:O43,$D$2:$O$2,$R$3) -> 238
B44: НСИ "Коршун" ДИН-П-42-6 | C44: шт | D44: 163 | E44: 163 | F44: 163 | G44: 163 | H44: 163 | P44: =SUMIFS(D44:O44,$D$2:$O$2,$R$3) -> 163
B45: НСИ "Коршун" ДИН-П-25-5 | C45: шт | D45: 147 | E45: 147 | F45: 147 | G45: 147 | H45: 147 | P45: =SUMIFS(D45:O45,$D$2:$O$2,$R$3) -> 147
A46: ВМ | B46: Hitronic II Standard 12 m | C46: шт | D46: 0 | E46: 0 | F46: 0 | G46: 0 | H46: 0 | P46: =SUMIFS(D46:O46,$D$2:$O$2,$R$3) -> 0
A47: ВМ | B47: Hitronic II Standard 15 m | C47: шт | D47: 0 | E47: 0 | F47: 0 | G47: 0 | H47: 0 | P47: =SUMIFS(D47:O47,$D$2:$O$2,$R$3) -> 0
A48: ВМ | B48: Hitronic II Standard 18 m | C48: шт | D48: 0 | E48: 0 | F48: 0 | G48: 0 | H48: 0 | P48: =SUMIFS(D48:O48,$D$2:$O$2,$R$3) -> 0
A49: ВМ | B49: Hitronic II Standard 20 m | C49: шт | D49: 0 | E49: 0 | F49: 0 | G49: 0 | H49: 0 | P49: =SUMIFS(D49:O49,$D$2:$O$2,$R$3) -> 0
A50: ВМ | B50: Провод медный 2-х жильный диаметром 0,60мм на напряжение 24В | C50: м | D50: 0 | E50: 0 | F50: 0 | G50: 0 | H50: 0 | P50: =SUMIFS(D50:O50,$D$2:$O$2,$R$3) -> 0
P51: =SUMIFS(D51:O51,$D$2:$O$2,$R$3) -> 0
P52: =SUMIFS(D52:O52,$D$2:$O$2,$R$3) -> 0
A53: БИ | B53: Пневмоударники | P53: =SUMIFS(D53:O53,$D$2:$O$2,$R$3) -> 0
A54: БИ | B54: Пневмоударник TH6 (QL60) 3-1/2 API Reg | C54: шт | D54: 0 | E54: 0 | H54: 89587 | P54: =SUMIFS(D54:O54,$D$2:$O$2,$R$3) -> 89587
A55: БИ | B55: Пневмоударник DT-H5A DHD350A 3-1/2 API Reg | C55: шт | D55: 75000 | E55: 75000 | F55: 75000 | G55: 75000 | H55: 75000 | P55: =SUMIFS(D55:O55,$D$2:$O$2,$R$3) -> 75000
A56: БИ | B56: Пневмоударник DT-H4 DHD340 2-3/8 API Reg | C56: шт | D56: 0 | E56: 88558.63 | F56: 88558.63 | G56: 83333 | H56: 83333 | P56: =SUMIFS(D56:O56,$D$2:$O$2,$R$3) -> 83333
A57: БИ | B57: Пневмоударник MS-H4. DHD340/340A 2 3/8 API Reg | C57: шт | D57: 0 | E57: 0 | P57: =SUMIFS(D57:O57,$D$2:$O$2,$R$3) -> 0
A58: БИ | B58: Пневмоударник К4. DHD340A 2 3/8 API Reg | C58: шт | D58: 0 | E58: 0 | P58: =SUMIFS(D58:O58,$D$2:$O$2,$R$3) -> 0
A59: БИ | B59: Пневмоударник JAB 44/DHD340 | C59: шт | D59: 0 | E59: 0 | P59: =SUMIFS(D59:O59,$D$2:$O$2,$R$3) -> 0
A60: БИ | B60: Пневмоударник DT-HCIR110 | C60: шт | D60: 0 | E60: 0 | P60: =SUMIFS(D60:O60,$D$2:$O$2,$R$3) -> 0
A61: БИ | B61: Пневмоударник П-110-3,2 ШРБ МХ 67.00 | C61: шт | D61: 0 | E61: 0 | P61: =SUMIFS(D61:O61,$D$2:$O$2,$R$3) -> 0
A62: БИ | B62: Пневмоударник DT-H5. DHD350 3-1/2 API Reg | C62: шт | D62: 0 | E62: 97990.64 | F62: 97990.64 | G62: 97990.64 | H62: 104000 | P62: =SUMIFS(D62:O62,$D$2:$O$2,$R$3) -> 104000
A63: БИ | B63: Пневмоударник DT-H6. 3-1/2 API REG QL60 | C63: шт | D63: 0 | E63: 84280.75 | F63: 84280.75 | G63: 84280.75 | H63: 84280.75 | P63: =SUMIFS(D63:O63,$D$2:$O$2,$R$3) -> 84280.75
A64: БИ | B64: Коронки буровые | P64: =SUMIFS(D64:O64,$D$2:$O$2,$R$3) -> 0
A65: БИ | B65: Коронка буровая DT-DHD360 165 мм CVSBL | C65: шт | D65: 0 | E65: 0 | P65: =SUMIFS(D65:O65,$D$2:$O$2,$R$3) -> 0
A66: БИ | B66: Коронка буровая DT-DHD350 152 мм CVSBL | C66: шт | D66: 0 | E66: 0 | F66: 21250 | G66: 21250 | H66: 22500 | P66: =SUMIFS(D66:O66,$D$2:$O$2,$R$3) -> 22500
A67: БИ | B67: Коронка буровая DTН-DHD340 130мм, комбо | C67: шт | D67: 0 | E67: 16583 | F67: 16583 | G67: 16583 | H67: 16583 | P67: =SUMIFS(D67:O67,$D$2:$O$2,$R$3) -> 16583
A68: БИ | B68: Коронка буровая DT-DHD340 125 мм CVD/SBL | C68: шт | D68: 0 | E68: 18859.64 | F68: 18859.64 | G68: 18859.64 | H68: 18859.64 | P68: =SUMIFS(D68:O68,$D$2:$O$2,$R$3) -> 18859.64
A69: БИ | B69: Коронка буровая DT-CIR110 122 мм CV/SPBL | C69: шт | D69: 0 | E69: 0 | P69: =SUMIFS(D69:O69,$D$2:$O$2,$R$3) -> 0
A70: БИ | B70: Коронка буровая DT-DHD340 115 мм CV/SBL | C70: шт | D70: 0 | E70: 0 | P70: =SUMIFS(D70:O70,$D$2:$O$2,$R$3) -> 0
A71: БИ | B71: Коронка буровая DT-KNSH 115 мм DC/SBL | C71: шт | D71: 0 | E71: 6720.83 | F71: 6720.83 | G71: 6720.83 | H71: 6720.83 | P71: =SUMIFS(D71:O71,$D$2:$O$2,$R$3) -> 6720.83
A72: БИ | B72: Коронка буровая DTH 130мм/DHD340 сфера | C72: шт | D72: 0 | E72: 15414.37 | F72: 15414.37 | G72: 15414.37 | H72: 15414.37 | P72: =SUMIFS(D72:O72,$D$2:$O$2,$R$3) -> 15414.37
A73: БИ | B73: Коронка буровая DTН-DHD340 130мм баллистика | C73: шт | D73: 0 | E73: 16983.4 | F73: 16983.4 | G73: 16983.4 | H73: 16983.4 | P73: =SUMIFS(D73:O73,$D$2:$O$2,$R$3) -> 16983.4
A74: БИ | B74: Коронка буровая QL60 165мм сфера | C74: шт | D74: 0 | E74: 28238.34 | F74: 28000 | G74: 28000 | H74: 29200 | P74: =SUMIFS(D74:O74,$D$2:$O$2,$R$3) -> 29200
A75: БИ | B75: Ремкомплекты для пневмоударников | P75: =SUMIFS(D75:O75,$D$2:$O$2,$R$3) -> 0
A76: БИ | B76: Ремкомплект DT-H4 DHD340 (внешний) | C76: шт | D76: 0 | E76: 58138.71 | F76: 58138.71 | G76: 58138.71 | H76: 58138.71 | P76: =SUMIFS(D76:O76,$D$2:$O$2,$R$3) -> 58138.71
A77: БИ | B77: Ремкомплект DT-HCIR110 M4 (внешний) | C77: шт | D77: 0 | E77: 20416.67 | F77: 20416.67 | G77: 20416.67 | H77: 20416.67 | P77: =SUMIFS(D77:O77,$D$2:$O$2,$R$3) -> 20416.67
B78: Ремкомплект DT-H6 D QL 60 3-1/2 API Reg | C78: шт | D78: 12000 | E78: 12000 | F78: 12000 | G78: 12000 | H78: 12000 | P78: =SUMIFS(D78:O78,$D$2:$O$2,$R$3) -> 12000
A79: БИ | B79: Поршень DT-HCIR110 M4 | C79: шт | D79: 0 | E79: 0 | P79: =SUMIFS(D79:O79,$D$2:$O$2,$R$3) -> 0
A80: БИ | B80: Патрон паводковый нижний (гайка нижняя) DT-H4 DHD340 | C80: шт | D80: 0 | E80: 9161.36 | F80: 9161.36 | G80: 9161.36 | H80: 9161.36 | P80: =SUMIFS(D80:O80,$D$2:$O$2,$R$3) -> 9161.36
A81: БИ | B81: Гайка нижняя DT-HCIR110 | C81: шт | D81: 0 | E81: 0 | P81: =SUMIFS(D81:O81,$D$2:$O$2,$R$3) -> 0
A82: БИ | B82: Ударник П-110-3,2 ШРБ МХ 67,03 | C82: шт | D82: 0 | E82: 0 | P82: =SUMIFS(D82:O82,$D$2:$O$2,$R$3) -> 0
A83: БИ | B83: Цилиндр П-110-3,2 ШРБ МХ 67.02 | C83: шт | D83: 0 | E83: 0 | P83: =SUMIFS(D83:O83,$D$2:$O$2,$R$3) -> 0
A84: БИ | B84: Букса ПП-110-2,8 Ш МХ 61.01 | C84: шт | D84: 0 | E84: 0 | P84: =SUMIFS(D84:O84,$D$2:$O$2,$R$3) -> 0
A85: БИ | B85: Полукольцо DT-H4 DHD340 | C85: шт | D85: 0 | E85: 0 | P85: =SUMIFS(D85:O85,$D$2:$O$2,$R$3) -> 0
A86: БИ | B86: Клапан пластиковый DHD 340 | C86: шт | D86: 0 | E86: 0 | P86: =SUMIFS(D86:O86,$D$2:$O$2,$R$3) -> 0
A87: БИ | B87: Скоба П-110-2,8 Ш МХ 61,03 | C87: шт | D87: 0 | E87: 0 | P87: =SUMIFS(D87:O87,$D$2:$O$2,$R$3) -> 0
A88: БИ | B88: Ремкомплект П-110 | C88: шт | D88: 0 | E88: 0 | P88: =SUMIFS(D88:O88,$D$2:$O$2,$R$3) -> 0
A89: БИ | B89: 0 | C89: 0 | D89: 0 | E89: 0 | P89: =SUMIFS(D89:O89,$D$2:$O$2,$R$3) -> 0
A90: БИ | B90: Трубы буровые | P90: =SUMIFS(D90:O90,$D$2:$O$2,$R$3) -> 0
A91: БИ | B91: Труба буровая 89х9х5000 2-3/8 API Reg | C91: шт | D91: 0 | E91: 0 | P91: =SUMIFS(D91:O91,$D$2:$O$2,$R$3) -> 0
A92: БИ | B92: Труба буровая 114х9х6000 2-3/8 API Reg | C92: шт | D92: 0 | E92: 40000 | F92: 40000 | G92: 40000 | H92: 58000 | P92: =SUMIFS(D92:O92,$D$2:$O$2,$R$3) -> 58000 | Q92: штанга
A93: БИ | B93: Труба буровая ТБСУ 63,5х6,0х1500 мм | C93: шт | D93: 0 | E93: 6645.97 | F93: 6645.97 | G93: 6645.97 | H93: 6645.97 | P93: =SUMIFS(D93:O93,$D$2:$O$2,$R$3) -> 6645.97
A94: БИ | B94: Труба буровая ТБСУ 63,5х6,0х3000 мм | C94: шт | D94: 0 | E94: 9975.51 | F94: 9975.51 | G94: 9975.51 | H94: 9975.51 | P94: =SUMIFS(D94:O94,$D$2:$O$2,$R$3) -> 9975.51
A95: БИ | B95: Труба буровая ТБСУ 63,5х6,0х4700 мм | C95: шт | D95: 0 | E95: 12495.11 | F95: 12417 | G95: 12417 | H95: 12417 | P95: =SUMIFS(D95:O95,$D$2:$O$2,$R$3) -> 12417
A96: БИ | B96: Труба буровая ТБСУ 63,5х5,0х1500 мм | C96: шт | D96: 0 | E96: 0 | P96: =SUMIFS(D96:O96,$D$2:$O$2,$R$3) -> 0
A97: БИ | B97: Труба буровая ТБСУ 63,5х5,0х3000 мм | C97: шт | D97: 0 | E97: 0 | P97: =SUMIFS(D97:O97,$D$2:$O$2,$R$3) -> 0
A98: БИ | B98: Труба буровая ТБСУ 63,5х5,0х4700 мм | C98: шт | D98: 0 | E98: 0 | P98: =SUMIFS(D98:O98,$D$2:$O$2,$R$3) -> 0
A99: БИ | B99: Шнек буровой ШБП123-73*6-4300-100 3-50 | C99: шт | D99: 0 | E99: 0 | P99: =SUMIFS(D99:O99,$D$2:$O$2,$R$3) -> 0
A100: БИ | B100: 0 | C100: 0 | D100: 0 | E100: 0 | P100: =SUMIFS(D100:O100,$D$2:$O$2,$R$3) -> 0
A101: БИ | B101: 0 | C101: 0 | D101: 0 | E101: 0 | P101: =SUMIFS(D101:O101,$D$2:$O$2,$R$3) -> 0
A102: БИ | B102: Переводники | P102: =SUMIFS(D102:O102,$D$2:$O$2,$R$3) -> 0
A103: БИ | B103: Переводник З-50/З-88м | C103: шт | D103: 0 | E103: 0 | F103: 5750 | G103: 5750 | H103: 5750 | P103: =SUMIFS(D103:O103,$D$2:$O$2,$R$3) -> 5750
A104: БИ | B104: Переводник З-50/З-66м(2паза) | C104: шт | D104: 0 | E104: 0 | P104: =SUMIFS(D104:O104,$D$2:$O$2,$R$3) -> 0
A105: БИ | B105: Переходник П 3-50/72х10 (2 лыски) | C105: шт | D105: 0 | E105: 0 | P105: =SUMIFS(D105:O105,$D$2:$O$2,$R$3) -> 0
A106: БИ | B106: Переводник З-50/72*10 | C106: шт | D106: 0 | E106: 3851.37 | F106: 3851.37 | G106: 3851.37 | H106: 3851.37 | P106: =SUMIFS(D106:O106,$D$2:$O$2,$R$3) -> 3851.37
A107: БИ | B107: Переход МЗ-50/НСП72*10 | C107: шт | D107: 0 | E107: 0 | P107: =SUMIFS(D107:O107,$D$2:$O$2,$R$3) -> 0
A108: БИ | B108: Переводник З-50м/З-63,5 (2паза) | C108: шт | D108: 0 | E108: 0 | P108: =SUMIFS(D108:O108,$D$2:$O$2,$R$3) -> 0
...

Sheet 5.амортизация новая
A2: Дата актуальности: 28.02.2023
A3: Вид, наименование | B3: Инв.номер | C3: Дата ввода | D3: Перв.стоимость | E3: Остаточная стоимость на 28.02.2023 | F3: СПИ по БУ | G3: Ам норма/мес БУ | H3: СПИ по УУ | I3: Ам норма/мес УУ | J3: Ам норма/1 оп | L3: Откл. БУ-УУ
A4: Приборы | D4: =SUM(D5:D10) -> 1124093.9 | E4: =SUM(E5:E10) -> 866215.35 | G4: =SUM(G5:G10) -> 27528.031 | I4: =SUM(I5:I10) -> 27528.031 | J4: =SUM(J5:J10) -> 1835.2021 | L4: =SUM(L5:L10) -> 0
A5: Устройство УВД-2А (дистанционное) | B5: 30201210 | C5: 01.07.2015 | D5: 93000 | E5: 0 | F5: 36 | G5: 0 | I5: 0 | J5: 0 | L5: =G5-I5 -> 0
A6: Тахограф Атол Drive- (5 СКЗИ (Т)) | B6: 30401207 | C6: 25.03.2015 | D6: 40084.75 | E6: 0 | F6: 36 | G6: 0 | I6: 0 | J6: 0 | L6: =G6-I6 -> 0
A7: Бластер-радиопередатчик HANWНA, модель HEBS-B-2A, сер.№ BAG2200034 | B7: 30201601 | C7: 15.11.2022 | D7: 301066.05 | E7: 263154.01 | F7: =3*12 -> 36 | G7: =D7/F7 -> 8362.9458 | H7: 36 | I7: =D7/H7 -> 8362.9458 | J7: =I7/15 -> 557.52972 | L7: =G7-I7 -> 0
A8: Бластер-радиопередатчик HANWНA, модель HEBS-B-2A, сер.№ BAG2200037 | B8: 30201604 | C8: 15.11.2022 | D8: 301066.07 | E8: 263154.03 | F8: =3*12 -> 36 | G8: =D8/F8 -> 8362.9464 | H8: 36 | I8: =D8/H8 -> 8362.9464 | J8: =I8/15 -> 557.52976 | L8: =G8-I8 -> 0
A9: Логгер (регистратор) - радиопередатчик HANWНA, модель HEBS-L-2A, сер.№ LAG2200009 | B9: 30201610 | C9: 15.11.2022 | D9: 156805.24 | E9: 137059.4 | F9: =3*12 -> 36 | G9: =D9/F9 -> 4355.7011 | H9: 36 | I9: =D9/H9 -> 4355.7011 | J9: =I9/15 -> 290.38007 | L9: =G9-I9 -> 0
A10: Планер устройство сканирующего типа HANWНA, сер.№ S21138522510806 | B10: 30201613 | C10: 15.11.2022 | D10: 232071.77 | E10: 202847.91 | F10: 36 | G10: =D10/F10 -> 6446.4381 | H10: 36 | I10: =D10/H10 -> 6446.4381 | J10: =I10/15 -> 429.76254 | L10: =G10-I10 -> 0
A11: Компьютеры и периферия | D11: =SUM(D12:D18) -> 479115.15 | E11: =SUM(E12:E18) -> 0 | G11: =SUM(G12:G18) -> 0 | I11: =SUM(I12:I18) -> 0 | J11: =SUM(J12:J18) -> 0 | L11: =SUM(L12:L18) -> 0
A12: Монитор Samsung 34" С34F791WQI | B12: 60201314 | C12: 07.02.2019 | D12: 41120.13 | E12: 0 | F12: 36 | G12: 0 | H12: 36 | I12: 0 | J12: 0 | L12: =G12-I12 -> 0
A13: Ноутбук Apple MacBook Pro MPXY2 II Intel Core i5 (3.1GHz) 8192 MB | B13: 60201256 | C13: 01.02.2018 | D13: 121525.42 | E13: 0 | F13: 36 | G13: 0 | H13: 36 | I13: 0 | J13: 0 | L13: =G13-I13 -> 0
A14: Ноутбук Apple MacBook Pro Space Grey 13.3" retina | B14: 60201360 | C14: 08.08.2019 | D14: 131000 | E14: 0 | F14: 36 | G14: 0 | H14: 36 | I14: 0 | J14: 0 | L14: =G14-I14 -> 0
A15: Ноутбук Dell Latitude 3480 14 (1920*1080) Intel Core i5 6200U | B15: 60201276 | C15: 28.02.2018 | D15: 46330.51 | E15: 0 | F15: 36 | G15: 0 | H15: 36 | I15: 0 | J15: 0 | L15: =G15-I15 -> 0
A16: Ноутбук Asus Zenbook UX410UA-GV298R 14" (5) | B16: 60201378 | C16: 11.11.2019 | D16: 54039.51 | E16: 0 | F16: 36 | G16: 0 | H16: 36 | I16: 0 | J16: 0 | L16: =G16-I16 -> 0
A17: Ноутбук Asus Zenbook UX433FA-A5046 | B17: 60201398 | C17: 18.02.2020 | D17: 43875 | E17: 0 | F17: 36 | G17: 0 | H17: 36 | I17: 0 | J17: 0 | L17: =G17-I17 -> 0
A18: Ноутбук Lenova ideaPad 320S-13IKB 81AK001SRK IntelCore | B18: 60201277 | C18: 28.02.2018 | D18: 41224.58 | E18: 0 | F18: 36 | G18: 0 | H18: 36 | I18: 0 | J18: 0 | L18: =G18-I18 -> 0
A19: База и вспомогательное | D19: =SUM(D20:D45) -> 22734085 | E19: =SUM(E20:E45) -> 14983280 | G19: =SUM(G20:G45) -> 147590.72 | I19: =SUM(I20:I45) -> 233099.75 | J19: =SUM(J20:J45) -> 15539.983 | L19: =SUM(L20:L45) -> -85509.024
A20: Земельный участок 59:11:0011118:84 (г. Чусовой, ул. Камгэс, 43-в) | B20: 120000291 | C20: 07.06.2018 | D20: 1522000 | E20: 1522000 | F20: 300 | G20: 0 | H20: 300 | I20: =D20/H20 -> 5073.3333 | J20: =I20/15 -> 338.22222 | L20: =G20-I20 -> -5073.3333 | T20: начисление амортизации условно, для ценообразования
A21: Земельный участок (11897 кв.м.), кад.номер 59:17:4182001:4 | B21: 120001549 | C21: 16.05.2022 | D21: 275091 | E21: 275091 | F21: 300 | G21: 0 | H21: 300 | I21: =D21/H21 -> 916.97 | J21: =I21/15 -> 61.131333 | L21: =G21-I21 -> -916.97 | T21: начисление амортизации условно, для ценообразования
A22: Земельный участок (13303 кв.м.), кад.номер 59:17:4182001:1 | B22: 120001550 | C22: 16.05.2022 | D22: 289656 | E22: 289656 | F22: 300 | G22: 0 | H22: 300 | I22: =D22/H22 -> 965.52 | J22: =I22/15 -> 64.368 | L22: =G22-I22 -> -965.52 | T22: начисление амортизации условно, для ценообразования
A23: Земельный участок (67750 кв.м.), кад.номер 59:17:4182001:2 | B23: 120001551 | C23: 16.05.2022 | D23: 961165.33 | E23: 961165.33 | F23: 300 | G23: 0 | H23: 300 | I23: =D23/H23 -> 3203.8844 | J23: =I23/15 -> 213.5923 | L23: =G23-I23 -> -3203.8844 | T23: начисление амортизации условно, для ценообразования
A24: Автодорога технологическая "завод-склад ВМ" (2500 м), кад.номер 59:17:4182001:22 | B24: 20701580 | C24: 01.09.2022 | D24: 505516.67 | E24: 488759.21 | F24: =15*12+1 -> 181 | G24: =D24/F24 -> 2792.9098 | H24: 181 | I24: =D24/H24 -> 2792.9098 | J24: =I24/15 -> 186.19399 | L24: =G24-I24 -> 0
A25: Нежилое здание (г. Чусовой, ул. Камгэс, 43-в) | B25: 11001290 | C25: 07.06.2018 | D25: 1522000 | E25: 1285751.7 | F25: =30*12+1 -> 361 | G25: =D25/F25 -> 4216.0665 | H25: 300 | I25: =D25/H25 -> 5073.3333 | J25: =I25/15 -> 338.22222 | L25: =G25-I25 -> -857.26685
A26: Котельная №1 (г.Чусовой, ул. Камгэс, 43в, литер А3) | B26: 30601372 | C26: 15.10.2019 | D26: 333102 | E26: 258986.66 | F26: =15*12 -> 180 | G26: 1857.18 | H26: 180 | I26: =D26/H26 -> 1850.5667 | J26: =I26/15 -> 123.37111 | L26: =G26-I26 -> 6.6133333 | T26: не идет,в бу корректировка 1857,18 в мес.
A27: Котельная газовая №2 (г.Чусовой, ул. Камгэс, 43в, литер А3) | B27: 30601625 | C27: 09.12.2022 | D27: 282470.63 | E27: 278167.86 | F27: =15*12 -> 180 | G27: =D27/F27 -> 1569.2813 | H27: 180 | I27: =D27/H27 -> 1569.2813 | J27: =I27/15 -> 104.61875 | L27: =G27-I27 -> 0
A28: Мобильное бытовое помещение 6*2,4*2,4 | B28: 10401542 | C28: 16.05.2022 | D28: 127750 | E28: 113277.58 | F28: =12*7 -> 84 | G28: =D28/F28 -> 1520.8333 | H28: 84 | I28: =D28/H28 -> 1520.8333 | J28: =I28/15 -> 101.38889 | L28: =G28-I28 -> 0
A29: Загрузчик шнековый | B29: 30501251 | C29: 28.09.2017 | D29: 613913.35 | E29: 148391.67 | F29: =12*7+1 -> 85 | G29: 7456.87 | H29: 84 | I29: =D29/H29 -> 7308.4923 | J29: =I29/15 -> 487.23282 | L29: =G29-I29 -> 148.37774 | T29: не идет,в бу корректировка 7456,87 в мес.
A30: Система молниезащиты здания | B30: 30601515 | C30: 28.12.2021 | D30: 102126.07 | E30: 90297.19 | F30: =10*12+1 -> 121 | G30: 844.92 | H30: 300 | I30: =D30/H30 -> 340.42023 | J30: =I30/15 -> 22.694682 | L30: =G30-I30 -> 504.49977 | T30: не идет,в бу корректировка 844,92 в мес.
A31: Контейнер-цистерна модели Т11-254 (зав.номер 010161, сетевой номер OZMU 1110108) | B31: 20501479 | C31: 03.05.2021 | D31: 1725157.3 | E31: 1295492.8 | F31: =7*12+1 -> 85 | G31: 20542.34 | H31: 120 | I31: =D31/H31 -> 14376.311 | J31: =I31/15 -> 958.42074 | L31: =G31-I31 -> 6166.0288 | T31: не идет,в бу корректировка 20542,34 в мес
A32: Контейнер-цистерна TGRU 321008-1, заводской номер Z 2214 | B32: 20501424 | C32: 30.07.2020 | D32: 818579.71 | E32: 519910.83 | F32: =7*12+1 -> 85 | G32: 9639.49 | H32: 60 | I32: =D32/H32 -> 13642.995 | J32: =I32/15 -> 909.53301 | L32: =G32-I32 -> -4003.5052 | T32: не идет,в бу корректировка 9639,49 в мес
A33: Контейнер-цистерна модели Т11-254 (зав.номер 0101185, сетевой номер OZMU 1110113) | B33: 20501478 | C33: 03.05.2021 | D33: 1629332.9 | E33: 1223534.2 | F33: =7*12+1 -> 85 | G33: 19401.31 | H33: 60 | I33: =D33/H33 -> 27155.548 | J33: =I33/15 -> 1810.3699 | L33: =G33-I33 -> -7754.238 | T33: не идет,в бу корректировка 19401,31 в мес
A34: Погрузчик вилочный 4014М | B34: 30501244 | C34: 21.10.2016 | D34: 200000 | E34: 0 | F34: 36 | G34: 0 | H34: 0 | I34: 0 | J34: 0 | L34: =G34-I34 -> 0
A35: Погрузчик телескопический Haulotte HTL 3210 | B35: 70501519 | C35: 28.12.2021 | D35: 5261214.8 | E35: 4492921.7 | F35: =8*12 -> 96 | G35: 54878.08 | H35: 84 | I35: =D35/H35 -> 62633.51 | J35: =I35/15 -> 4175.5673 | L35: =G35-I35 -> -7755.43 | T35: не идет,в бу корректировка 54 878,08 в мес
A36: Ковш двучелюстной для погрузчика Haulotte HTL 3210 | B36: 30501524 | C36: 01.02.2022 | D36: 283178.35 | E36: 239868.72 | F36: =7*12+1 -> 85 | G36: =D36/F36 -> 3331.51 | H36: 84 | I36: =D36/H36 -> 3371.1708 | J36: =I36/15 -> 224.74472 | L36: =G36-I36 -> -39.660833
A37: Полуприцеп-контейнеровоз ТОНАР 974624, VIN XOT974624G0000375 | B37: 70501427 | C37: 30.07.2020 | D37: 634644.94 | E37: 403086.97 | F37: =7*12+1 -> 85 | G37: 7473.5 | H37: 60 | I37: =D37/H37 -> 10577.416 | J37: =I37/15 -> 705.16104 | L37: =G37-I37 -> -3103.9157 | T37: не идет,в бу корректировка 7473,5 в мес
A38: Полуприцеп-контейнеровоз ТОНАР 974624, VIN XOT974624G0000399 | B38: 70501426 | C38: 30.07.2020 | D38: 634644.94 | E38: 403086.97 | F38: =7*12+1 -> 85 | G38: 7473.5 | H38: 60 | I38: =D38/H38 -> 10577.416 | J38: =I38/15 -> 705.16104 | L38: =G38-I38 -> -3103.9157 | T38: не идет,в бу корректировка 7473,5 в мес
A39: Технологический павильон 12*3,5*4,5м | B39: 10401246 | C39: 13.01.2017 | D39: 183584.75 | E39: 0 | F39: 36 | G39: 0 | I39: 0 | J39: 0 | L39: =G39-I39 -> 0
A40: Блиндаж-теплушка | B40: 10401222 | C40: 08.02.2016 | D40: 82160 | E40: 0 | F40: 84 | G40: 0 | I40: 0 | J40: 0 | L40: =G40-I40 -> 0
A41: Склад (контейнерного типа 1СС) | B41: 90601233 | C41: 13.05.2016 | D41: 105932.2 | E41: 35524.21 | F41: =10*12+1 -> 121 | G41: 901.92 | H41: 120 | I41: =D41/H41 -> 882.76833 | J41: =I41/15 -> 58.851222 | L41: =G41-I41 -> 19.151667 | T41: не идет,в бу корректировка 901,92 в мес
A42: Автомобиль бортовой КАМАЗ-43118, доработанный под перевозку опасных грузов | B42: 70401240 | C42: 29.09.2016 | D42: 113433.05 | E42: 0 | F42: =4*12+3*12 -> 84 | G42: 0 | I42: 0 | J42: 0 | L42: =G42-I42 -> 0
A43: Блочная комплексная трансформаторная подстанция (КТП-250/6/0,4) | B43: 30701622 | C43: 12.12.2022 | D43: 668072.99 | E43: 658309.67 | F43: =15*12+1 -> 181 | G43: =D43/F43 -> 3691.011 | H43: 180 | I43: =D43/H43 -> 3711.5166 | J43: =I43/15 -> 247.43444 | L43: =G43-I43 -> -20.505617
A44: Автомобиль Шевроле Нива 0603250 | B44: 70301238 | C44: 07.09.2016 | D44: 526025.43 | E44: 0 | F44: 60 | G44: 0 | I44: 0 | J44: 0 | L44: =G44-I44 -> 0
A45: Легковой автомобиль GWM POER | D45: 3333333 | H45: 60 | I45: =D45/H45 -> 55555.55 | J45: =I45/15 -> 3703.7033 | L45: =G45-I45 -> -55555.55
A46: Буровое оборудование | D46: =SUM(D47:D60) -> 2.3305495e+08 | E46: =SUM(E47:E60) -> 66340734 | G46: =SUM(G47:G60) -> 1108209.5 | I46: =SUM(I47:I60) -> 2504167.1 | J46: =SUM(J47:J60) -> 137252.17 | L46: =SUM(L47:L60) -> -1395957.6
A47: Буровая установка УРБ-2А2 на шасси КамАЗ 43118 ХТС431183С2433891 | B47: 30301241 | C47: 29.09.2016 | D47: 1745758.9 | E47: 32418.35 | F47: =7*12+11 -> 95 | G47: 1807.71 | H47: 84 | I47: =D47/H47 -> 20782.844 | J47: =I47/15 -> 1385.5229 | L47: =G47-I47 -> -18975.134 | T47: не идет,в бу корректировка 1807,71 в мес
A48: Буровая установка УРБ-2А2 на шасси КамАЗ 43118 ХТС431183С2433890 | B48: 30301242 | C48: 29.09.2016 | D48: 1439398.1 | E48: 24440.56 | F48: =7*12+11 -> 95 | G48: 1362.86 | H48: 84 | I48: =D48/H48 -> 17135.691 | J48: =I48/15 -> 1142.3794 | L48: =G48-I48 -> -15772.831 | T48: не идет,в бу корректировка 1362,86 в мес
A49: Буровая установка УРБ-2Д2 с элементами 2Д3 на шасси КАМАЗ-43118 на модернизированной гидравлической | B49: 30301485 | C49: 09.06.2021 | D49: 5324583.3 | E49: 3532617.8 | F49: =5*12 -> 60 | G49: 89964.8 | H49: 84 | I49: =D49/H49 -> 63387.897 | J49: =I49/15 -> 4225.8598 | L49: =G49-I49 -> 26576.903 | T49: не идет,в бу корректировка 89964,8 в мес
A50: Буровая установка УРБ-2А2 на шасси КамАЗ 43118 ХТС431183С2433853 | B50: 30301243 | C50: 29.09.2016 | D50: 500833.9 | E50: 0 | F50: =2*12+3 -> 27 | G50: 0 | I50: 0 | J50: 0 | L50: =G50-I50 -> 0
A51: Самоходная буровая гидравлич.гусенич.установка ТМ-BOHRTECHNIK TM255T-RU | B51: 70301234 | C51: 01.06.2016 | D51: 18220339 | E51: 2945097.9 | F51: =8*12 -> 96 | G51: 196339.86 | H51: 84 | I51: =D51/H51 -> 216908.8 | J51: =I51/15 -> 14460.586 | L51: =G51-I51 -> -20568.937 | T51: не идет,в бу корректировка 196339,86 в мес
A52: Буровая установка Soosan JD-2000 | B52: 70401581 | C52: 13.09.2022 | D52: 34158508 | E52: 31881274 | F52: 84 | G52: =D52/F52 -> 406648.9 | H52: 84 | I52: =D52/H52 -> 406648.9 | J52: =I52/40 -> 10166.223 | L52: =G52-I52 -> 0
A53: Самоходная буровая установка ZEGA D480A (заводской номер BBJ0031) | B53: 30401654 | C53: 21.02.2023 | D53: 25701186 | E53: 25613767 | F53: =7*12 -> 84 | G53: =D53/F53 -> 305966.5 | H53: 84 | I53: =D53/H53 -> 305966.5 | J53: =I53/40 -> 7649.1626 | L53: =G53-I53 -> 0
A54: Компрессор AIRMAN PDS J750S | B54: 30301283 | C54: 16.05.2018 | D54: 2966101.7 | E54: 228967.2 | F54: =7*12+5 -> 89 | G54: 7272.52 | H54: 60 | I54: =D54/H54 -> 49435.028 | J54: =I54/15 -> 3295.6685 | L54: =G54-I54 -> -42162.508 | T54: не идет,в бу корректировка 7 272,52 в мес
A55: Компрессор XAXS277 CD SQE BOX WUX 691358 | B55: 30301383 | C55: 03.12.2019 | D55: 2888333.3 | E55: 1041075.4 | F55: 60 | G55: 49423.18 | H55: 60 | I55: =D55/H55 -> 48138.889 | J55: =I55/15 -> 3209.2593 | L55: =G55-I55 -> 1284.2912 | T55: не идет,в бу корректировка 49423,18 в мес
A56: Компрессор XAXS277 CD SQE BOX WUX 691359 | B56: 30301384 | C56: 03.12.2019 | D56: 2888333.3 | E56: 1041075.4 | F56: 60 | G56: 49423.18 | H56: 60 | I56: =D56/H56 -> 48138.889 | J56: =I56/15 -> 3209.2593 | L56: =G56-I56 -> 1284.2912 | T56: не идет,в бу корректировка 49423,18 в мес
A57: Буровая установка Soosan JD-2000 | D57: 40628166 | H57: 84 | I57: =D57/H57 -> 483668.64 | J57: =I57/15 -> 32244.576 | L57: =G57-I57 -> -483668.64
A58: Гидравлическая буровая установка DEX203 | D58: 41000000 | H58: 84 | I58: =D58/H58 -> 488095.24 | J58: =I58/15 -> 32539.683 | L58: =G58-I58 -> -488095.24
A59: Самоходная буровая установка ZEGA D480A 0031 | D59: 25701186
A60: Самоходная буровая установка ZEGA D480A 0043 | D60: 29892222 | H60: 84 | I60: =D60/H60 -> 355859.79 | J60: =I60/15 -> 23723.986 | L60: =G60-I60 -> -355859.79
A61: МПП | D61: =SUM(D62) -> 41693193 | E61: =SUM(E62) -> 38554996 | G61: =SUM(G62) -> 347443.28 | I61: =SUM(I62) -> 496347.54 | J61: =SUM(J62) -> 1240.8688 | L61: =SUM(L62) -> -148904.26
A62: УМПП НК ЭВВ 5 (ОСП Чусовой) | B62: 30501552 | C62: 44712 | D62: 41693193 | E62: 38554996 | F62: 120 | G62: =D62/F62 -> 347443.28 | H62: 84 | I62: =D62/H62 -> 496347.54 | J62: =I62/400 -> 1240.8688 | L62: =G62-I62 -> -148904.26 | T62: делится на 400
A63: Машины и оборудование | D63: =SUM(D64:D75) -> 66942811 | E63: =SUM(E64:E75) -> 18058955 | G63: =SUM(G64:G75) -> 548213.94 | I63: =SUM(I64:I75) -> 924186.89 | J63: =SUM(J64:J75) -> 61612.459 | L63: =SUM(L64:L75) -> -375972.95
A64: Прицеп самосвал ГКБ-819 | B64: 70501432 | C64: 01.09.2020 | D64: 124000 | E64: 81398.12 | F64: =7*12+1 -> 85 | G64: 1479.97 | H64: 60 | I64: =D64/H64 -> 2066.6667 | J64: =I64/15 -> 137.77778 | L64: =G64-I64 -> -586.69667 | T64: не идет,в бу корректировка 1479,97 в мес
A65: Автомобиль КРАЗ 6510 МЗ ЗБ | B65: 70301235 | C65: 24.06.2016 | D65: 3543643.1 | E65: 944971.5 | F65: =7*12+6 -> 90 | G65: 0 | H65: 60 | I65: =D65/H65 -> 59060.719 | J65: =I65/15 -> 3937.3813 | L65: =G65-I65 -> -59060.719 | T65: не идет,в бу корректировка 0 в мес
A66: СЗМ "ANFO" (на базе IVECO) | B66: 30201131 | C66: 21.12.2009 | D66: 9621615.1 | E66: 320376.56 | F66: =15*12+6 -> 186 | G66: 11588.88 | H66: 60 | I66: =D66/H66 -> 160360.25 | J66: =I66/15 -> 10690.683 | L66: =G66-I66 -> -148771.37 | T66: не идет,в бу корректировка 11588,88 в мес
A67: СЗМ.TDR.PR-12 на базе шасси КАМАЗ (зав.номер 0340621) | B67: 30201484 | C67: 10.06.2021 | D67: 11876847 | E67: 5168252.4 | F67: =3*12 -> 36 | G67: 337794.27 | H67: 84 | I67: =D67/H67 -> 141391.03 | J67: =I67/15 -> 9426.0689 | L67: =G67-I67 -> 196403.24 | T67: не идет,в бу корректировка 337 794,27 в мес
A68: СЗМ.TDR.TTT-15 (заводской номер 0091620) | B68: 30201410 | C68: 06.05.2020 | D68: 7870207.3 | E68: 894649.96 | F68: 60 | G68: 34197.47 | H68: 60 | I68: =D68/H68 -> 131170.12 | J68: =I68/15 -> 8744.6748 | L68: =G68-I68 -> -96972.652 | T68: не идет,в бу корректировка 34 197,47 в мес
A69: Лаборатория специальная взрывчатых веществ ЛУИДОР-2250Е3 | B69: 70401217 | C69: 17.11.2015 | D69: 1031023.3 | E69: 0 | F69: 72 | G69: 0 | I69: 0 | J69: 0 | L69: =G69-I69 -> 0
A70: А/м для перевозки взрывчатых веществ категории EX/II класс опасности 1 на базе шасси ГАЗ-А32R32 | B70: 70401248 | C70: 14.06.2017 | D70: 1489608.2 | E70: 105489.21 | F70: =7*12+1 -> 85 | G70: 6419.22 | H70: 72 | I70: =D70/H70 -> 20689.003 | J70: =I70/15 -> 1379.2669 | L70: =G70-I70 -> -14269.783 | T70: не идет,в бу корректировка 6419,22 в мес
A71: Автомобиль для перевозки опасных грузов 2 класса на базе Ford Transit (VIN X2FXXXESGXMK79701) | B71: 70401529 | C71: 07.02.2022 | D71: 3390350 | E71: 0 | F71: =6*12 -> 72 | G71: 0 | I71: 0 | J71: 0 | L71: =G71-I71 -> 0
A72: Специализированный полуприцеп-контейнеровоз УСТ 946519 (шасси Z0V946519NA000029,VINZ0V946519NA000029 | B72: 70401544 | C72: 23.05.2022 | D72: 2252712.7 | E72: 2003564.8 | F72: 84 | G72: =D72/F72 -> 26818.008 | H72: 60 | I72: =D72/H72 -> 37545.212 | J72: =I72/15 -> 2503.0141 | L72: =G72-I72 -> -10727.203
A73: Специальный седельный тягач с КМУ УСТ 54531U (шасси ХТС652255NR462147, VIN: Z0V54531UN5000560) | B73: 70501545 | C73: 23.05.2022 | D73: 9256917.5 | E73: 8540252.9 | F73: 120 | G73: =D73/F73 -> 77140.979 | H73: 60 | I73: =D73/H73 -> 154281.96 | J73: =I73/15 -> 10285.464 | L73: =G73-I73 -> -77140.979
A74: Специализированный автомобиль для перевозки опасных грузов ГАЗ 5796М1 (VIN ***5212) | B74: 70401684 | C74: 45083 | D74: 4485887 | F74: 85 | G74: =D74/F74 -> 52775.142 | H74: 60 | I74: =D74/H74 -> 74764.784 | J74: =I74/15 -> 4984.3189 | L74: =G74-I74 -> -21989.642
A75: СЗМ.TDR.PR-12 план | D75: 12000000 | H75: 84 | I75: =D75/H75 -> 142857.14 | J75: =I75/15 -> 9523.8095 | L75: =G75-I75 -> -142857.14
A76: ИТОГО | D76: =D63+D61+D46+D19+D11+D4 -> 3.6602825e+08 | E76: =E63+E61+E46+E19+E11+E4 -> 1.3880418e+08 | G76: =G63+G61+G46+G19+G11+G4 -> 2178985.5 | H76: =H63+H61+H46+H19+H11+H4 -> 0 | I76: =I63+I61+I46+I19+I11+I4 -> 4185329.3 | J76: =J63+J61+J46+J19+J11+J4 -> 217480.68 | L76: =L63+L61+L46+L19+L11+L4 -> -2006343.8

Sheet ФОТ
A2: Анализ зарплаты по сотрудникам (в целом за период)
A4: Организация | C4: Урал Поволжье
A5: Период | C5: 2022
A7: Подразделение | C7: Отработано | E7: Всего начислено ФАКТ за 12 месяцев | F7: Всего начислено | G7: НДФЛ
A8: Должность основного сотрудника на конец периода | C8: Дней | D8: Часов
A9: Производственный отдел | C9: 6846 | D9: 60800.6 | E9: 27080657 | F9: 27487926 | G9: 2931085
A10: Аппаратчик приготовления эмульсии | C10: 183 | D10: 1462 | E10: 567507.03 | F10: 569007.03 | G10: 73776
A11: Взрывник | C11: 744 | D11: 6304 | E11: 2759927.8 | F11: 2792927.8 | G11: 357798
A12: Водитель специального автомобиля | C12: 260 | D12: 2238 | E12: 691207.22 | F12: 692707.22 | G12: 89311
A13: Водитель-оператор СЗМ и ЗМ | C13: 608 | D13: 5414.1 | E13: 2390873.9 | F13: 2396873.9 | G13: 308895
A14: Горнорабочий по доставке ВМ | C14: 125 | D14: 1000 | E14: 263650.67 | F14: 267553.19 | G14: 33689
A15: Заместитель начальника производства взрывных работ | C15: 230 | D15: 1834 | E15: 985381.98 | F15: 992381.98 | G15: 128099
A16: Машинист буровой установки | C16: 1028 | D16: 10274 | E16: 5587542.9 | F16: 5632384.2 | G16: 492614
A17: Механик | C17: 232 | D17: 1824 | E17: 1190318 | F17: 1198418 | G17: 157387
A18: Начальник производства буровых работ | C18: 254 | D18: 2025 | E18: 1331820.7 | F18: 1485302.5 | G18: 188958
A19: Начальник производства взрывных работ | C19: 240 | D19: 1912 | E19: 1044049.8 | F19: 1051526.9 | G19: 133906
A20: Оператор самоходной буровой установки | C20: 417 | D20: 4170 | E20: 2525040.1 | F20: 2562074.6 | G20: 240331
... A29: Итого | C29: 6846 | D29: 60800.6 | E29: 27080657 | F29: 27487926 | G29: 2931085
A31: Сводная таблица ао Урал Поволжью за 2022 год
A33: Затратные счета | B33: Должность/профессия | C33: отработано за 12 мес | E33: Заработано за 12 мес | F33: Стоимость часа | G33: Средняя Заработная плата за месяц в сопоставимых цифрах (средняя норма за 2022)
C34: дни | D34: часы | G34: 164.4
A35: 20 | B35: Аппаратчик приготовления эмульсии | C35: =C10 -> 183 | D35: =D10 -> 1462 | E35: 567507.03 | F35: =E35/D35 -> 388.1717 | G35: =F35*$G$34 -> 63815.428
A36: 20 | B36: Взрывник | C36: =C11 -> 744 | D36: =D11 -> 6304 | E36: 2759927.8 | F36: =E36/D36 -> 437.8058 | G36: =F36*$G$34 -> 71975.273
A37: 25 | B37: Водитель специального автомобиля | C37: =C12 -> 260 | D37: =D12 -> 2238 | E37: 691207.22 | F37: =E37/D37 -> 308.85041 | G37: =F37*$G$34 -> 50775.008
A38: 20 | B38: Водитель-оператор СЗМ и ЗМ | C38: =C13 -> 608 | D38: =D13 -> 5414.1 | E38: 2390873.9 | F38: =E38/D38 -> 441.60136 | G38: =F38*$G$34 -> 72599.263
A39: 20 | B39: Горнорабочий по доставке ВМ | C39: =C14 -> 125 | D39: =D14 -> 1000 | E39: 263650.67 | F39: =E39/D39 -> 263.65067 | G39: =F39*$G$34 -> 43344.17
A40: 25 | B40: Заместитель начальника производства взрывных работ | C40: =C15 -> 230 | D40: =D15 -> 1834 | E40: 985381.98 | F40: =E40/D40 -> 537.2857 | G40: =F40*$G$34 -> 88329.77
A41: 20 | B41: Машинист буровой установки | C41: =C16 -> 1028 | D41: =D16 -> 10274 | E41: 5587542.9 | F41: =E41/D41 -> 543.85273 | G41: =F41*$G$34 -> 89409.388
A42: 25 | B42: Механик | C42: =C17 -> 232 | D42: =D17 -> 1824 | E42: 1190318 | F42: =E42/D42 -> 652.58662 | G42: =F42*$G$34 -> 107285.24
A43: 25 | B43: Начальник производства буровых работ | C43: =C18 -> 254 | D43: =D18 -> 2025 | E43: 1331820.7 | F43: =E43/D43 -> 657.68925 | G43: =F43*$G$34 -> 108124.11
A44: 25 | B44: Начальник производства взрывных работ | C44: =C19 -> 240 | D44: =D19 -> 1912 | E44: 1044049.8 | F44: =E44/D44 -> 546.05114 | G44: =F44*$G$34 -> 89770.807
A45: 20 | B45: Оператор самоходной буровой установки | C45: =C20 -> 417 | D45: =D20 -> 4170 | E45: 2525040.1 | F45: =E45/D45 -> 605.52521 | G45: =F45*$G$34 -> 99548.344
A46: 20 | B46: Помощник машиниста буровой установки | C46: =C21 -> 1125 | D46: =D21 -> 11244 | E46: 4937238.7 | F46: =E46/D46 -> 439.09985 | G46: =F46*$G$34 -> 72188.016
A47: 25 | B47: Помощник оператора самоходной буровой установки | C47: =C22 -> 113 | D47: =D22 -> 1130 | E47: 480109.57 | F47: =E47/D47 -> 424.87573 | G47: =F47*$G$34 -> 69849.569
A48: 25 | B48: Слесарь по ремонту оборудования | C48: =C24 -> 17 | D48: =D24 -> 136 | E48: 44700.59 | F48: =E48/D48 -> 328.68081 | G48: =F48*$G$34 -> 54035.125
A49: 25 | B49: Специалист производственного отдела | C49: =C25 -> 228 | D49: =D25 -> 1819 | E49: 639430.28 | F49: =E49/D49 -> 351.52847 | G49: =F49*$G$34 -> 57791.28
A50: 25 | B50: Электромеханик | C50: =C27 -> 228 | D50: =D27 -> 1137 | E50: 450465.21 | F50: =E50/D50 -> 396.18752 | G50: =F50*$G$34 -> 65133.228

Sheet Лист1
A1: 13884
A2: 18200
A3: 21635
A4: 18493
A5: 30355
A6: 37956
A7: 20871
A8: 25967
A9: 20224
A10: 55857
A11: 72662
A12: 70872
... A14: 75069
A15: объем | B15: усл | C15: мат | D15: всего
A16: =SUM(A1:A15) -> 527344 | B16: 318105.91 | C16: 806925 | D16: =B16+C16 -> 1125030.9
B17: =B16/A16 -> 0.60322277 | C17: =C16/A16 -> 1.5301682 | D17: =D16/A16 -> 2.1333909
B18: =B17*25000 -> 15080.569 | C18: =C17*25000 -> 38254.204 | D18: =D17*25000 -> 53334.773
A20: спецодежда | B20: 138000
B21: =B20/A16*25000 -> 6542.2191

Sheet Амортизация ОС
A1: № п/п | B1: Наименование ОС | C1: Марка | D1: Дата ввода | E1: Перв.стоимость | F1: Остаточная стоимость | G1: СПИ по БУ | H1: Ам норма/мес БУ | I1: А/м норма в смену | J1: Ам норма/мес УУ | K1: Ам норма/1 оп
A2: 1 | B2: Машина смесительно-зарядная | C2: Inteo EM-VR-12 | D2: 46113 | F2: 21000000 | G2: 84 | H2: =F2/G2 -> 250000 | I2: =H2/20 -> 12500
A3: 2 | B3: Автомобиль легковой специализироованный для перевозки ВМ | C3: Sollers Atlant L3H2 | D3: 46113 | F3: 4100000 | G3: 84 | H3: =F3/G3 -> 48809.524 | I3: =H3/20 -> 2440.4762
A4: 3 | B4: Установка буровая самоходная | C4: JK 830-2 | D4: 46113 | F4: 30000000 | G4: 84 | H4: =F4/G4 -> 357142.86 | I4: =H4/20 -> 17857.143
A5: 4
A6: 5
A7: 6
A8: 7
A9: 8
A10: 9
A11: 10
A12: 11
A13: 12
A14: 13
A15: 14
A16: 15
... A41: 40

Sheet 5.зп
A1: Средняя заработная плата за 5 месцев (с Января по Май 2022) Урал Поволжье
B2: Должность основного сотрудника на конец периода | H2: Сумма | I2: 153 | J2: ч. | K2: смена,ч. | L2: смена, руб. | N2: 153 ч. | O2: среднее количество часов в месяц по производственному календарю с янв.-май 2022 г.
A3: 1 | B3: Взрывник | H3: 58690.645 | I3: =H3/$I$2 -> 383.59899 | K3: 8 | L3: =I3*K3 -> 3068.7919
A4: 2 | B4: Водитель-оператор СЗМ и ЗМ | H4: 69010.376 | I4: =H4/$I$2 -> 451.04821 | K4: 8 | L4: =I4*K4 -> 3608.3857
A5: 3 | B5: Машинист буровой установки | H5: 83517.211 | I5: =H5/$I$2 -> 545.86413 | K5: 11 | L5: =I5*K5 -> 6004.5054
A6: 4 | B6: Начальник производства буровых работ | H6: 97614.406 | I6: =H6/$I$2 -> 638.00265 | K6: 8 | L6: =I6*K6 -> 5104.0212
A7: 5 | B7: Начальник производства взрывных работ | H7: 72580.365 | I7: =H7/$I$2 -> 474.38147 | K7: 8 | L7: =I7*K7 -> 3795.0518
A8: 6 | B8: Помощник машиниста буровой установки | H8: 66723.17 | I8: =H8/$I$2 -> 436.09915 | K8: 11 | L8: =I8*K8 -> 4797.0906
A9: 7 | B9: Заведующий складом взрывчатых материалов | H9: 34565.5 | I9: =H9/$I$2 -> 225.9183 | K9: 8 | L9: =I9*K9 -> 1807.3464
